Workbook
Name CGI: 'Cálculos_CGI e Fin'!$P$21
Name Data_de_Nasc: [1]Capa!$P$6
Name DFI: 'Cálculos_CGI e Fin'!$J$33
Name FIN: 'Cálculos_CGI e Fin'!$P$22
Name FIN_TCC: 'Cálculos_CGI e Fin'!$P$25
Name LTV: 'Cálculos_CGI e Fin'!$I$6
Name mensagem: [1]Capa!#REF!
Name mensagem: [1]Capa!#REF!
Name mensagem: [1]Capa!#REF!
Name MIP: 'Cálculos_CGI e Fin'!$J$32
Name obs: 'Cálculos_CGI e Fin'!$K$30
Name PRAZO: 'Cálculos_CGI e Fin'!$J$6
Name PRICE_POS: 'Cálculos_CGI e Fin'!$P$19
Name PRICE_PRE: 'Cálculos_CGI e Fin'!$P$17
Name PRODUTO: 'Cálculos_CGI e Fin'!$D$3
Name SAC_POS: 'Cálculos_CGI e Fin'!$P$20
Name SAC_PRE: 'Cálculos_CGI e Fin'!$P$18
Name SISTEMA_AMORTIZAÇÃO: 'Cálculos_CGI e Fin'!$K$6
Name TAXA: 'Cálculos_CGI e Fin'!$J$22
Name TCC: 'Cálculos_CGI e Fin'!$P$23
Name TIPO_IMÓVEL: 'Cálculos_CGI e Fin'!$I$3
Name VALOR_CREDITO_BRUTO: 'Cálculos_CGI e Fin'!$D$6
Name VALOR_ESTIMADO_IMÓVEL: 'Cálculos_CGI e Fin'!$G$6

Sheet Cálculos_CGI - SAC FIXA
C2: Produto | H2: Tipo Imóvel
C3: Crédito Com Garantia de Imóvel - CGI | H3: Apartamento
C5: Valor do Crédito Bruto | F5: Valor Estimado do Imóvel | H5: LTV | I5: Prazo | J5: Sistema Amortização
C6: 200000 | F6: 500000 | H6: =IFERROR(C6/F6,"") -> 0.4 | I6: 360 | J6: PRICE - FIXA
C8: Cliente | H8: Nascimento | J8: Renda Familiar Min.
C9: < Insira dados do cleinte mais velho> | H9: =T39 -> 29586 | J9: =ROUNDUP(J44/36%,-2) -> 7800
C12: Valores da Operação - Aproximados | J12: %
C13: Valor Principal do Crédito | I13: =C6 -> 200000 | J13: ---
C14: Valor Estimado do Valor do Imóvel | I14: =F6 -> 500000
C15: Valor Total das Despesas acessórias | I15: 3000 | J15: =I15/I13 -> 0.015
C16: Valor Total do IOF no ato da liberação do Crédito (Sem IOF para operaçõees contratadas até Outubro de 2020) | I16: =IF(TODAY()<=1/10/2020,Q39,"0,00") -> 0,00 | J16: =I16/I13 -> 0
C17: Valor Liquido a ser Liberado ao Emitente ou Vendedor | I17: =I13-I15-I16 -> 197000 | J17: =I17/I13 -> 0.985
C18: Prazo da Operação | I18: =I6 -> 360
C19: Taxa Efetiva - Anual | I19: =EFFECT(I21,(I18/12)) -> 0.13941581
C20: Taxa Efetiva - Mensal | I20: =IF(H6<=49.99%,1.09%,1.29%) -> 0.0109
C21: Taxa Nominal - Anual | I21: =I22*12 -> 0.1308
C22: Taxa Nominal - Mensal | I22: =I20 -> 0.0109
C23: Sistema de Amortização | I23: =J6 -> PRICE - FIXA | AR23: SISTEMA | AS23: PRÉ | AT23: PÓS
C24: Data de Vencimento da Primeira Prestação | I24: =TODAY() -> 46058 | AR24: PRICE
C25: Data de Vencimento da Última Prestação | I25: =VLOOKUP(I18,A36:B426,2,0) -> 57015 | AR25: SAC
C26: Valor da Prestação (Amortização + Juros) | I26: =$G$44 -> 2735.5556 | Z26: Controles de despesas
C27: Valor do Prêmio de Seguro MIP (Morte e Invalidez Permanente) | I27: =$H$44 -> 46 | J27: 0.00023 | Z27: TRUE
C28: Valor do Prêmio de Seguro DFI (Danos Físicos ao Imóvel) | I28: =$I$44 -> 20 | J28: 4e-05 | Z28: TRUE
C29: Valor Total da Prestação mensal | I29: =I26+I27+I28 -> 2801.5556 | Z29: TRUE
C30: CET - Custo Efetitvo Total | I30: =EFFECT(RATE(I18,((I26+I27+I28)*-1),I13,,)*12,(240/12)) -> 0.1808534
Z32: 3 | AA32: Parcelas
Z33: 2 | AA33: Amortização
Z35: 1 | AA35: Saldo
N36: Formulas de Cálculo IOF | T36: Formulas de Cálculo Idade | AA36: 3 | AB36: =IF(AA36=1,"Evolução Saldo SAC x Price",IF(AA36=2,"Evolução Amortização SAC x Price","Evolução Parcelas SAC x Price")) -> Evolução Parcelas SAC x Price | AC36: =VLOOKUP(AA36,Z32:AA35,2,0) -> Parcelas | AO36: Amortização da View
AO37: N° Parc. | AP37: Tipo | AQ37: Vencimento | AR37: Sdo. Principal | AS37: Principal | AT37: IOF | AU37: Juros | AV37: Seguro | AW37: Parcela Total
O38: Calculo IOF | S38: Part | T38: Faixa Idade | U38: Idade | V38: Alicota | W38: DFI | X38: % de Comp. Renda | AA38: Parc | AB38: =IF($AA$36=1,VLOOKUP(AA38,$AE$38:$AK$218,6,0),IF($AA$36=2,VLOOKUP(AA38,$AE$38:$AK$218,4,0),VLOOKUP(AA38,$AE$38:$AK$218,2,0))) -> Parcela PRICE | AC38: =IF($AA$36=1,VLOOKUP(AA38,$AE$38:$AK$218,7,0),IF($AA$36=2,VLOOKUP(AA38,$AE$38:$AK$218,5,0),VLOOKUP(AA38,$AE$38:$AK$218,3,0))) -> Parcela SAC | AE38: Parc | AF38: Parcela PRICE | AG38: Parcela SAC | AH38: Amort. PRICE | AI38: Amort. SAC | AJ38: Saldo PRICE | AK38: Saldo SAC | AN38: =AR39-K44 -> 50399.576 | AO38: 1 | AP38: JP | AQ38: 44078 | AR38: 250000 | AS38: 155.98 | AT38: 0 | AU38: 3225 | AV38: 77.5 | AW38: 3458.48
N39: Acima de 12meses | O39: 0.03 | P39: =SUM(O56:O251) -> 3266.6667 | Q39: =SUM(P39:P41) -> 4173.0567 | S39: 1° Part | T39: =[1]Capa!P6 -> 29586 | U39: =IF($T$39="","",INT((TODAY())-$T$39)/365.25) -> 45.097878 | V39: =IF(AND(U39>=S48,U39<S49),U48,IF(AND(U39>=S49,U39<S50),U49,IF(AND(U39>=S50,U39<S51),U50,IF(AND(U39>=S51,U39<S52),U51,IF(AND(U39>=S52,U39<S53),U52,IF(AND(U39>=S53,U39<S54),U53,IF(AND(U39>=S54,U39<S55),U54,IF(AND(U39>=S55,U39<S56),U55,IF(AND(U39>=S56,U39<T56),U56,""))))))))) -> 0.00023 | W39: 4e-05 | AA39: =A44 -> 1 | AB39: =IF($AA$36=1,VLOOKUP(AA39,$AE$38:$AK$218,6,0),IF($AA$36=2,VLOOKUP(AA39,$AE$38:$AK$218,4,0),VLOOKUP(AA39,$AE$38:$AK$218,2,0))) -> 16352.11 | AC39: =IF($AA$36=1,VLOOKUP(AA39,$AE$38:$AK$278,7,0),IF($AA$36=2,VLOOKUP(AA39,$AE$38:$AK$278,5,0),VLOOKUP(AA39,$AE$38:$AK$278,3,0))) -> 2801.5556 | AE39: =AA39 -> 1 | AF39: =IFERROR(VLOOKUP(AE39,[1]Cálculos_PRICE!$A$32:$K$212,10,0),"") -> 16352.11 | AG39: =IFERROR(VLOOKUP(AE39,'Cálculos_CGI - SAC FIXA'!A37:K429,10,0),"") -> 2801.5556 | AH39: =IFERROR(VLOOKUP(AE39,[1]Cálculos_PRICE!$A$32:$K$212,6,0),"") -> 1104.2104 | AI39: =IFERROR(VLOOKUP(AE39,'Cálculos_CGI - SAC FIXA'!A37:K429,6,0),"") -> 555.55556 | AJ39: =IFERROR(VLOOKUP(AE39,[1]Cálculos_PRICE!$A$32:$K$240,11,0),"") -> 998895.79 | AK39: =IFERROR(VLOOKUP(AE39,'Cálculos_CGI - SAC FIXA'!A37:K429,11,0),"") -> 199444.44 | AN39: =AR40-K45 -> 50797.141 | AO39: 2 | AP39: JP | AQ39: 44108 | AR39: 249844.02 | AS39: 157.99 | AT39: 0 | AU39: 3222.99 | AV39: 77.46 | AW39: 3458.44
N40: Valor Financiado | O40: 0.0038 | P40: =ROUNDUP(O40*$C$43,2) -> 760 | S40: 2° Part | AA40: =A45 -> 2 | AB40: =IF($AA$36=1,VLOOKUP(AA40,$AE$38:$AK$218,6,0),IF($AA$36=2,VLOOKUP(AA40,$AE$38:$AK$218,4,0),VLOOKUP(AA40,$AE$38:$AK$218,2,0))) -> 16351.865 | AC40: =IF($AA$36=1,VLOOKUP(AA40,$AE$38:$AK$278,7,0),IF($AA$36=2,VLOOKUP(AA40,$AE$38:$AK$278,5,0),VLOOKUP(AA40,$AE$38:$AK$278,3,0))) -> 2290.7842 | AE40: =AA40 -> 2 | AF40: =IFERROR(VLOOKUP(AE40,[1]Cálculos_PRICE!$A$32:$K$212,10,0),"") -> 16351.865 | AG40: =IFERROR(VLOOKUP(AE40,'Cálculos_CGI - SAC FIXA'!A38:K430,10,0),"") -> 2290.7842 | AH40: =IFERROR(VLOOKUP(AE40,[1]Cálculos_PRICE!$A$32:$K$212,6,0),"") -> 1120.7736 | AI40: =IFERROR(VLOOKUP(AE40,'Cálculos_CGI - SAC FIXA'!A38:K430,6,0),"") -> 555.55556 | AJ40: =IFERROR(VLOOKUP(AE40,[1]Cálculos_PRICE!$A$32:$K$240,11,0),"") -> 997775.02 | AK40: =IFERROR(VLOOKUP(AE40,'Cálculos_CGI - SAC FIXA'!A38:K430,11,0),"") -> 198888.89 | AN40: =AR41-K46 -> 51192.667 | AO40: 3 | AP40: JP | AQ40: 44139 | AR40: 249686.03 | AS40: 160.03 | AT40: 0 | AU40: 3220.95 | AV40: 77.43 | AW40: 3458.41
N41: Até 12 meses | O41: 0.0001118 | P41: =SUM(O44:O55) -> 146.39 | S41: 3° Part | AA41: =A46 -> 3 | AB41: =IF($AA$36=1,VLOOKUP(AA41,$AE$38:$AK$218,6,0),IF($AA$36=2,VLOOKUP(AA41,$AE$38:$AK$218,4,0),VLOOKUP(AA41,$AE$38:$AK$218,2,0))) -> 16351.616 | AC41: =IF($AA$36=1,VLOOKUP(AA41,$AE$38:$AK$278,7,0),IF($AA$36=2,VLOOKUP(AA41,$AE$38:$AK$278,5,0),VLOOKUP(AA41,$AE$38:$AK$278,3,0))) -> 2290.6564 | AE41: =AA41 -> 3 | AF41: =IFERROR(VLOOKUP(AE41,[1]Cálculos_PRICE!$A$32:$K$212,10,0),"") -> 16351.616 | AG41: =IFERROR(VLOOKUP(AE41,'Cálculos_CGI - SAC FIXA'!A39:K431,10,0),"") -> 2290.6564 | AH41: =IFERROR(VLOOKUP(AE41,[1]Cálculos_PRICE!$A$32:$K$212,6,0),"") -> 1137.5852 | AI41: =IFERROR(VLOOKUP(AE41,'Cálculos_CGI - SAC FIXA'!A39:K431,6,0),"") -> 555.55556 | AJ41: =IFERROR(VLOOKUP(AE41,[1]Cálculos_PRICE!$A$32:$K$240,11,0),"") -> 996637.43 | AK41: =IFERROR(VLOOKUP(AE41,'Cálculos_CGI - SAC FIXA'!A39:K431,11,0),"") -> 198333.33 | AN41: =AR42-K47 -> 51586.132 | AO41: 4 | AP41: JP | AQ41: 44169 | AR41: 249526 | AS41: 162.09 | AT41: 0 | AU41: 3218.89 | AV41: 77.39 | AW41: 3458.37
A42: Parc | B42: Vencimento | C42: Saldo Inicial | D42: Juros | E42: Saldo Atualizado | F42: Amortização | G42: Prestação Mensal | H42: MIP | I42: DFI | J42: Prestação Mensal Total | K42: Saldo Devedor | O42: IOF DIÁRIO | P42: DIAS | Q42: DIAS_SOMA | S42: 4° Part | AA42: =A47 -> 4 | AB42: =IF($AA$36=1,VLOOKUP(AA42,$AE$38:$AK$218,6,0),IF($AA$36=2,VLOOKUP(AA42,$AE$38:$AK$218,4,0),VLOOKUP(AA42,$AE$38:$AK$218,2,0))) -> 16351.363 | AC42: =IF($AA$36=1,VLOOKUP(AA42,$AE$38:$AK$278,7,0),IF($AA$36=2,VLOOKUP(AA42,$AE$38:$AK$278,5,0),VLOOKUP(AA42,$AE$38:$AK$278,3,0))) -> 2290.5286 | AE42: =AA42 -> 4 | AF42: =IFERROR(VLOOKUP(AE42,[1]Cálculos_PRICE!$A$32:$K$212,10,0),"") -> 16351.363 | AG42: =IFERROR(VLOOKUP(AE42,'Cálculos_CGI - SAC FIXA'!A40:K432,10,0),"") -> 2290.5286 | AH42: =IFERROR(VLOOKUP(AE42,[1]Cálculos_PRICE!$A$32:$K$212,6,0),"") -> 1154.6489 | AI42: =IFERROR(VLOOKUP(AE42,'Cálculos_CGI - SAC FIXA'!A40:K432,6,0),"") -> 555.55556 | AJ42: =IFERROR(VLOOKUP(AE42,[1]Cálculos_PRICE!$A$32:$K$240,11,0),"") -> 995482.78 | AK42: =IFERROR(VLOOKUP(AE42,'Cálculos_CGI - SAC FIXA'!A40:K432,11,0),"") -> 197777.78 | AN42: =AR43-K48 -> 51977.498 | AO42: 5 | AP42: JP | AQ42: 44200 | AR42: 249363.91 | AS42: 164.19 | AT42: 0 | AU42: 3216.79 | AV42: 77.35 | AW42: 3458.33
A43: 0 | B43: =I24 -> 46058 | C43: =I13 -> 200000 | J43: =I17*-1 -> -197000 | K43: =C43 -> 200000 | S43: 5° Part | AA43: =A48 -> 5 | AB43: =IF($AA$36=1,VLOOKUP(AA43,$AE$38:$AK$218,6,0),IF($AA$36=2,VLOOKUP(AA43,$AE$38:$AK$218,4,0),VLOOKUP(AA43,$AE$38:$AK$218,2,0))) -> 16351.106 | AC43: =IF($AA$36=1,VLOOKUP(AA43,$AE$38:$AK$278,7,0),IF($AA$36=2,VLOOKUP(AA43,$AE$38:$AK$278,5,0),VLOOKUP(AA43,$AE$38:$AK$278,3,0))) -> 2290.4009 | AE43: =AA43 -> 5 | AF43: =IFERROR(VLOOKUP(AE43,[1]Cálculos_PRICE!$A$32:$K$212,10,0),"") -> 16351.106 | AG43: =IFERROR(VLOOKUP(AE43,'Cálculos_CGI - SAC FIXA'!A41:K433,10,0),"") -> 2290.4009 | AH43: =IFERROR(VLOOKUP(AE43,[1]Cálculos_PRICE!$A$32:$K$212,6,0),"") -> 1171.9687 | AI43: =IFERROR(VLOOKUP(AE43,'Cálculos_CGI - SAC FIXA'!A41:K433,6,0),"") -> 555.55556 | AJ43: =IFERROR(VLOOKUP(AE43,[1]Cálculos_PRICE!$A$32:$K$240,11,0),"") -> 994310.81 | AK43: =IFERROR(VLOOKUP(AE43,'Cálculos_CGI - SAC FIXA'!A41:K433,11,0),"") -> 197222.22 | AN43: =AR44-K49 -> 52366.753 | AO43: 6 | AP43: JP | AQ43: 44231 | AR43: 249199.72 | AS43: 166.3 | AT43: 0 | AU43: 3214.68 | AV43: 77.32 | AW43: 3458.3
A44: =IF(AND(A43=0,A43<$I$18),A43+1,0) -> 1 | B44: =IFERROR(IF(A44<=$I$18,DATE(YEAR(B43),MONTH(B43)+1,DAY(B43)),"-"),"") -> 46086 | C44: =IF(A44="","",K43) -> 200000 | D44: =C44*$I$20 -> 2180 | E44: =IFERROR(C44+D44,"") -> 202180 | F44: =$I$13/$I$18 -> 555.55556 | G44: =F44+D44 -> 2735.5556 | H44: =C44*$J$27 -> 46 | I44: =IF(A44="","",IF(K43="","",IF(K43=0,"",$J$28*$I$14))) -> 20 | J44: =IFERROR(SUM(I44+H44+G44),"") -> 2801.5556 | K44: =C44-F44 -> 199444.44 | O44: =ROUNDUP(F44*$O$41*Q44,2) -> 1.74 | P44: =IF($A44<=$I$18,B44-B43,) -> 28 | Q44: =IF($A44<=$I$18,$B44-$B$43,) -> 28 | S44: 6° Part | AA44: =A49 -> 6 | AB44: =IF($AA$36=1,VLOOKUP(AA44,$AE$38:$AK$218,6,0),IF($AA$36=2,VLOOKUP(AA44,$AE$38:$AK$218,4,0),VLOOKUP(AA44,$AE$38:$AK$218,2,0))) -> 16350.845 | AC44: =IF($AA$36=1,VLOOKUP(AA44,$AE$38:$AK$278,7,0),IF($AA$36=2,VLOOKUP(AA44,$AE$38:$AK$278,5,0),VLOOKUP(AA44,$AE$38:$AK$278,3,0))) -> 2290.2731 | AE44: =AA44 -> 6 | AF44: =IFERROR(VLOOKUP(AE44,[1]Cálculos_PRICE!$A$32:$K$212,10,0),"") -> 16350.845 | AG44: =IFERROR(VLOOKUP(AE44,'Cálculos_CGI - SAC FIXA'!A42:K434,10,0),"") -> 2290.2731 | AH44: =IFERROR(VLOOKUP(AE44,[1]Cálculos_PRICE!$A$32:$K$212,6,0),"") -> 1189.5482 | AI44: =IFERROR(VLOOKUP(AE44,'Cálculos_CGI - SAC FIXA'!A42:K434,6,0),"") -> 555.55556 | AJ44: =IFERROR(VLOOKUP(AE44,[1]Cálculos_PRICE!$A$32:$K$240,11,0),"") -> 993121.27 | AK44: =IFERROR(VLOOKUP(AE44,'Cálculos_CGI - SAC FIXA'!A42:K434,11,0),"") -> 196666.67 | AN44: =AR45-K50 -> 52753.859 | AO44: 7 | AP44: JP | AQ44: 44259 | AR44: 249033.42 | AS44: 168.45 | AT44: 0 | AU44: 3212.53 | AV44: 77.28 | AW44: 3458.26
A45: =IF(IF(AND(A44>0,A44<$I$18),A44+1,0)=0,"",IF(AND(A44>0,A44<$I$18),A44+1,0)) -> 2 | B45: =IFERROR(IF(A45<=$I$18,DATE(YEAR($B$44),MONTH($B$44)+A44,DAY($B$44)),"-"),"") -> 46117 | C45: =IF(A45="","",K44) -> 199444.44 | D45: =C45*$I$20 -> 2173.9444 | E45: =IFERROR(C45+D45,"") -> 201618.39 | F45: =$I$13/$I$18 -> 555.55556 | G45: =IF(A45="","",PMT($I$20,$I$18,$C$44)*-1) -> 2224.912 | H45: =C45*$J$27 -> 45.872222 | I45: =IF(A45="","",IF(K44="","",IF(K44=0,"",$J$28*$I$14))) -> 20 | J45: =IFERROR(SUM(I45+H45+G45),"") -> 2290.7842 | K45: =C45-F45 -> 198888.89 | O45: =ROUNDUP(F45*$O$41*Q45,2) -> 3.67 | P45: =IF($A45<=$I$18,B45-B44,) -> 31 | Q45: =IF($A45<=$I$18,$B45-$B$43,) -> 59 | S45: 7° Part | AA45: =A50 -> 7 | AB45: =IF($AA$36=1,VLOOKUP(AA45,$AE$38:$AK$218,6,0),IF($AA$36=2,VLOOKUP(AA45,$AE$38:$AK$218,4,0),VLOOKUP(AA45,$AE$38:$AK$218,2,0))) -> 16350.581 | AC45: =IF($AA$36=1,VLOOKUP(AA45,$AE$38:$AK$278,7,0),IF($AA$36=2,VLOOKUP(AA45,$AE$38:$AK$278,5,0),VLOOKUP(AA45,$AE$38:$AK$278,3,0))) -> 2290.1453 | AE45: =AA45 -> 7 | AF45: =IFERROR(VLOOKUP(AE45,[1]Cálculos_PRICE!$A$32:$K$212,10,0),"") -> 16350.581 | AG45: =IFERROR(VLOOKUP(AE45,'Cálculos_CGI - SAC FIXA'!A43:K435,10,0),"") -> 2290.1453 | AH45: =IFERROR(VLOOKUP(AE45,[1]Cálculos_PRICE!$A$32:$K$212,6,0),"") -> 1207.3914 | AI45: =IFERROR(VLOOKUP(AE45,'Cálculos_CGI - SAC FIXA'!A43:K435,6,0),"") -> 555.55556 | AJ45: =IFERROR(VLOOKUP(AE45,[1]Cálculos_PRICE!$A$32:$K$240,11,0),"") -> 991913.87 | AK45: =IFERROR(VLOOKUP(AE45,'Cálculos_CGI - SAC FIXA'!A43:K435,11,0),"") -> 196111.11 | AN45: =AR46-K51 -> 53138.794 | AO45: 8 | AP45: JP | AQ45: 44290 | AR45: 248864.97 | AS45: 170.62 | AT45: 0 | AU45: 3210.36 | AV45: 77.24 | AW45: 3458.22
A46: =IF(IF(AND(A45>0,A45<$I$18),A45+1,0)=0,"",IF(AND(A45>0,A45<$I$18),A45+1,0)) -> 3 | B46: =IFERROR(IF(A46<=$I$18,DATE(YEAR($B$44),MONTH($B$44)+A45,DAY($B$44)),"-"),"") -> 46147 | C46: =IF(A46="","",K45) -> 198888.89 | D46: =C46*$I$20 -> 2167.8889 | E46: =IFERROR(C46+D46,"") -> 201056.78 | F46: =$I$13/$I$18 -> 555.55556 | G46: =IF(A46="","",PMT($I$20,$I$18,$C$44)*-1) -> 2224.912 | H46: =C46*$J$27 -> 45.744444 | I46: =IF(A46="","",IF(K45="","",IF(K45=0,"",$J$28*$I$14))) -> 20 | J46: =IFERROR(SUM(I46+H46+G46),"") -> 2290.6564 | K46: =C46-F46 -> 198333.33 | O46: =ROUNDUP(F46*$O$41*Q46,2) -> 5.53 | P46: =IF($A46<=$I$18,B46-B45,) -> 30 | Q46: =IF($A46<=$I$18,$B46-$B$43,) -> 89 | S46: 8° Part | AA46: =A51 -> 8 | AB46: =IF($AA$36=1,VLOOKUP(AA46,$AE$38:$AK$218,6,0),IF($AA$36=2,VLOOKUP(AA46,$AE$38:$AK$218,4,0),VLOOKUP(AA46,$AE$38:$AK$218,2,0))) -> 16350.312 | AC46: =IF($AA$36=1,VLOOKUP(AA46,$AE$38:$AK$278,7,0),IF($AA$36=2,VLOOKUP(AA46,$AE$38:$AK$278,5,0),VLOOKUP(AA46,$AE$38:$AK$278,3,0))) -> 2290.0175 | AE46: =AA46 -> 8 | AF46: =IFERROR(VLOOKUP(AE46,[1]Cálculos_PRICE!$A$32:$K$212,10,0),"") -> 16350.312 | AG46: =IFERROR(VLOOKUP(AE46,'Cálculos_CGI - SAC FIXA'!A44:K436,10,0),"") -> 2290.0175 | AH46: =IFERROR(VLOOKUP(AE46,[1]Cálculos_PRICE!$A$32:$K$212,6,0),"") -> 1225.5023 | AI46: =IFERROR(VLOOKUP(AE46,'Cálculos_CGI - SAC FIXA'!A44:K436,6,0),"") -> 555.55556 | AJ46: =IFERROR(VLOOKUP(AE46,[1]Cálculos_PRICE!$A$32:$K$240,11,0),"") -> 990688.37 | AK46: =IFERROR(VLOOKUP(AE46,'Cálculos_CGI - SAC FIXA'!A44:K436,11,0),"") -> 195555.56 | AN46: =AR47-K52 -> 53521.53 | AO46: 9 | AP46: JP | AQ46: 44320 | AR46: 248694.35 | AS46: 172.82 | AT46: 0 | AU46: 3208.16 | AV46: 77.2 | AW46: 3458.18
A47: =IF(IF(AND(A46>0,A46<$I$18),A46+1,0)=0,"",IF(AND(A46>0,A46<$I$18),A46+1,0)) -> 4 | B47: =IFERROR(IF(A47<=$I$18,DATE(YEAR($B$44),MONTH($B$44)+A46,DAY($B$44)),"-"),"") -> 46178 | C47: =IF(A47="","",K46) -> 198333.33 | D47: =C47*$I$20 -> 2161.8333 | E47: =IFERROR(C47+D47,"") -> 200495.17 | F47: =$I$13/$I$18 -> 555.55556 | G47: =IF(A47="","",PMT($I$20,$I$18,$C$44)*-1) -> 2224.912 | H47: =C47*$J$27 -> 45.616667 | I47: =IF(A47="","",IF(K46="","",IF(K46=0,"",$J$28*$I$14))) -> 20 | J47: =IFERROR(SUM(I47+H47+G47),"") -> 2290.5286 | K47: =C47-F47 -> 197777.78 | O47: =ROUNDUP(F47*$O$41*Q47,2) -> 7.46 | P47: =IF($A47<=$I$18,B47-B46,) -> 31 | Q47: =IF($A47<=$I$18,$B47-$B$43,) -> 120 | S47: Faixa Idade | U47: Alicota | V47: DFI | AA47: =A52 -> 9 | AB47: =IF($AA$36=1,VLOOKUP(AA47,$AE$38:$AK$218,6,0),IF($AA$36=2,VLOOKUP(AA47,$AE$38:$AK$218,4,0),VLOOKUP(AA47,$AE$38:$AK$218,2,0))) -> 16350.039 | AC47: =IF($AA$36=1,VLOOKUP(AA47,$AE$38:$AK$278,7,0),IF($AA$36=2,VLOOKUP(AA47,$AE$38:$AK$278,5,0),VLOOKUP(AA47,$AE$38:$AK$278,3,0))) -> 2289.8897 | AE47: =AA47 -> 9 | AF47: =IFERROR(VLOOKUP(AE47,[1]Cálculos_PRICE!$A$32:$K$212,10,0),"") -> 16350.039 | AG47: =IFERROR(VLOOKUP(AE47,'Cálculos_CGI - SAC FIXA'!A45:K437,10,0),"") -> 2289.8897 | AH47: =IFERROR(VLOOKUP(AE47,[1]Cálculos_PRICE!$A$32:$K$212,6,0),"") -> 1243.8848 | AI47: =IFERROR(VLOOKUP(AE47,'Cálculos_CGI - SAC FIXA'!A45:K437,6,0),"") -> 555.55556 | AJ47: =IFERROR(VLOOKUP(AE47,[1]Cálculos_PRICE!$A$32:$K$240,11,0),"") -> 989444.49 | AK47: =IFERROR(VLOOKUP(AE47,'Cálculos_CGI - SAC FIXA'!A45:K437,11,0),"") -> 195000 | AN47: =AR48-K53 -> 53902.036 | AO47: 10 | AP47: JP | AQ47: 44351 | AR47: 248521.53 | AS47: 175.05 | AT47: 0 | AU47: 3205.93 | AV47: 77.16 | AW47: 3458.14
A48: =IF(IF(AND(A47>0,A47<$I$18),A47+1,0)=0,"",IF(AND(A47>0,A47<$I$18),A47+1,0)) -> 5 | B48: =IFERROR(IF(A48<=$I$18,DATE(YEAR($B$44),MONTH($B$44)+A47,DAY($B$44)),"-"),"") -> 46208 | C48: =IF(A48="","",K47) -> 197777.78 | D48: =C48*$I$20 -> 2155.7778 | E48: =IFERROR(C48+D48,"") -> 199933.56 | F48: =$I$13/$I$18 -> 555.55556 | G48: =IF(A48="","",PMT($I$20,$I$18,$C$44)*-1) -> 2224.912 | H48: =C48*$J$27 -> 45.488889 | I48: =IF(A48="","",IF(K47="","",IF(K47=0,"",$J$28*$I$14))) -> 20 | J48: =IFERROR(SUM(I48+H48+G48),"") -> 2290.4009 | K48: =C48-F48 -> 197222.22 | O48: =ROUNDUP(F48*$O$41*Q48,2) -> 9.32 | P48: =IF($A48<=$I$18,B48-B47,) -> 30 | Q48: =IF($A48<=$I$18,$B48-$B$43,) -> 150 | S48: 18 | T48: 25 | U48: 0.00023 | V48: Alicota_1 | AA48: =A53 -> 10 | AB48: =IF($AA$36=1,VLOOKUP(AA48,$AE$38:$AK$218,6,0),IF($AA$36=2,VLOOKUP(AA48,$AE$38:$AK$218,4,0),VLOOKUP(AA48,$AE$38:$AK$218,2,0))) -> 16349.763 | AC48: =IF($AA$36=1,VLOOKUP(AA48,$AE$38:$AK$278,7,0),IF($AA$36=2,VLOOKUP(AA48,$AE$38:$AK$278,5,0),VLOOKUP(AA48,$AE$38:$AK$278,3,0))) -> 2289.762 | AE48: =AA48 -> 10 | AF48: =IFERROR(VLOOKUP(AE48,[1]Cálculos_PRICE!$A$32:$K$212,10,0),"") -> 16349.763 | AG48: =IFERROR(VLOOKUP(AE48,'Cálculos_CGI - SAC FIXA'!A46:K438,10,0),"") -> 2289.762 | AH48: =IFERROR(VLOOKUP(AE48,[1]Cálculos_PRICE!$A$32:$K$212,6,0),"") -> 1262.5431 | AI48: =IFERROR(VLOOKUP(AE48,'Cálculos_CGI - SAC FIXA'!A46:K438,6,0),"") -> 555.55556 | AJ48: =IFERROR(VLOOKUP(AE48,[1]Cálculos_PRICE!$A$32:$K$240,11,0),"") -> 988181.94 | AK48: =IFERROR(VLOOKUP(AE48,'Cálculos_CGI - SAC FIXA'!A46:K438,11,0),"") -> 194444.44 | AN48: =AR49-K54 -> 54280.281 | AO48: 11 | AP48: JP | AQ48: 44381 | AR48: 248346.48 | AS48: 177.31 | AT48: 0 | AU48: 3203.67 | AV48: 77.12 | AW48: 3458.1
A49: =IF(IF(AND(A48>0,A48<$I$18),A48+1,0)=0,"",IF(AND(A48>0,A48<$I$18),A48+1,0)) -> 6 | B49: =IFERROR(IF(A49<=$I$18,DATE(YEAR($B$44),MONTH($B$44)+A48,DAY($B$44)),"-"),"") -> 46239 | C49: =IF(A49="","",K48) -> 197222.22 | D49: =C49*$I$20 -> 2149.7222 | E49: =IFERROR(C49+D49,"") -> 199371.94 | F49: =$I$13/$I$18 -> 555.55556 | G49: =IF(A49="","",PMT($I$20,$I$18,$C$44)*-1) -> 2224.912 | H49: =C49*$J$27 -> 45.361111 | I49: =IF(A49="","",IF(K48="","",IF(K48=0,"",$J$28*$I$14))) -> 20 | J49: =IFERROR(SUM(I49+H49+G49),"") -> 2290.2731 | K49: =C49-F49 -> 196666.67 | O49: =ROUNDUP(F49*$O$41*Q49,2) -> 11.25 | P49: =IF($A49<=$I$18,B49-B48,) -> 31 | Q49: =IF($A49<=$I$18,$B49-$B$43,) -> 181 | S49: 26 | T49: 30 | U49: 0.00023 | V49: Alicota_2 | AA49: =A54 -> 11 | AB49: =IF($AA$36=1,VLOOKUP(AA49,$AE$38:$AK$218,6,0),IF($AA$36=2,VLOOKUP(AA49,$AE$38:$AK$218,4,0),VLOOKUP(AA49,$AE$38:$AK$218,2,0))) -> 16349.482 | AC49: =IF($AA$36=1,VLOOKUP(AA49,$AE$38:$AK$278,7,0),IF($AA$36=2,VLOOKUP(AA49,$AE$38:$AK$278,5,0),VLOOKUP(AA49,$AE$38:$AK$278,3,0))) -> 2289.6342 | AE49: =AA49 -> 11 | AF49: =IFERROR(VLOOKUP(AE49,[1]Cálculos_PRICE!$A$32:$K$212,10,0),"") -> 16349.482 | AG49: =IFERROR(VLOOKUP(AE49,'Cálculos_CGI - SAC FIXA'!A47:K439,10,0),"") -> 2289.6342 | AH49: =IFERROR(VLOOKUP(AE49,[1]Cálculos_PRICE!$A$32:$K$212,6,0),"") -> 1281.4812 | AI49: =IFERROR(VLOOKUP(AE49,'Cálculos_CGI - SAC FIXA'!A47:K439,6,0),"") -> 555.55556 | AJ49: =IFERROR(VLOOKUP(AE49,[1]Cálculos_PRICE!$A$32:$K$240,11,0),"") -> 986900.46 | AK49: =IFERROR(VLOOKUP(AE49,'Cálculos_CGI - SAC FIXA'!A47:K439,11,0),"") -> 193888.89 | AN49: =AR50-K55 -> 54656.237 | AO49: 12 | AP49: JP | AQ49: 44412 | AR49: 248169.17 | AS49: 179.6 | AT49: 0 | AU49: 3201.38 | AV49: 77.08 | AW49: 3458.06
A50: =IF(IF(AND(A49>0,A49<$I$18),A49+1,0)=0,"",IF(AND(A49>0,A49<$I$18),A49+1,0)) -> 7 | B50: =IFERROR(IF(A50<=$I$18,DATE(YEAR($B$44),MONTH($B$44)+A49,DAY($B$44)),"-"),"") -> 46270 | C50: =IF(A50="","",K49) -> 196666.67 | D50: =C50*$I$20 -> 2143.6667 | E50: =IFERROR(C50+D50,"") -> 198810.33 | F50: =$I$13/$I$18 -> 555.55556 | G50: =IF(A50="","",PMT($I$20,$I$18,$C$44)*-1) -> 2224.912 | H50: =C50*$J$27 -> 45.233333 | I50: =IF(A50="","",IF(K49="","",IF(K49=0,"",$J$28*$I$14))) -> 20 | J50: =IFERROR(SUM(I50+H50+G50),"") -> 2290.1453 | K50: =C50-F50 -> 196111.11 | O50: =ROUNDUP(F50*$O$41*Q50,2) -> 13.17 | P50: =IF($A50<=$I$18,B50-B49,) -> 31 | Q50: =IF($A50<=$I$18,$B50-$B$43,) -> 212 | S50: 31 | T50: 35 | U50: 0.00023 | V50: Alicota_3 | AA50: =A55 -> 12 | AB50: =IF($AA$36=1,VLOOKUP(AA50,$AE$38:$AK$218,6,0),IF($AA$36=2,VLOOKUP(AA50,$AE$38:$AK$218,4,0),VLOOKUP(AA50,$AE$38:$AK$218,2,0))) -> 16349.197 | AC50: =IF($AA$36=1,VLOOKUP(AA50,$AE$38:$AK$278,7,0),IF($AA$36=2,VLOOKUP(AA50,$AE$38:$AK$278,5,0),VLOOKUP(AA50,$AE$38:$AK$278,3,0))) -> 2289.5064 | AE50: =AA50 -> 12 | AF50: =IFERROR(VLOOKUP(AE50,[1]Cálculos_PRICE!$A$32:$K$212,10,0),"") -> 16349.197 | AG50: =IFERROR(VLOOKUP(AE50,'Cálculos_CGI - SAC FIXA'!A48:K440,10,0),"") -> 2289.5064 | AH50: =IFERROR(VLOOKUP(AE50,[1]Cálculos_PRICE!$A$32:$K$212,6,0),"") -> 1300.7035 | AI50: =IFERROR(VLOOKUP(AE50,'Cálculos_CGI - SAC FIXA'!A48:K440,6,0),"") -> 555.55556 | AJ50: =IFERROR(VLOOKUP(AE50,[1]Cálculos_PRICE!$A$32:$K$240,11,0),"") -> 985599.76 | AK50: =IFERROR(VLOOKUP(AE50,'Cálculos_CGI - SAC FIXA'!A48:K440,11,0),"") -> 193333.33 | AN50: =AR51-K56 -> 55029.882 | AO50: 13 | AP50: JP | AQ50: 44443 | AR50: 247989.57 | AS50: 181.91 | AT50: 0 | AU50: 3199.07 | AV50: 77.04 | AW50: 3458.02
A51: =IF(IF(AND(A50>0,A50<$I$18),A50+1,0)=0,"",IF(AND(A50>0,A50<$I$18),A50+1,0)) -> 8 | B51: =IFERROR(IF(A51<=$I$18,DATE(YEAR($B$44),MONTH($B$44)+A50,DAY($B$44)),"-"),"") -> 46300 | C51: =IF(A51="","",K50) -> 196111.11 | D51: =C51*$I$20 -> 2137.6111 | E51: =IFERROR(C51+D51,"") -> 198248.72 | F51: =$I$13/$I$18 -> 555.55556 | G51: =IF(A51="","",PMT($I$20,$I$18,$C$44)*-1) -> 2224.912 | H51: =C51*$J$27 -> 45.105556 | I51: =IF(A51="","",IF(K50="","",IF(K50=0,"",$J$28*$I$14))) -> 20 | J51: =IFERROR(SUM(I51+H51+G51),"") -> 2290.0175 | K51: =C51-F51 -> 195555.56 | O51: =ROUNDUP(F51*$O$41*Q51,2) -> 15.04 | P51: =IF($A51<=$I$18,B51-B50,) -> 30 | Q51: =IF($A51<=$I$18,$B51-$B$43,) -> 242 | S51: 36 | T51: 40 | U51: 0.00023 | V51: Alicota_4 | AA51: =A56 -> 13 | AB51: =IF($AA$36=1,VLOOKUP(AA51,$AE$38:$AK$218,6,0),IF($AA$36=2,VLOOKUP(AA51,$AE$38:$AK$218,4,0),VLOOKUP(AA51,$AE$38:$AK$218,2,0))) -> 16348.908 | AC51: =IF($AA$36=1,VLOOKUP(AA51,$AE$38:$AK$278,7,0),IF($AA$36=2,VLOOKUP(AA51,$AE$38:$AK$278,5,0),VLOOKUP(AA51,$AE$38:$AK$278,3,0))) -> 2289.3786 | AE51: =AA51 -> 13 | AF51: =IFERROR(VLOOKUP(AE51,[1]Cálculos_PRICE!$A$32:$K$212,10,0),"") -> 16348.908 | AG51: =IFERROR(VLOOKUP(AE51,'Cálculos_CGI - SAC FIXA'!A49:K441,10,0),"") -> 2289.3786 | AH51: =IFERROR(VLOOKUP(AE51,[1]Cálculos_PRICE!$A$32:$K$212,6,0),"") -> 1320.214 | AI51: =IFERROR(VLOOKUP(AE51,'Cálculos_CGI - SAC FIXA'!A49:K441,6,0),"") -> 555.55556 | AJ51: =IFERROR(VLOOKUP(AE51,[1]Cálculos_PRICE!$A$32:$K$240,11,0),"") -> 984279.54 | AK51: =IFERROR(VLOOKUP(AE51,'Cálculos_CGI - SAC FIXA'!A49:K441,11,0),"") -> 192777.78 | AN51: =AR52-K57 -> 55401.178 | AO51: 14 | AP51: JP | AQ51: 44473 | AR51: 247807.66 | AS51: 184.26 | AT51: 0 | AU51: 3196.72 | AV51: 77 | AW51: 3457.98
A52: =IF(IF(AND(A51>0,A51<$I$18),A51+1,0)=0,"",IF(AND(A51>0,A51<$I$18),A51+1,0)) -> 9 | B52: =IFERROR(IF(A52<=$I$18,DATE(YEAR($B$44),MONTH($B$44)+A51,DAY($B$44)),"-"),"") -> 46331 | C52: =IF(A52="","",K51) -> 195555.56 | D52: =C52*$I$20 -> 2131.5556 | E52: =IFERROR(C52+D52,"") -> 197687.11 | F52: =$I$13/$I$18 -> 555.55556 | G52: =IF(A52="","",PMT($I$20,$I$18,$C$44)*-1) -> 2224.912 | H52: =C52*$J$27 -> 44.977778 | I52: =IF(A52="","",IF(K51="","",IF(K51=0,"",$J$28*$I$14))) -> 20 | J52: =IFERROR(SUM(I52+H52+G52),"") -> 2289.8897 | K52: =C52-F52 -> 195000 | O52: =ROUNDUP(F52*$O$41*Q52,2) -> 16.96 | P52: =IF($A52<=$I$18,B52-B51,) -> 31 | Q52: =IF($A52<=$I$18,$B52-$B$43,) -> 273 | S52: 41 | T52: 50 | U52: 0.00023 | V52: Alicota_5 | AA52: =A57 -> 14 | AB52: =IF($AA$36=1,VLOOKUP(AA52,$AE$38:$AK$218,6,0),IF($AA$36=2,VLOOKUP(AA52,$AE$38:$AK$218,4,0),VLOOKUP(AA52,$AE$38:$AK$218,2,0))) -> 16348.614 | AC52: =IF($AA$36=1,VLOOKUP(AA52,$AE$38:$AK$278,7,0),IF($AA$36=2,VLOOKUP(AA52,$AE$38:$AK$278,5,0),VLOOKUP(AA52,$AE$38:$AK$278,3,0))) -> 2289.2509 | AE52: =AA52 -> 14 | AF52: =IFERROR(VLOOKUP(AE52,[1]Cálculos_PRICE!$A$32:$K$212,10,0),"") -> 16348.614 | AG52: =IFERROR(VLOOKUP(AE52,'Cálculos_CGI - SAC FIXA'!A50:K442,10,0),"") -> 2289.2509 | AH52: =IFERROR(VLOOKUP(AE52,[1]Cálculos_PRICE!$A$32:$K$212,6,0),"") -> 1340.0172 | AI52: =IFERROR(VLOOKUP(AE52,'Cálculos_CGI - SAC FIXA'!A50:K442,6,0),"") -> 555.55556 | AJ52: =IFERROR(VLOOKUP(AE52,[1]Cálculos_PRICE!$A$32:$K$240,11,0),"") -> 982939.53 | AK52: =IFERROR(VLOOKUP(AE52,'Cálculos_CGI - SAC FIXA'!A50:K442,11,0),"") -> 192222.22 | AN52: =AR53-K58 -> 55770.093 | AO52: 15 | AP52: JP | AQ52: 44504 | AR52: 247623.4 | AS52: 186.64 | AT52: 0 | AU52: 3194.34 | AV52: 76.95 | AW52: 3457.93
A53: =IF(IF(AND(A52>0,A52<$I$18),A52+1,0)=0,"",IF(AND(A52>0,A52<$I$18),A52+1,0)) -> 10 | B53: =IFERROR(IF(A53<=$I$18,DATE(YEAR($B$44),MONTH($B$44)+A52,DAY($B$44)),"-"),"") -> 46361 | C53: =IF(A53="","",K52) -> 195000 | D53: =C53*$I$20 -> 2125.5 | E53: =IFERROR(C53+D53,"") -> 197125.5 | F53: =$I$13/$I$18 -> 555.55556 | G53: =IF(A53="","",PMT($I$20,$I$18,$C$44)*-1) -> 2224.912 | H53: =C53*$J$27 -> 44.85 | I53: =IF(A53="","",IF(K52="","",IF(K52=0,"",$J$28*$I$14))) -> 20 | J53: =IFERROR(SUM(I53+H53+G53),"") -> 2289.762 | K53: =C53-F53 -> 194444.44 | O53: =ROUNDUP(F53*$O$41*Q53,2) -> 18.82 | P53: =IF($A53<=$I$18,B53-B52,) -> 30 | Q53: =IF($A53<=$I$18,$B53-$B$43,) -> 303 | S53: 51 | T53: 60 | U53: 0.00023 | V53: Alicota_6 | AA53: =A58 -> 15 | AB53: =IF($AA$36=1,VLOOKUP(AA53,$AE$38:$AK$218,6,0),IF($AA$36=2,VLOOKUP(AA53,$AE$38:$AK$218,4,0),VLOOKUP(AA53,$AE$38:$AK$218,2,0))) -> 16348.316 | AC53: =IF($AA$36=1,VLOOKUP(AA53,$AE$38:$AK$278,7,0),IF($AA$36=2,VLOOKUP(AA53,$AE$38:$AK$278,5,0),VLOOKUP(AA53,$AE$38:$AK$278,3,0))) -> 2289.1231 | AE53: =AA53 -> 15 | AF53: =IFERROR(VLOOKUP(AE53,[1]Cálculos_PRICE!$A$32:$K$212,10,0),"") -> 16348.316 | AG53: =IFERROR(VLOOKUP(AE53,'Cálculos_CGI - SAC FIXA'!A51:K443,10,0),"") -> 2289.1231 | AH53: =IFERROR(VLOOKUP(AE53,[1]Cálculos_PRICE!$A$32:$K$212,6,0),"") -> 1360.1175 | AI53: =IFERROR(VLOOKUP(AE53,'Cálculos_CGI - SAC FIXA'!A51:K443,6,0),"") -> 555.55556 | AJ53: =IFERROR(VLOOKUP(AE53,[1]Cálculos_PRICE!$A$32:$K$240,11,0),"") -> 981579.41 | AK53: =IFERROR(VLOOKUP(AE53,'Cálculos_CGI - SAC FIXA'!A51:K443,11,0),"") -> 191666.67 | AN53: =AR54-K59 -> 56136.599 | AO53: 16 | AP53: JP | AQ53: 44534 | AR53: 247436.76 | AS53: 189.05 | AT53: 0 | AU53: 3191.93 | AV53: 76.91 | AW53: 3457.89
A54: =IF(IF(AND(A53>0,A53<$I$18),A53+1,0)=0,"",IF(AND(A53>0,A53<$I$18),A53+1,0)) -> 11 | B54: =IFERROR(IF(A54<=$I$18,DATE(YEAR($B$44),MONTH($B$44)+A53,DAY($B$44)),"-"),"") -> 46392 | C54: =IF(A54="","",K53) -> 194444.44 | D54: =C54*$I$20 -> 2119.4444 | E54: =IFERROR(C54+D54,"") -> 196563.89 | F54: =$I$13/$I$18 -> 555.55556 | G54: =IF(A54="","",PMT($I$20,$I$18,$C$44)*-1) -> 2224.912 | H54: =C54*$J$27 -> 44.722222 | I54: =IF(A54="","",IF(K53="","",IF(K53=0,"",$J$28*$I$14))) -> 20 | J54: =IFERROR(SUM(I54+H54+G54),"") -> 2289.6342 | K54: =C54-F54 -> 193888.89 | O54: =ROUNDUP(F54*$O$41*Q54,2) -> 20.75 | P54: =IF($A54<=$I$18,B54-B53,) -> 31 | Q54: =IF($A54<=$I$18,$B54-$B$43,) -> 334 | S54: 61 | T54: 70 | U54: 0.00023 | V54: Alicota_7 | AA54: =A59 -> 16 | AB54: =IF($AA$36=1,VLOOKUP(AA54,$AE$38:$AK$218,6,0),IF($AA$36=2,VLOOKUP(AA54,$AE$38:$AK$218,4,0),VLOOKUP(AA54,$AE$38:$AK$218,2,0))) -> 16348.014 | AC54: =IF($AA$36=1,VLOOKUP(AA54,$AE$38:$AK$278,7,0),IF($AA$36=2,VLOOKUP(AA54,$AE$38:$AK$278,5,0),VLOOKUP(AA54,$AE$38:$AK$278,3,0))) -> 2288.9953 | AE54: =AA54 -> 16 | AF54: =IFERROR(VLOOKUP(AE54,[1]Cálculos_PRICE!$A$32:$K$212,10,0),"") -> 16348.014 | AG54: =IFERROR(VLOOKUP(AE54,'Cálculos_CGI - SAC FIXA'!A52:K444,10,0),"") -> 2288.9953 | AH54: =IFERROR(VLOOKUP(AE54,[1]Cálculos_PRICE!$A$32:$K$212,6,0),"") -> 1380.5192 | AI54: =IFERROR(VLOOKUP(AE54,'Cálculos_CGI - SAC FIXA'!A52:K444,6,0),"") -> 555.55556 | AJ54: =IFERROR(VLOOKUP(AE54,[1]Cálculos_PRICE!$A$32:$K$240,11,0),"") -> 980198.89 | AK54: =IFERROR(VLOOKUP(AE54,'Cálculos_CGI - SAC FIXA'!A52:K444,11,0),"") -> 191111.11 | AN54: =AR55-K60 -> 56500.674 | AO54: 17 | AP54: JP | AQ54: 44565 | AR54: 247247.71 | AS54: 191.48 | AT54: 0 | AU54: 3189.5 | AV54: 76.87 | AW54: 3457.85
A55: =IF(IF(AND(A54>0,A54<$I$18),A54+1,0)=0,"",IF(AND(A54>0,A54<$I$18),A54+1,0)) -> 12 | B55: =IFERROR(IF(A55<=$I$18,DATE(YEAR($B$44),MONTH($B$44)+A54,DAY($B$44)),"-"),"") -> 46423 | C55: =IF(A55="","",K54) -> 193888.89 | D55: =C55*$I$20 -> 2113.3889 | E55: =IFERROR(C55+D55,"") -> 196002.28 | F55: =$I$13/$I$18 -> 555.55556 | G55: =IF(A55="","",PMT($I$20,$I$18,$C$44)*-1) -> 2224.912 | H55: =C55*$J$27 -> 44.594444 | I55: =IF(A55="","",IF(K54="","",IF(K54=0,"",$J$28*$I$14))) -> 20 | J55: =IFERROR(SUM(I55+H55+G55),"") -> 2289.5064 | K55: =C55-F55 -> 193333.33 | O55: =ROUNDUP(F55*$O$41*Q55,2) -> 22.68 | P55: =IF($A55<=$I$18,B55-B54,) -> 31 | Q55: =IF($A55<=$I$18,$B55-$B$43,) -> 365 | S55: 71 | T55: 75 | U55: 0.00023 | V55: Alicota_8 | AA55: =A60 -> 17 | AB55: =IF($AA$36=1,VLOOKUP(AA55,$AE$38:$AK$218,6,0),IF($AA$36=2,VLOOKUP(AA55,$AE$38:$AK$218,4,0),VLOOKUP(AA55,$AE$38:$AK$218,2,0))) -> 16347.707 | AC55: =IF($AA$36=1,VLOOKUP(AA55,$AE$38:$AK$278,7,0),IF($AA$36=2,VLOOKUP(AA55,$AE$38:$AK$278,5,0),VLOOKUP(AA55,$AE$38:$AK$278,3,0))) -> 2288.8675 | AE55: =AA55 -> 17 | AF55: =IFERROR(VLOOKUP(AE55,[1]Cálculos_PRICE!$A$32:$K$212,10,0),"") -> 16347.707 | AG55: =IFERROR(VLOOKUP(AE55,'Cálculos_CGI - SAC FIXA'!A53:K445,10,0),"") -> 2288.8675 | AH55: =IFERROR(VLOOKUP(AE55,[1]Cálculos_PRICE!$A$32:$K$212,6,0),"") -> 1401.227 | AI55: =IFERROR(VLOOKUP(AE55,'Cálculos_CGI - SAC FIXA'!A53:K445,6,0),"") -> 555.55556 | AJ55: =IFERROR(VLOOKUP(AE55,[1]Cálculos_PRICE!$A$32:$K$240,11,0),"") -> 978797.66 | AK55: =IFERROR(VLOOKUP(AE55,'Cálculos_CGI - SAC FIXA'!A53:K445,11,0),"") -> 190555.56 | AN55: =AR56-K61 -> 56862.28 | AO55: 18 | AP55: JP | AQ55: 44596 | AR55: 247056.23 | AS55: 193.95 | AT55: 0 | AU55: 3187.03 | AV55: 76.82 | AW55: 3457.8
A56: =IF(IF(AND(A55>0,A55<$I$18),A55+1,0)=0,"",IF(AND(A55>0,A55<$I$18),A55+1,0)) -> 13 | B56: =IFERROR(IF(A56<=$I$18,DATE(YEAR($B$44),MONTH($B$44)+A55,DAY($B$44)),"-"),"") -> 46451 | C56: =IF(A56="","",K55) -> 193333.33 | D56: =C56*$I$20 -> 2107.3333 | E56: =IFERROR(C56+D56,"") -> 195440.67 | F56: =$I$13/$I$18 -> 555.55556 | G56: =IF(A56="","",PMT($I$20,$I$18,$C$44)*-1) -> 2224.912 | H56: =C56*$J$27 -> 44.466667 | I56: =IF(A56="","",IF(K55="","",IF(K55=0,"",$J$28*$I$14))) -> 20 | J56: =IFERROR(SUM(I56+H56+G56),"") -> 2289.3786 | K56: =C56-F56 -> 192777.78 | O56: =IFERROR(F56*$O$39,0) -> 16.666667 | P56: =IF($A56<=$I$18,B56-B55,) -> 28 | Q56: 365 | S56: 76 | T56: 80.4 | U56: 0.00023 | V56: Alicota_9 | AA56: =A61 -> 18 | AB56: =IF($AA$36=1,VLOOKUP(AA56,$AE$38:$AK$218,6,0),IF($AA$36=2,VLOOKUP(AA56,$AE$38:$AK$218,4,0),VLOOKUP(AA56,$AE$38:$AK$218,2,0))) -> 16347.395 | AC56: =IF($AA$36=1,VLOOKUP(AA56,$AE$38:$AK$278,7,0),IF($AA$36=2,VLOOKUP(AA56,$AE$38:$AK$278,5,0),VLOOKUP(AA56,$AE$38:$AK$278,3,0))) -> 2288.7397 | AE56: =AA56 -> 18 | AF56: =IFERROR(VLOOKUP(AE56,[1]Cálculos_PRICE!$A$32:$K$212,10,0),"") -> 16347.395 | AG56: =IFERROR(VLOOKUP(AE56,'Cálculos_CGI - SAC FIXA'!A54:K446,10,0),"") -> 2288.7397 | AH56: =IFERROR(VLOOKUP(AE56,[1]Cálculos_PRICE!$A$32:$K$212,6,0),"") -> 1422.2454 | AI56: =IFERROR(VLOOKUP(AE56,'Cálculos_CGI - SAC FIXA'!A54:K446,6,0),"") -> 555.55556 | AJ56: =IFERROR(VLOOKUP(AE56,[1]Cálculos_PRICE!$A$32:$K$240,11,0),"") -> 977375.42 | AK56: =IFERROR(VLOOKUP(AE56,'Cálculos_CGI - SAC FIXA'!A54:K446,11,0),"") -> 190000 | AN56: =AR57-K62 -> 57221.376 | AO56: 19 | AP56: JP | AQ56: 44624 | AR56: 246862.28 | AS56: 196.46 | AT56: 0 | AU56: 3184.52 | AV56: 76.78 | AW56: 3457.76
A57: =IF(IF(AND(A56>0,A56<$I$18),A56+1,0)=0,"",IF(AND(A56>0,A56<$I$18),A56+1,0)) -> 14 | B57: =IFERROR(IF(A57<=$I$18,DATE(YEAR($B$44),MONTH($B$44)+A56,DAY($B$44)),"-"),"") -> 46482 | C57: =IF(A57="","",K56) -> 192777.78 | D57: =C57*$I$20 -> 2101.2778 | E57: =IFERROR(C57+D57,"") -> 194879.06 | F57: =$I$13/$I$18 -> 555.55556 | G57: =IF(A57="","",PMT($I$20,$I$18,$C$44)*-1) -> 2224.912 | H57: =C57*$J$27 -> 44.338889 | I57: =IF(A57="","",IF(K56="","",IF(K56=0,"",$J$28*$I$14))) -> 20 | J57: =IFERROR(SUM(I57+H57+G57),"") -> 2289.2509 | K57: =C57-F57 -> 192222.22 | O57: =IFERROR(F57*$O$39,0) -> 16.666667 | P57: =IF($A57<=$I$18,B57-B56,) -> 31 | Q57: 365 | AA57: =A62 -> 19 | AB57: =IF($AA$36=1,VLOOKUP(AA57,$AE$38:$AK$218,6,0),IF($AA$36=2,VLOOKUP(AA57,$AE$38:$AK$218,4,0),VLOOKUP(AA57,$AE$38:$AK$218,2,0))) -> 16347.079 | AC57: =IF($AA$36=1,VLOOKUP(AA57,$AE$38:$AK$278,7,0),IF($AA$36=2,VLOOKUP(AA57,$AE$38:$AK$278,5,0),VLOOKUP(AA57,$AE$38:$AK$278,3,0))) -> 2288.612 | AE57: =AA57 -> 19 | AF57: =IFERROR(VLOOKUP(AE57,[1]Cálculos_PRICE!$A$32:$K$212,10,0),"") -> 16347.079 | AG57: =IFERROR(VLOOKUP(AE57,'Cálculos_CGI - SAC FIXA'!A55:K447,10,0),"") -> 2288.612 | AH57: =IFERROR(VLOOKUP(AE57,[1]Cálculos_PRICE!$A$32:$K$212,6,0),"") -> 1443.5791 | AI57: =IFERROR(VLOOKUP(AE57,'Cálculos_CGI - SAC FIXA'!A55:K447,6,0),"") -> 555.55556 | AJ57: =IFERROR(VLOOKUP(AE57,[1]Cálculos_PRICE!$A$32:$K$240,11,0),"") -> 975931.84 | AK57: =IFERROR(VLOOKUP(AE57,'Cálculos_CGI - SAC FIXA'!A55:K447,11,0),"") -> 189444.44 | AN57: =AR58-K63 -> 57577.941 | AO57: 20 | AP57: JP | AQ57: 44655 | AR57: 246665.82 | AS57: 198.99 | AT57: 0 | AU57: 3181.99 | AV57: 76.73 | AW57: 3457.71
A58: =IF(IF(AND(A57>0,A57<$I$18),A57+1,0)=0,"",IF(AND(A57>0,A57<$I$18),A57+1,0)) -> 15 | B58: =IFERROR(IF(A58<=$I$18,DATE(YEAR($B$44),MONTH($B$44)+A57,DAY($B$44)),"-"),"") -> 46512 | C58: =IF(A58="","",K57) -> 192222.22 | D58: =C58*$I$20 -> 2095.2222 | E58: =IFERROR(C58+D58,"") -> 194317.44 | F58: =$I$13/$I$18 -> 555.55556 | G58: =IF(A58="","",PMT($I$20,$I$18,$C$44)*-1) -> 2224.912 | H58: =C58*$J$27 -> 44.211111 | I58: =IF(A58="","",IF(K57="","",IF(K57=0,"",$J$28*$I$14))) -> 20 | J58: =IFERROR(SUM(I58+H58+G58),"") -> 2289.1231 | K58: =C58-F58 -> 191666.67 | O58: =IFERROR(F58*$O$39,0) -> 16.666667 | P58: =IF($A58<=$I$18,B58-B57,) -> 30 | Q58: 365 | S58: COBRA IOF | AA58: =A63 -> 20 | AB58: =IF($AA$36=1,VLOOKUP(AA58,$AE$38:$AK$218,6,0),IF($AA$36=2,VLOOKUP(AA58,$AE$38:$AK$218,4,0),VLOOKUP(AA58,$AE$38:$AK$218,2,0))) -> 16346.758 | AC58: =IF($AA$36=1,VLOOKUP(AA58,$AE$38:$AK$278,7,0),IF($AA$36=2,VLOOKUP(AA58,$AE$38:$AK$278,5,0),VLOOKUP(AA58,$AE$38:$AK$278,3,0))) -> 2288.4842 | AE58: =AA58 -> 20 | AF58: =IFERROR(VLOOKUP(AE58,[1]Cálculos_PRICE!$A$32:$K$212,10,0),"") -> 16346.758 | AG58: =IFERROR(VLOOKUP(AE58,'Cálculos_CGI - SAC FIXA'!A56:K448,10,0),"") -> 2288.4842 | AH58: =IFERROR(VLOOKUP(AE58,[1]Cálculos_PRICE!$A$32:$K$212,6,0),"") -> 1465.2328 | AI58: =IFERROR(VLOOKUP(AE58,'Cálculos_CGI - SAC FIXA'!A56:K448,6,0),"") -> 555.55556 | AJ58: =IFERROR(VLOOKUP(AE58,[1]Cálculos_PRICE!$A$32:$K$240,11,0),"") -> 974466.61 | AK58: =IFERROR(VLOOKUP(AE58,'Cálculos_CGI - SAC FIXA'!A56:K448,11,0),"") -> 188888.89 | AN58: =AR59-K64 -> 57931.937 | AO58: 21 | AP58: JP | AQ58: 44685 | AR58: 246466.83 | AS58: 201.56 | AT58: 0 | AU58: 3179.42 | AV58: 76.69 | AW58: 3457.67
A59: =IF(IF(AND(A58>0,A58<$I$18),A58+1,0)=0,"",IF(AND(A58>0,A58<$I$18),A58+1,0)) -> 16 | B59: =IFERROR(IF(A59<=$I$18,DATE(YEAR($B$44),MONTH($B$44)+A58,DAY($B$44)),"-"),"") -> 46543 | C59: =IF(A59="","",K58) -> 191666.67 | D59: =C59*$I$20 -> 2089.1667 | E59: =IFERROR(C59+D59,"") -> 193755.83 | F59: =$I$13/$I$18 -> 555.55556 | G59: =IF(A59="","",PMT($I$20,$I$18,$C$44)*-1) -> 2224.912 | H59: =C59*$J$27 -> 44.083333 | I59: =IF(A59="","",IF(K58="","",IF(K58=0,"",$J$28*$I$14))) -> 20 | J59: =IFERROR(SUM(I59+H59+G59),"") -> 2288.9953 | K59: =C59-F59 -> 191111.11 | O59: =IFERROR(F59*$O$39,0) -> 16.666667 | P59: =IF($A59<=$I$18,B59-B58,) -> 31 | Q59: 365 | S59: FCTO-AQUIS | X59: IOF | Y59: LTV | AA59: =A64 -> 21 | AB59: =IF($AA$36=1,VLOOKUP(AA59,$AE$38:$AK$218,6,0),IF($AA$36=2,VLOOKUP(AA59,$AE$38:$AK$218,4,0),VLOOKUP(AA59,$AE$38:$AK$218,2,0))) -> 16346.432 | AC59: =IF($AA$36=1,VLOOKUP(AA59,$AE$38:$AK$278,7,0),IF($AA$36=2,VLOOKUP(AA59,$AE$38:$AK$278,5,0),VLOOKUP(AA59,$AE$38:$AK$278,3,0))) -> 2288.3564 | AE59: =AA59 -> 21 | AF59: =IFERROR(VLOOKUP(AE59,[1]Cálculos_PRICE!$A$32:$K$212,10,0),"") -> 16346.432 | AG59: =IFERROR(VLOOKUP(AE59,'Cálculos_CGI - SAC FIXA'!A57:K449,10,0),"") -> 2288.3564 | AH59: =IFERROR(VLOOKUP(AE59,[1]Cálculos_PRICE!$A$32:$K$212,6,0),"") -> 1487.2113 | AI59: =IFERROR(VLOOKUP(AE59,'Cálculos_CGI - SAC FIXA'!A57:K449,6,0),"") -> 555.55556 | AJ59: =IFERROR(VLOOKUP(AE59,[1]Cálculos_PRICE!$A$32:$K$240,11,0),"") -> 972979.4 | AK59: =IFERROR(VLOOKUP(AE59,'Cálculos_CGI - SAC FIXA'!A57:K449,11,0),"") -> 188333.33 | AN59: =AR60-K65 -> 58283.332 | AO59: 22 | AP59: JP | AQ59: 44716 | AR59: 246265.27 | AS59: 204.16 | AT59: 0 | AU59: 3176.82 | AV59: 76.64 | AW59: 3457.62
A60: =IF(IF(AND(A59>0,A59<$I$18),A59+1,0)=0,"",IF(AND(A59>0,A59<$I$18),A59+1,0)) -> 17 | B60: =IFERROR(IF(A60<=$I$18,DATE(YEAR($B$44),MONTH($B$44)+A59,DAY($B$44)),"-"),"") -> 46573 | C60: =IF(A60="","",K59) -> 191111.11 | D60: =C60*$I$20 -> 2083.1111 | E60: =IFERROR(C60+D60,"") -> 193194.22 | F60: =$I$13/$I$18 -> 555.55556 | G60: =IF(A60="","",PMT($I$20,$I$18,$C$44)*-1) -> 2224.912 | H60: =C60*$J$27 -> 43.955556 | I60: =IF(A60="","",IF(K59="","",IF(K59=0,"",$J$28*$I$14))) -> 20 | J60: =IFERROR(SUM(I60+H60+G60),"") -> 2288.8675 | K60: =C60-F60 -> 190555.56 | O60: =IFERROR(F60*$O$39,0) -> 16.666667 | P60: =IF($A60<=$I$18,B60-B59,) -> 30 | Q60: 365 | S60: 1 - RESIDENCIAL - CASA | X60: NÃO | Y60: 70 | AA60: =A65 -> 22 | AB60: =IF($AA$36=1,VLOOKUP(AA60,$AE$38:$AK$218,6,0),IF($AA$36=2,VLOOKUP(AA60,$AE$38:$AK$218,4,0),VLOOKUP(AA60,$AE$38:$AK$218,2,0))) -> 16346.101 | AC60: =IF($AA$36=1,VLOOKUP(AA60,$AE$38:$AK$278,7,0),IF($AA$36=2,VLOOKUP(AA60,$AE$38:$AK$278,5,0),VLOOKUP(AA60,$AE$38:$AK$278,3,0))) -> 2288.2286 | AE60: =AA60 -> 22 | AF60: =IFERROR(VLOOKUP(AE60,[1]Cálculos_PRICE!$A$32:$K$212,10,0),"") -> 16346.101 | AG60: =IFERROR(VLOOKUP(AE60,'Cálculos_CGI - SAC FIXA'!A58:K450,10,0),"") -> 2288.2286 | AH60: =IFERROR(VLOOKUP(AE60,[1]Cálculos_PRICE!$A$32:$K$212,6,0),"") -> 1509.5195 | AI60: =IFERROR(VLOOKUP(AE60,'Cálculos_CGI - SAC FIXA'!A58:K450,6,0),"") -> 555.55556 | AJ60: =IFERROR(VLOOKUP(AE60,[1]Cálculos_PRICE!$A$32:$K$240,11,0),"") -> 971469.88 | AK60: =IFERROR(VLOOKUP(AE60,'Cálculos_CGI - SAC FIXA'!A58:K450,11,0),"") -> 187777.78 | AN60: =AR61-K66 -> 58632.098 | AO60: 23 | AP60: JP | AQ60: 44746 | AR60: 246061.11 | AS60: 206.79 | AT60: 0 | AU60: 3174.19 | AV60: 76.59 | AW60: 3457.57
A61: =IF(IF(AND(A60>0,A60<$I$18),A60+1,0)=0,"",IF(AND(A60>0,A60<$I$18),A60+1,0)) -> 18 | B61: =IFERROR(IF(A61<=$I$18,DATE(YEAR($B$44),MONTH($B$44)+A60,DAY($B$44)),"-"),"") -> 46604 | C61: =IF(A61="","",K60) -> 190555.56 | D61: =C61*$I$20 -> 2077.0556 | E61: =IFERROR(C61+D61,"") -> 192632.61 | F61: =$I$13/$I$18 -> 555.55556 | G61: =IF(A61="","",PMT($I$20,$I$18,$C$44)*-1) -> 2224.912 | H61: =C61*$J$27 -> 43.827778 | I61: =IF(A61="","",IF(K60="","",IF(K60=0,"",$J$28*$I$14))) -> 20 | J61: =IFERROR(SUM(I61+H61+G61),"") -> 2288.7397 | K61: =C61-F61 -> 190000 | O61: =IFERROR(F61*$O$39,0) -> 16.666667 | P61: =IF($A61<=$I$18,B61-B60,) -> 31 | Q61: 365 | S61: 2 - RESIDENCIAL - APARTAMENTO | X61: NÃO | Y61: 70 | AA61: =A66 -> 23 | AB61: =IF($AA$36=1,VLOOKUP(AA61,$AE$38:$AK$218,6,0),IF($AA$36=2,VLOOKUP(AA61,$AE$38:$AK$218,4,0),VLOOKUP(AA61,$AE$38:$AK$218,2,0))) -> 16345.765 | AC61: =IF($AA$36=1,VLOOKUP(AA61,$AE$38:$AK$278,7,0),IF($AA$36=2,VLOOKUP(AA61,$AE$38:$AK$278,5,0),VLOOKUP(AA61,$AE$38:$AK$278,3,0))) -> 2288.1009 | AE61: =AA61 -> 23 | AF61: =IFERROR(VLOOKUP(AE61,[1]Cálculos_PRICE!$A$32:$K$212,10,0),"") -> 16345.765 | AG61: =IFERROR(VLOOKUP(AE61,'Cálculos_CGI - SAC FIXA'!A59:K451,10,0),"") -> 2288.1009 | AH61: =IFERROR(VLOOKUP(AE61,[1]Cálculos_PRICE!$A$32:$K$212,6,0),"") -> 1532.1623 | AI61: =IFERROR(VLOOKUP(AE61,'Cálculos_CGI - SAC FIXA'!A59:K451,6,0),"") -> 555.55556 | AJ61: =IFERROR(VLOOKUP(AE61,[1]Cálculos_PRICE!$A$32:$K$240,11,0),"") -> 969937.71 | AK61: =IFERROR(VLOOKUP(AE61,'Cálculos_CGI - SAC FIXA'!A59:K451,11,0),"") -> 187222.22 | AN61: =AR62-K67 -> 58978.193 | AO61: 24 | AP61: JP | AQ61: 44777 | AR61: 245854.32 | AS61: 209.46 | AT61: 0 | AU61: 3171.52 | AV61: 76.55 | AW61: 3457.53
A62: =IF(IF(AND(A61>0,A61<$I$18),A61+1,0)=0,"",IF(AND(A61>0,A61<$I$18),A61+1,0)) -> 19 | B62: =IFERROR(IF(A62<=$I$18,DATE(YEAR($B$44),MONTH($B$44)+A61,DAY($B$44)),"-"),"") -> 46635 | C62: =IF(A62="","",K61) -> 190000 | D62: =C62*$I$20 -> 2071 | E62: =IFERROR(C62+D62,"") -> 192071 | F62: =$I$13/$I$18 -> 555.55556 | G62: =IF(A62="","",PMT($I$20,$I$18,$C$44)*-1) -> 2224.912 | H62: =C62*$J$27 -> 43.7 | I62: =IF(A62="","",IF(K61="","",IF(K61=0,"",$J$28*$I$14))) -> 20 | J62: =IFERROR(SUM(I62+H62+G62),"") -> 2288.612 | K62: =C62-F62 -> 189444.44 | O62: =IFERROR(F62*$O$39,0) -> 16.666667 | P62: =IF($A62<=$I$18,B62-B61,) -> 31 | Q62: 365 | S62: 3 - COMERCIAL - LOJA | X62: SIM | Y62: 50 | AA62: =A67 -> 24 | AB62: =IF($AA$36=1,VLOOKUP(AA62,$AE$38:$AK$218,6,0),IF($AA$36=2,VLOOKUP(AA62,$AE$38:$AK$218,4,0),VLOOKUP(AA62,$AE$38:$AK$218,2,0))) -> 16345.425 | AC62: =IF($AA$36=1,VLOOKUP(AA62,$AE$38:$AK$278,7,0),IF($AA$36=2,VLOOKUP(AA62,$AE$38:$AK$278,5,0),VLOOKUP(AA62,$AE$38:$AK$278,3,0))) -> 2287.9731 | AE62: =AA62 -> 24 | AF62: =IFERROR(VLOOKUP(AE62,[1]Cálculos_PRICE!$A$32:$K$212,10,0),"") -> 16345.425 | AG62: =IFERROR(VLOOKUP(AE62,'Cálculos_CGI - SAC FIXA'!A60:K452,10,0),"") -> 2287.9731 | AH62: =IFERROR(VLOOKUP(AE62,[1]Cálculos_PRICE!$A$32:$K$212,6,0),"") -> 1555.1447 | AI62: =IFERROR(VLOOKUP(AE62,'Cálculos_CGI - SAC FIXA'!A60:K452,6,0),"") -> 555.55556 | AJ62: =IFERROR(VLOOKUP(AE62,[1]Cálculos_PRICE!$A$32:$K$240,11,0),"") -> 968382.57 | AK62: =IFERROR(VLOOKUP(AE62,'Cálculos_CGI - SAC FIXA'!A60:K452,11,0),"") -> 186666.67 | AN62: =AR63-K68 -> 59321.589 | AO62: 25 | AP62: JP | AQ62: 44808 | AR62: 245644.86 | AS62: 212.16 | AT62: 0 | AU62: 3168.82 | AV62: 76.5 | AW62: 3457.48
A63: =IF(IF(AND(A62>0,A62<$I$18),A62+1,0)=0,"",IF(AND(A62>0,A62<$I$18),A62+1,0)) -> 20 | B63: =IFERROR(IF(A63<=$I$18,DATE(YEAR($B$44),MONTH($B$44)+A62,DAY($B$44)),"-"),"") -> 46665 | C63: =IF(A63="","",K62) -> 189444.44 | D63: =C63*$I$20 -> 2064.9444 | E63: =IFERROR(C63+D63,"") -> 191509.39 | F63: =$I$13/$I$18 -> 555.55556 | G63: =IF(A63="","",PMT($I$20,$I$18,$C$44)*-1) -> 2224.912 | H63: =C63*$J$27 -> 43.572222 | I63: =IF(A63="","",IF(K62="","",IF(K62=0,"",$J$28*$I$14))) -> 20 | J63: =IFERROR(SUM(I63+H63+G63),"") -> 2288.4842 | K63: =C63-F63 -> 188888.89 | O63: =IFERROR(F63*$O$39,0) -> 16.666667 | P63: =IF($A63<=$I$18,B63-B62,) -> 30 | Q63: 365 | S63: 4 - COMERCIAL - SALA COMERCIAL | X63: SIM | Y63: 50 | AA63: =A68 -> 25 | AB63: =IF($AA$36=1,VLOOKUP(AA63,$AE$38:$AK$218,6,0),IF($AA$36=2,VLOOKUP(AA63,$AE$38:$AK$218,4,0),VLOOKUP(AA63,$AE$38:$AK$218,2,0))) -> 16345.079 | AC63: =IF($AA$36=1,VLOOKUP(AA63,$AE$38:$AK$278,7,0),IF($AA$36=2,VLOOKUP(AA63,$AE$38:$AK$278,5,0),VLOOKUP(AA63,$AE$38:$AK$278,3,0))) -> 2287.8453 | AE63: =AA63 -> 25 | AF63: =IFERROR(VLOOKUP(AE63,[1]Cálculos_PRICE!$A$32:$K$212,10,0),"") -> 16345.079 | AG63: =IFERROR(VLOOKUP(AE63,'Cálculos_CGI - SAC FIXA'!A61:K453,10,0),"") -> 2287.8453 | AH63: =IFERROR(VLOOKUP(AE63,[1]Cálculos_PRICE!$A$32:$K$212,6,0),"") -> 1578.4719 | AI63: =IFERROR(VLOOKUP(AE63,'Cálculos_CGI - SAC FIXA'!A61:K453,6,0),"") -> 555.55556 | AJ63: =IFERROR(VLOOKUP(AE63,[1]Cálculos_PRICE!$A$32:$K$240,11,0),"") -> 966804.1 | AK63: =IFERROR(VLOOKUP(AE63,'Cálculos_CGI - SAC FIXA'!A61:K453,11,0),"") -> 186111.11 | AN63: =AR64-K69 -> 59662.244 | AO63: 26 | AP63: JP | AQ63: 44838 | AR63: 245432.7 | AS63: 214.9 | AT63: 0 | AU63: 3166.08 | AV63: 76.45 | AW63: 3457.43
A64: =IF(IF(AND(A63>0,A63<$I$18),A63+1,0)=0,"",IF(AND(A63>0,A63<$I$18),A63+1,0)) -> 21 | B64: =IFERROR(IF(A64<=$I$18,DATE(YEAR($B$44),MONTH($B$44)+A63,DAY($B$44)),"-"),"") -> 46696 | C64: =IF(A64="","",K63) -> 188888.89 | D64: =C64*$I$20 -> 2058.8889 | E64: =IFERROR(C64+D64,"") -> 190947.78 | F64: =$I$13/$I$18 -> 555.55556 | G64: =IF(A64="","",PMT($I$20,$I$18,$C$44)*-1) -> 2224.912 | H64: =C64*$J$27 -> 43.444444 | I64: =IF(A64="","",IF(K63="","",IF(K63=0,"",$J$28*$I$14))) -> 20 | J64: =IFERROR(SUM(I64+H64+G64),"") -> 2288.3564 | K64: =C64-F64 -> 188333.33 | O64: =IFERROR(F64*$O$39,0) -> 16.666667 | P64: =IF($A64<=$I$18,B64-B63,) -> 31 | Q64: 365 | S64: 5 - MISTO - COMERCIAL / RESIDENCIAL | X64: SIM | Y64: 70 | AA64: =A69 -> 26 | AB64: =IF($AA$36=1,VLOOKUP(AA64,$AE$38:$AK$218,6,0),IF($AA$36=2,VLOOKUP(AA64,$AE$38:$AK$218,4,0),VLOOKUP(AA64,$AE$38:$AK$218,2,0))) -> 16344.728 | AC64: =IF($AA$36=1,VLOOKUP(AA64,$AE$38:$AK$278,7,0),IF($AA$36=2,VLOOKUP(AA64,$AE$38:$AK$278,5,0),VLOOKUP(AA64,$AE$38:$AK$278,3,0))) -> 2287.7175 | AE64: =AA64 -> 26 | AF64: =IFERROR(VLOOKUP(AE64,[1]Cálculos_PRICE!$A$32:$K$212,10,0),"") -> 16344.728 | AG64: =IFERROR(VLOOKUP(AE64,'Cálculos_CGI - SAC FIXA'!A62:K454,10,0),"") -> 2287.7175 | AH64: =IFERROR(VLOOKUP(AE64,[1]Cálculos_PRICE!$A$32:$K$212,6,0),"") -> 1602.1489 | AI64: =IFERROR(VLOOKUP(AE64,'Cálculos_CGI - SAC FIXA'!A62:K454,6,0),"") -> 555.55556 | AJ64: =IFERROR(VLOOKUP(AE64,[1]Cálculos_PRICE!$A$32:$K$240,11,0),"") -> 965201.95 | AK64: =IFERROR(VLOOKUP(AE64,'Cálculos_CGI - SAC FIXA'!A62:K454,11,0),"") -> 185555.56 | AN64: =AR65-K70 -> 60000.13 | AO64: 27 | AP64: JP | AQ64: 44869 | AR64: 245217.8 | AS64: 217.67 | AT64: 0 | AU64: 3163.31 | AV64: 76.4 | AW64: 3457.38
A65: =IF(IF(AND(A64>0,A64<$I$18),A64+1,0)=0,"",IF(AND(A64>0,A64<$I$18),A64+1,0)) -> 22 | B65: =IFERROR(IF(A65<=$I$18,DATE(YEAR($B$44),MONTH($B$44)+A64,DAY($B$44)),"-"),"") -> 46726 | C65: =IF(A65="","",K64) -> 188333.33 | D65: =C65*$I$20 -> 2052.8333 | E65: =IFERROR(C65+D65,"") -> 190386.17 | F65: =$I$13/$I$18 -> 555.55556 | G65: =IF(A65="","",PMT($I$20,$I$18,$C$44)*-1) -> 2224.912 | H65: =C65*$J$27 -> 43.316667 | I65: =IF(A65="","",IF(K64="","",IF(K64=0,"",$J$28*$I$14))) -> 20 | J65: =IFERROR(SUM(I65+H65+G65),"") -> 2288.2286 | K65: =C65-F65 -> 187777.78 | O65: =IFERROR(F65*$O$39,0) -> 16.666667 | P65: =IF($A65<=$I$18,B65-B64,) -> 30 | Q65: 365 | S65: 6 - IMOVEL VERANEIO | X65: NÃO | Y65: 70 | AA65: =A70 -> 27 | AB65: =IF($AA$36=1,VLOOKUP(AA65,$AE$38:$AK$218,6,0),IF($AA$36=2,VLOOKUP(AA65,$AE$38:$AK$218,4,0),VLOOKUP(AA65,$AE$38:$AK$218,2,0))) -> 16344.371 | AC65: =IF($AA$36=1,VLOOKUP(AA65,$AE$38:$AK$278,7,0),IF($AA$36=2,VLOOKUP(AA65,$AE$38:$AK$278,5,0),VLOOKUP(AA65,$AE$38:$AK$278,3,0))) -> 2287.5897 | AE65: =AA65 -> 27 | AF65: =IFERROR(VLOOKUP(AE65,[1]Cálculos_PRICE!$A$32:$K$212,10,0),"") -> 16344.371 | AG65: =IFERROR(VLOOKUP(AE65,'Cálculos_CGI - SAC FIXA'!A63:K455,10,0),"") -> 2287.5897 | AH65: =IFERROR(VLOOKUP(AE65,[1]Cálculos_PRICE!$A$32:$K$212,6,0),"") -> 1626.1812 | AI65: =IFERROR(VLOOKUP(AE65,'Cálculos_CGI - SAC FIXA'!A63:K455,6,0),"") -> 555.55556 | AJ65: =IFERROR(VLOOKUP(AE65,[1]Cálculos_PRICE!$A$32:$K$240,11,0),"") -> 963575.77 | AK65: =IFERROR(VLOOKUP(AE65,'Cálculos_CGI - SAC FIXA'!A63:K455,11,0),"") -> 185000 | AN65: =AR66-K71 -> 60335.206 | AO65: 28 | AP65: JP | AQ65: 44899 | AR65: 245000.13 | AS65: 220.48 | AT65: 0 | AU65: 3160.5 | AV65: 76.35 | AW65: 3457.33
A66: =IF(IF(AND(A65>0,A65<$I$18),A65+1,0)=0,"",IF(AND(A65>0,A65<$I$18),A65+1,0)) -> 23 | B66: =IFERROR(IF(A66<=$I$18,DATE(YEAR($B$44),MONTH($B$44)+A65,DAY($B$44)),"-"),"") -> 46757 | C66: =IF(A66="","",K65) -> 187777.78 | D66: =C66*$I$20 -> 2046.7778 | E66: =IFERROR(C66+D66,"") -> 189824.56 | F66: =$I$13/$I$18 -> 555.55556 | G66: =IF(A66="","",PMT($I$20,$I$18,$C$44)*-1) -> 2224.912 | H66: =C66*$J$27 -> 43.188889 | I66: =IF(A66="","",IF(K65="","",IF(K65=0,"",$J$28*$I$14))) -> 20 | J66: =IFERROR(SUM(I66+H66+G66),"") -> 2288.1009 | K66: =C66-F66 -> 187222.22 | O66: =IFERROR(F66*$O$39,0) -> 16.666667 | P66: =IF($A66<=$I$18,B66-B65,) -> 31 | Q66: 365 | S66: 7 - TERRENO + CONSTRUÇÃO CONCLUÍDA | X66: SIM | Y66: 50 | AA66: =A71 -> 28 | AB66: =IF($AA$36=1,VLOOKUP(AA66,$AE$38:$AK$218,6,0),IF($AA$36=2,VLOOKUP(AA66,$AE$38:$AK$218,4,0),VLOOKUP(AA66,$AE$38:$AK$218,2,0))) -> 16344.01 | AC66: =IF($AA$36=1,VLOOKUP(AA66,$AE$38:$AK$278,7,0),IF($AA$36=2,VLOOKUP(AA66,$AE$38:$AK$278,5,0),VLOOKUP(AA66,$AE$38:$AK$278,3,0))) -> 2287.462 | AE66: =AA66 -> 28 | AF66: =IFERROR(VLOOKUP(AE66,[1]Cálculos_PRICE!$A$32:$K$212,10,0),"") -> 16344.01 | AG66: =IFERROR(VLOOKUP(AE66,'Cálculos_CGI - SAC FIXA'!A64:K456,10,0),"") -> 2287.462 | AH66: =IFERROR(VLOOKUP(AE66,[1]Cálculos_PRICE!$A$32:$K$212,6,0),"") -> 1650.5739 | AI66: =IFERROR(VLOOKUP(AE66,'Cálculos_CGI - SAC FIXA'!A64:K456,6,0),"") -> 555.55556 | AJ66: =IFERROR(VLOOKUP(AE66,[1]Cálculos_PRICE!$A$32:$K$240,11,0),"") -> 961925.19 | AK66: =IFERROR(VLOOKUP(AE66,'Cálculos_CGI - SAC FIXA'!A64:K456,11,0),"") -> 184444.44 | AN66: =AR67-K72 -> 60667.441 | AO66: 29 | AP66: JP | AQ66: 44930 | AR66: 244779.65 | AS66: 223.32 | AT66: 0 | AU66: 3157.66 | AV66: 76.3 | AW66: 3457.28
A67: =IF(IF(AND(A66>0,A66<$I$18),A66+1,0)=0,"",IF(AND(A66>0,A66<$I$18),A66+1,0)) -> 24 | B67: =IFERROR(IF(A67<=$I$18,DATE(YEAR($B$44),MONTH($B$44)+A66,DAY($B$44)),"-"),"") -> 46788 | C67: =IF(A67="","",K66) -> 187222.22 | D67: =C67*$I$20 -> 2040.7222 | E67: =IFERROR(C67+D67,"") -> 189262.94 | F67: =$I$13/$I$18 -> 555.55556 | G67: =IF(A67="","",PMT($I$20,$I$18,$C$44)*-1) -> 2224.912 | H67: =C67*$J$27 -> 43.061111 | I67: =IF(A67="","",IF(K66="","",IF(K66=0,"",$J$28*$I$14))) -> 20 | J67: =IFERROR(SUM(I67+H67+G67),"") -> 2287.9731 | K67: =C67-F67 -> 186666.67 | O67: =IFERROR(F67*$O$39,0) -> 16.666667 | P67: =IF($A67<=$I$18,B67-B66,) -> 31 | Q67: 365 | S67: COBRA IOF | AA67: =A72 -> 29 | AB67: =IF($AA$36=1,VLOOKUP(AA67,$AE$38:$AK$218,6,0),IF($AA$36=2,VLOOKUP(AA67,$AE$38:$AK$218,4,0),VLOOKUP(AA67,$AE$38:$AK$218,2,0))) -> 16343.643 | AC67: =IF($AA$36=1,VLOOKUP(AA67,$AE$38:$AK$278,7,0),IF($AA$36=2,VLOOKUP(AA67,$AE$38:$AK$278,5,0),VLOOKUP(AA67,$AE$38:$AK$278,3,0))) -> 2287.3342 | AE67: =AA67 -> 29 | AF67: =IFERROR(VLOOKUP(AE67,[1]Cálculos_PRICE!$A$32:$K$212,10,0),"") -> 16343.643 | AG67: =IFERROR(VLOOKUP(AE67,'Cálculos_CGI - SAC FIXA'!A65:K457,10,0),"") -> 2287.3342 | AH67: =IFERROR(VLOOKUP(AE67,[1]Cálculos_PRICE!$A$32:$K$212,6,0),"") -> 1675.3325 | AI67: =IFERROR(VLOOKUP(AE67,'Cálculos_CGI - SAC FIXA'!A65:K457,6,0),"") -> 555.55556 | AJ67: =IFERROR(VLOOKUP(AE67,[1]Cálculos_PRICE!$A$32:$K$240,11,0),"") -> 960249.86 | AK67: =IFERROR(VLOOKUP(AE67,'Cálculos_CGI - SAC FIXA'!A65:K457,11,0),"") -> 183888.89 | AN67: =AR68-K73 -> 60996.797 | AO67: 30 | AP67: JP | AQ67: 44961 | AR67: 244556.33 | AS67: 226.2 | AT67: 0 | AU67: 3154.78 | AV67: 76.25 | AW67: 3457.23
A68: =IF(IF(AND(A67>0,A67<$I$18),A67+1,0)=0,"",IF(AND(A67>0,A67<$I$18),A67+1,0)) -> 25 | B68: =IFERROR(IF(A68<=$I$18,DATE(YEAR($B$44),MONTH($B$44)+A67,DAY($B$44)),"-"),"") -> 46817 | C68: =IF(A68="","",K67) -> 186666.67 | D68: =C68*$I$20 -> 2034.6667 | E68: =IFERROR(C68+D68,"") -> 188701.33 | F68: =$I$13/$I$18 -> 555.55556 | G68: =IF(A68="","",PMT($I$20,$I$18,$C$44)*-1) -> 2224.912 | H68: =C68*$J$27 -> 42.933333 | I68: =IF(A68="","",IF(K67="","",IF(K67=0,"",$J$28*$I$14))) -> 20 | J68: =IFERROR(SUM(I68+H68+G68),"") -> 2287.8453 | K68: =C68-F68 -> 186111.11 | O68: =IFERROR(F68*$O$39,0) -> 16.666667 | P68: =IF($A68<=$I$18,B68-B67,) -> 29 | Q68: 365 | S68: CGI | X68: IOF | Y68: LTV | AA68: =A73 -> 30 | AB68: =IF($AA$36=1,VLOOKUP(AA68,$AE$38:$AK$218,6,0),IF($AA$36=2,VLOOKUP(AA68,$AE$38:$AK$218,4,0),VLOOKUP(AA68,$AE$38:$AK$218,2,0))) -> 16343.27 | AC68: =IF($AA$36=1,VLOOKUP(AA68,$AE$38:$AK$278,7,0),IF($AA$36=2,VLOOKUP(AA68,$AE$38:$AK$278,5,0),VLOOKUP(AA68,$AE$38:$AK$278,3,0))) -> 2287.2064 | AE68: =AA68 -> 30 | AF68: =IFERROR(VLOOKUP(AE68,[1]Cálculos_PRICE!$A$32:$K$212,10,0),"") -> 16343.27 | AG68: =IFERROR(VLOOKUP(AE68,'Cálculos_CGI - SAC FIXA'!A66:K458,10,0),"") -> 2287.2064 | AH68: =IFERROR(VLOOKUP(AE68,[1]Cálculos_PRICE!$A$32:$K$212,6,0),"") -> 1700.4625 | AI68: =IFERROR(VLOOKUP(AE68,'Cálculos_CGI - SAC FIXA'!A66:K458,6,0),"") -> 555.55556 | AJ68: =IFERROR(VLOOKUP(AE68,[1]Cálculos_PRICE!$A$32:$K$240,11,0),"") -> 958549.4 | AK68: =IFERROR(VLOOKUP(AE68,'Cálculos_CGI - SAC FIXA'!A66:K458,11,0),"") -> 183333.33 | AN68: =AR69-K74 -> 61323.232 | AO68: 31 | AP68: JP | AQ68: 44989 | AR68: 244330.13 | AS68: 229.12 | AT68: 0 | AU68: 3151.86 | AV68: 76.2 | AW68: 3457.18
A69: =IF(IF(AND(A68>0,A68<$I$18),A68+1,0)=0,"",IF(AND(A68>0,A68<$I$18),A68+1,0)) -> 26 | B69: =IFERROR(IF(A69<=$I$18,DATE(YEAR($B$44),MONTH($B$44)+A68,DAY($B$44)),"-"),"") -> 46848 | C69: =IF(A69="","",K68) -> 186111.11 | D69: =C69*$I$20 -> 2028.6111 | E69: =IFERROR(C69+D69,"") -> 188139.72 | F69: =$I$13/$I$18 -> 555.55556 | G69: =IF(A69="","",PMT($I$20,$I$18,$C$44)*-1) -> 2224.912 | H69: =C69*$J$27 -> 42.805556 | I69: =IF(A69="","",IF(K68="","",IF(K68=0,"",$J$28*$I$14))) -> 20 | J69: =IFERROR(SUM(I69+H69+G69),"") -> 2287.7175 | K69: =C69-F69 -> 185555.56 | O69: =IFERROR(F69*$O$39,0) -> 16.666667 | P69: =IF($A69<=$I$18,B69-B68,) -> 31 | Q69: 365 | S69: 1 - RESIDENCIAL - CASA | X69: SIM | Y69: 60 | AA69: =A74 -> 31 | AB69: =IF($AA$36=1,VLOOKUP(AA69,$AE$38:$AK$218,6,0),IF($AA$36=2,VLOOKUP(AA69,$AE$38:$AK$218,4,0),VLOOKUP(AA69,$AE$38:$AK$218,2,0))) -> 16342.892 | AC69: =IF($AA$36=1,VLOOKUP(AA69,$AE$38:$AK$278,7,0),IF($AA$36=2,VLOOKUP(AA69,$AE$38:$AK$278,5,0),VLOOKUP(AA69,$AE$38:$AK$278,3,0))) -> 2287.0786 | AE69: =AA69 -> 31 | AF69: =IFERROR(VLOOKUP(AE69,[1]Cálculos_PRICE!$A$32:$K$212,10,0),"") -> 16342.892 | AG69: =IFERROR(VLOOKUP(AE69,'Cálculos_CGI - SAC FIXA'!A67:K459,10,0),"") -> 2287.0786 | AH69: =IFERROR(VLOOKUP(AE69,[1]Cálculos_PRICE!$A$32:$K$212,6,0),"") -> 1725.9694 | AI69: =IFERROR(VLOOKUP(AE69,'Cálculos_CGI - SAC FIXA'!A67:K459,6,0),"") -> 555.55556 | AJ69: =IFERROR(VLOOKUP(AE69,[1]Cálculos_PRICE!$A$32:$K$240,11,0),"") -> 956823.43 | AK69: =IFERROR(VLOOKUP(AE69,'Cálculos_CGI - SAC FIXA'!A67:K459,11,0),"") -> 182777.78 | AN69: =AR70-K75 -> 61646.708 | AO69: 32 | AP69: JP | AQ69: 45020 | AR69: 244101.01 | AS69: 232.08 | AT69: 0 | AU69: 3148.9 | AV69: 76.14 | AW69: 3457.12
A70: =IF(IF(AND(A69>0,A69<$I$18),A69+1,0)=0,"",IF(AND(A69>0,A69<$I$18),A69+1,0)) -> 27 | B70: =IFERROR(IF(A70<=$I$18,DATE(YEAR($B$44),MONTH($B$44)+A69,DAY($B$44)),"-"),"") -> 46878 | C70: =IF(A70="","",K69) -> 185555.56 | D70: =C70*$I$20 -> 2022.5556 | E70: =IFERROR(C70+D70,"") -> 187578.11 | F70: =$I$13/$I$18 -> 555.55556 | G70: =IF(A70="","",PMT($I$20,$I$18,$C$44)*-1) -> 2224.912 | H70: =C70*$J$27 -> 42.677778 | I70: =IF(A70="","",IF(K69="","",IF(K69=0,"",$J$28*$I$14))) -> 20 | J70: =IFERROR(SUM(I70+H70+G70),"") -> 2287.5897 | K70: =C70-F70 -> 185000 | O70: =IFERROR(F70*$O$39,0) -> 16.666667 | P70: =IF($A70<=$I$18,B70-B69,) -> 30 | Q70: 365 | S70: 2 - RESIDENCIAL - APARTAMENTO | X70: SIM | Y70: 60 | AA70: =A75 -> 32 | AB70: =IF($AA$36=1,VLOOKUP(AA70,$AE$38:$AK$218,6,0),IF($AA$36=2,VLOOKUP(AA70,$AE$38:$AK$218,4,0),VLOOKUP(AA70,$AE$38:$AK$218,2,0))) -> 16342.508 | AC70: =IF($AA$36=1,VLOOKUP(AA70,$AE$38:$AK$278,7,0),IF($AA$36=2,VLOOKUP(AA70,$AE$38:$AK$278,5,0),VLOOKUP(AA70,$AE$38:$AK$278,3,0))) -> 2286.9509 | AE70: =AA70 -> 32 | AF70: =IFERROR(VLOOKUP(AE70,[1]Cálculos_PRICE!$A$32:$K$212,10,0),"") -> 16342.508 | AG70: =IFERROR(VLOOKUP(AE70,'Cálculos_CGI - SAC FIXA'!A68:K460,10,0),"") -> 2286.9509 | AH70: =IFERROR(VLOOKUP(AE70,[1]Cálculos_PRICE!$A$32:$K$212,6,0),"") -> 1751.859 | AI70: =IFERROR(VLOOKUP(AE70,'Cálculos_CGI - SAC FIXA'!A68:K460,6,0),"") -> 555.55556 | AJ70: =IFERROR(VLOOKUP(AE70,[1]Cálculos_PRICE!$A$32:$K$240,11,0),"") -> 955071.57 | AK70: =IFERROR(VLOOKUP(AE70,'Cálculos_CGI - SAC FIXA'!A68:K460,11,0),"") -> 182222.22 | AN70: =AR71-K76 -> 61967.193 | AO70: 33 | AP70: JP | AQ70: 45050 | AR70: 243868.93 | AS70: 235.07 | AT70: 0 | AU70: 3145.91 | AV70: 76.09 | AW70: 3457.07
A71: =IF(IF(AND(A70>0,A70<$I$18),A70+1,0)=0,"",IF(AND(A70>0,A70<$I$18),A70+1,0)) -> 28 | B71: =IFERROR(IF(A71<=$I$18,DATE(YEAR($B$44),MONTH($B$44)+A70,DAY($B$44)),"-"),"") -> 46909 | C71: =IF(A71="","",K70) -> 185000 | D71: =C71*$I$20 -> 2016.5 | E71: =IFERROR(C71+D71,"") -> 187016.5 | F71: =$I$13/$I$18 -> 555.55556 | G71: =IF(A71="","",PMT($I$20,$I$18,$C$44)*-1) -> 2224.912 | H71: =C71*$J$27 -> 42.55 | I71: =IF(A71="","",IF(K70="","",IF(K70=0,"",$J$28*$I$14))) -> 20 | J71: =IFERROR(SUM(I71+H71+G71),"") -> 2287.462 | K71: =C71-F71 -> 184444.44 | O71: =IFERROR(F71*$O$39,0) -> 16.666667 | P71: =IF($A71<=$I$18,B71-B70,) -> 31 | Q71: 365 | S71: 3 - COMERCIAL - LOJA | X71: SIM | Y71: 60 | AA71: =A76 -> 33 | AB71: =IF($AA$36=1,VLOOKUP(AA71,$AE$38:$AK$218,6,0),IF($AA$36=2,VLOOKUP(AA71,$AE$38:$AK$218,4,0),VLOOKUP(AA71,$AE$38:$AK$218,2,0))) -> 16342.118 | AC71: =IF($AA$36=1,VLOOKUP(AA71,$AE$38:$AK$278,7,0),IF($AA$36=2,VLOOKUP(AA71,$AE$38:$AK$278,5,0),VLOOKUP(AA71,$AE$38:$AK$278,3,0))) -> 2286.8231 | AE71: =AA71 -> 33 | AF71: =IFERROR(VLOOKUP(AE71,[1]Cálculos_PRICE!$A$32:$K$212,10,0),"") -> 16342.118 | AG71: =IFERROR(VLOOKUP(AE71,'Cálculos_CGI - SAC FIXA'!A69:K461,10,0),"") -> 2286.8231 | AH71: =IFERROR(VLOOKUP(AE71,[1]Cálculos_PRICE!$A$32:$K$212,6,0),"") -> 1778.1369 | AI71: =IFERROR(VLOOKUP(AE71,'Cálculos_CGI - SAC FIXA'!A69:K461,6,0),"") -> 555.55556 | AJ71: =IFERROR(VLOOKUP(AE71,[1]Cálculos_PRICE!$A$32:$K$240,11,0),"") -> 953293.43 | AK71: =IFERROR(VLOOKUP(AE71,'Cálculos_CGI - SAC FIXA'!A69:K461,11,0),"") -> 181666.67 | AN71: =AR72-K77 -> 62284.649 | AO71: 34 | AP71: JP | AQ71: 45081 | AR71: 243633.86 | AS71: 238.1 | AT71: 0 | AU71: 3142.88 | AV71: 76.04 | AW71: 3457.02
A72: =IF(IF(AND(A71>0,A71<$I$18),A71+1,0)=0,"",IF(AND(A71>0,A71<$I$18),A71+1,0)) -> 29 | B72: =IFERROR(IF(A72<=$I$18,DATE(YEAR($B$44),MONTH($B$44)+A71,DAY($B$44)),"-"),"") -> 46939 | C72: =IF(A72="","",K71) -> 184444.44 | D72: =C72*$I$20 -> 2010.4444 | E72: =IFERROR(C72+D72,"") -> 186454.89 | F72: =$I$13/$I$18 -> 555.55556 | G72: =IF(A72="","",PMT($I$20,$I$18,$C$44)*-1) -> 2224.912 | H72: =C72*$J$27 -> 42.422222 | I72: =IF(A72="","",IF(K71="","",IF(K71=0,"",$J$28*$I$14))) -> 20 | J72: =IFERROR(SUM(I72+H72+G72),"") -> 2287.3342 | K72: =C72-F72 -> 183888.89 | O72: =IFERROR(F72*$O$39,0) -> 16.666667 | P72: =IF($A72<=$I$18,B72-B71,) -> 30 | Q72: 365 | S72: 4 - COMERCIAL - SALA COMERCIAL | X72: SIM | Y72: 60 | AA72: =A77 -> 34 | AB72: =IF($AA$36=1,VLOOKUP(AA72,$AE$38:$AK$218,6,0),IF($AA$36=2,VLOOKUP(AA72,$AE$38:$AK$218,4,0),VLOOKUP(AA72,$AE$38:$AK$218,2,0))) -> 16341.723 | AC72: =IF($AA$36=1,VLOOKUP(AA72,$AE$38:$AK$278,7,0),IF($AA$36=2,VLOOKUP(AA72,$AE$38:$AK$278,5,0),VLOOKUP(AA72,$AE$38:$AK$278,3,0))) -> 2286.6953 | AE72: =AA72 -> 34 | AF72: =IFERROR(VLOOKUP(AE72,[1]Cálculos_PRICE!$A$32:$K$212,10,0),"") -> 16341.723 | AG72: =IFERROR(VLOOKUP(AE72,'Cálculos_CGI - SAC FIXA'!A70:K462,10,0),"") -> 2286.6953 | AH72: =IFERROR(VLOOKUP(AE72,[1]Cálculos_PRICE!$A$32:$K$212,6,0),"") -> 1804.8089 | AI72: =IFERROR(VLOOKUP(AE72,'Cálculos_CGI - SAC FIXA'!A70:K462,6,0),"") -> 555.55556 | AJ72: =IFERROR(VLOOKUP(AE72,[1]Cálculos_PRICE!$A$32:$K$240,11,0),"") -> 951488.62 | AK72: =IFERROR(VLOOKUP(AE72,'Cálculos_CGI - SAC FIXA'!A70:K462,11,0),"") -> 181111.11 | AN72: =AR73-K78 -> 62599.034 | AO72: 35 | AP72: JP | AQ72: 45111 | AR72: 243395.76 | AS72: 241.17 | AT72: 0 | AU72: 3139.81 | AV72: 75.98 | AW72: 3456.96
A73: =IF(IF(AND(A72>0,A72<$I$18),A72+1,0)=0,"",IF(AND(A72>0,A72<$I$18),A72+1,0)) -> 30 | B73: =IFERROR(IF(A73<=$I$18,DATE(YEAR($B$44),MONTH($B$44)+A72,DAY($B$44)),"-"),"") -> 46970 | C73: =IF(A73="","",K72) -> 183888.89 | D73: =C73*$I$20 -> 2004.3889 | E73: =IFERROR(C73+D73,"") -> 185893.28 | F73: =$I$13/$I$18 -> 555.55556 | G73: =IF(A73="","",PMT($I$20,$I$18,$C$44)*-1) -> 2224.912 | H73: =C73*$J$27 -> 42.294444 | I73: =IF(A73="","",IF(K72="","",IF(K72=0,"",$J$28*$I$14))) -> 20 | J73: =IFERROR(SUM(I73+H73+G73),"") -> 2287.2064 | K73: =C73-F73 -> 183333.33 | O73: =IFERROR(F73*$O$39,0) -> 16.666667 | P73: =IF($A73<=$I$18,B73-B72,) -> 31 | Q73: 365 | S73: 5 - MISTO - COMERCIAL / RESIDENCIAL | X73: SIM | Y73: 60 | AA73: =A78 -> 35 | AB73: =IF($AA$36=1,VLOOKUP(AA73,$AE$38:$AK$218,6,0),IF($AA$36=2,VLOOKUP(AA73,$AE$38:$AK$218,4,0),VLOOKUP(AA73,$AE$38:$AK$218,2,0))) -> 16341.321 | AC73: =IF($AA$36=1,VLOOKUP(AA73,$AE$38:$AK$278,7,0),IF($AA$36=2,VLOOKUP(AA73,$AE$38:$AK$278,5,0),VLOOKUP(AA73,$AE$38:$AK$278,3,0))) -> 2286.5675 | AE73: =AA73 -> 35 | AF73: =IFERROR(VLOOKUP(AE73,[1]Cálculos_PRICE!$A$32:$K$212,10,0),"") -> 16341.321 | AG73: =IFERROR(VLOOKUP(AE73,'Cálculos_CGI - SAC FIXA'!A71:K463,10,0),"") -> 2286.5675 | AH73: =IFERROR(VLOOKUP(AE73,[1]Cálculos_PRICE!$A$32:$K$212,6,0),"") -> 1831.881 | AI73: =IFERROR(VLOOKUP(AE73,'Cálculos_CGI - SAC FIXA'!A71:K463,6,0),"") -> 555.55556 | AJ73: =IFERROR(VLOOKUP(AE73,[1]Cálculos_PRICE!$A$32:$K$240,11,0),"") -> 949656.74 | AK73: =IFERROR(VLOOKUP(AE73,'Cálculos_CGI - SAC FIXA'!A71:K463,11,0),"") -> 180555.56 | AN73: =AR74-K79 -> 62910.3 | AO73: 36 | AP73: JP | AQ73: 45142 | AR73: 243154.59 | AS73: 244.29 | AT73: 0 | AU73: 3136.69 | AV73: 75.93 | AW73: 3456.91
A74: =IF(IF(AND(A73>0,A73<$I$18),A73+1,0)=0,"",IF(AND(A73>0,A73<$I$18),A73+1,0)) -> 31 | B74: =IFERROR(IF(A74<=$I$18,DATE(YEAR($B$44),MONTH($B$44)+A73,DAY($B$44)),"-"),"") -> 47001 | C74: =IF(A74="","",K73) -> 183333.33 | D74: =C74*$I$20 -> 1998.3333 | E74: =IFERROR(C74+D74,"") -> 185331.67 | F74: =$I$13/$I$18 -> 555.55556 | G74: =IF(A74="","",PMT($I$20,$I$18,$C$44)*-1) -> 2224.912 | H74: =C74*$J$27 -> 42.166667 | I74: =IF(A74="","",IF(K73="","",IF(K73=0,"",$J$28*$I$14))) -> 20 | J74: =IFERROR(SUM(I74+H74+G74),"") -> 2287.0786 | K74: =C74-F74 -> 182777.78 | O74: =IFERROR(F74*$O$39,0) -> 16.666667 | P74: =IF($A74<=$I$18,B74-B73,) -> 31 | Q74: 365 | S74: 6 - IMOVEL VERANEIO | X74: SIM | Y74: 60 | AA74: =A79 -> 36 | AB74: =IF($AA$36=1,VLOOKUP(AA74,$AE$38:$AK$218,6,0),IF($AA$36=2,VLOOKUP(AA74,$AE$38:$AK$218,4,0),VLOOKUP(AA74,$AE$38:$AK$218,2,0))) -> 16340.914 | AC74: =IF($AA$36=1,VLOOKUP(AA74,$AE$38:$AK$278,7,0),IF($AA$36=2,VLOOKUP(AA74,$AE$38:$AK$278,5,0),VLOOKUP(AA74,$AE$38:$AK$278,3,0))) -> 2286.4397 | AE74: =AA74 -> 36 | AF74: =IFERROR(VLOOKUP(AE74,[1]Cálculos_PRICE!$A$32:$K$212,10,0),"") -> 16340.914 | AG74: =IFERROR(VLOOKUP(AE74,'Cálculos_CGI - SAC FIXA'!A72:K464,10,0),"") -> 2286.4397 | AH74: =IFERROR(VLOOKUP(AE74,[1]Cálculos_PRICE!$A$32:$K$212,6,0),"") -> 1859.3593 | AI74: =IFERROR(VLOOKUP(AE74,'Cálculos_CGI - SAC FIXA'!A72:K464,6,0),"") -> 555.55556 | AJ74: =IFERROR(VLOOKUP(AE74,[1]Cálculos_PRICE!$A$32:$K$240,11,0),"") -> 947797.38 | AK74: =IFERROR(VLOOKUP(AE74,'Cálculos_CGI - SAC FIXA'!A72:K464,11,0),"") -> 180000 | AN74: =AR75-K80 -> 63218.416 | AO74: 37 | AP74: JP | AQ74: 45173 | AR74: 242910.3 | AS74: 247.44 | AT74: 0 | AU74: 3133.54 | AV74: 75.87 | AW74: 3456.85
A75: =IF(IF(AND(A74>0,A74<$I$18),A74+1,0)=0,"",IF(AND(A74>0,A74<$I$18),A74+1,0)) -> 32 | B75: =IFERROR(IF(A75<=$I$18,DATE(YEAR($B$44),MONTH($B$44)+A74,DAY($B$44)),"-"),"") -> 47031 | C75: =IF(A75="","",K74) -> 182777.78 | D75: =C75*$I$20 -> 1992.2778 | E75: =IFERROR(C75+D75,"") -> 184770.06 | F75: =$I$13/$I$18 -> 555.55556 | G75: =IF(A75="","",PMT($I$20,$I$18,$C$44)*-1) -> 2224.912 | H75: =C75*$J$27 -> 42.038889 | I75: =IF(A75="","",IF(K74="","",IF(K74=0,"",$J$28*$I$14))) -> 20 | J75: =IFERROR(SUM(I75+H75+G75),"") -> 2286.9509 | K75: =C75-F75 -> 182222.22 | O75: =IFERROR(F75*$O$39,0) -> 16.666667 | P75: =IF($A75<=$I$18,B75-B74,) -> 30 | Q75: 365 | S75: 7 - TERRENO + CONSTRUÇÃO CONCLUÍDA | X75: SIM | Y75: 60 | AA75: =A80 -> 37 | AB75: =IF($AA$36=1,VLOOKUP(AA75,$AE$38:$AK$218,6,0),IF($AA$36=2,VLOOKUP(AA75,$AE$38:$AK$218,4,0),VLOOKUP(AA75,$AE$38:$AK$218,2,0))) -> 16340.501 | AC75: =IF($AA$36=1,VLOOKUP(AA75,$AE$38:$AK$278,7,0),IF($AA$36=2,VLOOKUP(AA75,$AE$38:$AK$278,5,0),VLOOKUP(AA75,$AE$38:$AK$278,3,0))) -> 2286.312 | AE75: =AA75 -> 37 | AF75: =IFERROR(VLOOKUP(AE75,[1]Cálculos_PRICE!$A$32:$K$212,10,0),"") -> 16340.501 | AG75: =IFERROR(VLOOKUP(AE75,'Cálculos_CGI - SAC FIXA'!A73:K465,10,0),"") -> 2286.312 | AH75: =IFERROR(VLOOKUP(AE75,[1]Cálculos_PRICE!$A$32:$K$212,6,0),"") -> 1887.2496 | AI75: =IFERROR(VLOOKUP(AE75,'Cálculos_CGI - SAC FIXA'!A73:K465,6,0),"") -> 555.55556 | AJ75: =IFERROR(VLOOKUP(AE75,[1]Cálculos_PRICE!$A$32:$K$240,11,0),"") -> 945910.13 | AK75: =IFERROR(VLOOKUP(AE75,'Cálculos_CGI - SAC FIXA'!A73:K465,11,0),"") -> 179444.44 | AN75: =AR76-K81 -> 63523.341 | AO75: 38 | AP75: JP | AQ75: 45203 | AR75: 242662.86 | AS75: 250.63 | AT75: 0 | AU75: 3130.35 | AV75: 75.81 | AW75: 3456.79
A76: =IF(IF(AND(A75>0,A75<$I$18),A75+1,0)=0,"",IF(AND(A75>0,A75<$I$18),A75+1,0)) -> 33 | B76: =IFERROR(IF(A76<=$I$18,DATE(YEAR($B$44),MONTH($B$44)+A75,DAY($B$44)),"-"),"") -> 47062 | C76: =IF(A76="","",K75) -> 182222.22 | D76: =C76*$I$20 -> 1986.2222 | E76: =IFERROR(C76+D76,"") -> 184208.44 | F76: =$I$13/$I$18 -> 555.55556 | G76: =IF(A76="","",PMT($I$20,$I$18,$C$44)*-1) -> 2224.912 | H76: =C76*$J$27 -> 41.911111 | I76: =IF(A76="","",IF(K75="","",IF(K75=0,"",$J$28*$I$14))) -> 20 | J76: =IFERROR(SUM(I76+H76+G76),"") -> 2286.8231 | K76: =C76-F76 -> 181666.67 | O76: =IFERROR(F76*$O$39,0) -> 16.666667 | P76: =IF($A76<=$I$18,B76-B75,) -> 31 | Q76: 365 | AA76: =A81 -> 38 | AB76: =IF($AA$36=1,VLOOKUP(AA76,$AE$38:$AK$218,6,0),IF($AA$36=2,VLOOKUP(AA76,$AE$38:$AK$218,4,0),VLOOKUP(AA76,$AE$38:$AK$218,2,0))) -> 16340.081 | AC76: =IF($AA$36=1,VLOOKUP(AA76,$AE$38:$AK$278,7,0),IF($AA$36=2,VLOOKUP(AA76,$AE$38:$AK$278,5,0),VLOOKUP(AA76,$AE$38:$AK$278,3,0))) -> 2286.1842 | AE76: =AA76 -> 38 | AF76: =IFERROR(VLOOKUP(AE76,[1]Cálculos_PRICE!$A$32:$K$212,10,0),"") -> 16340.081 | AG76: =IFERROR(VLOOKUP(AE76,'Cálculos_CGI - SAC FIXA'!A74:K466,10,0),"") -> 2286.1842 | AH76: =IFERROR(VLOOKUP(AE76,[1]Cálculos_PRICE!$A$32:$K$212,6,0),"") -> 1915.5584 | AI76: =IFERROR(VLOOKUP(AE76,'Cálculos_CGI - SAC FIXA'!A74:K466,6,0),"") -> 555.55556 | AJ76: =IFERROR(VLOOKUP(AE76,[1]Cálculos_PRICE!$A$32:$K$240,11,0),"") -> 943994.58 | AK76: =IFERROR(VLOOKUP(AE76,'Cálculos_CGI - SAC FIXA'!A74:K466,11,0),"") -> 178888.89 | AN76: =AR77-K82 -> 63825.037 | AO76: 39 | AP76: JP | AQ76: 45234 | AR76: 242412.23 | AS76: 253.86 | AT76: 0 | AU76: 3127.12 | AV76: 75.75 | AW76: 3456.73
A77: =IF(IF(AND(A76>0,A76<$I$18),A76+1,0)=0,"",IF(AND(A76>0,A76<$I$18),A76+1,0)) -> 34 | B77: =IFERROR(IF(A77<=$I$18,DATE(YEAR($B$44),MONTH($B$44)+A76,DAY($B$44)),"-"),"") -> 47092 | C77: =IF(A77="","",K76) -> 181666.67 | D77: =C77*$I$20 -> 1980.1667 | E77: =IFERROR(C77+D77,"") -> 183646.83 | F77: =$I$13/$I$18 -> 555.55556 | G77: =IF(A77="","",PMT($I$20,$I$18,$C$44)*-1) -> 2224.912 | H77: =C77*$J$27 -> 41.783333 | I77: =IF(A77="","",IF(K76="","",IF(K76=0,"",$J$28*$I$14))) -> 20 | J77: =IFERROR(SUM(I77+H77+G77),"") -> 2286.6953 | K77: =C77-F77 -> 181111.11 | O77: =IFERROR(F77*$O$39,0) -> 16.666667 | P77: =IF($A77<=$I$18,B77-B76,) -> 30 | Q77: 365 | AA77: =A82 -> 39 | AB77: =IF($AA$36=1,VLOOKUP(AA77,$AE$38:$AK$218,6,0),IF($AA$36=2,VLOOKUP(AA77,$AE$38:$AK$218,4,0),VLOOKUP(AA77,$AE$38:$AK$218,2,0))) -> 16339.655 | AC77: =IF($AA$36=1,VLOOKUP(AA77,$AE$38:$AK$278,7,0),IF($AA$36=2,VLOOKUP(AA77,$AE$38:$AK$278,5,0),VLOOKUP(AA77,$AE$38:$AK$278,3,0))) -> 2286.0564 | AE77: =AA77 -> 39 | AF77: =IFERROR(VLOOKUP(AE77,[1]Cálculos_PRICE!$A$32:$K$212,10,0),"") -> 16339.655 | AG77: =IFERROR(VLOOKUP(AE77,'Cálculos_CGI - SAC FIXA'!A75:K467,10,0),"") -> 2286.0564 | AH77: =IFERROR(VLOOKUP(AE77,[1]Cálculos_PRICE!$A$32:$K$212,6,0),"") -> 1944.2918 | AI77: =IFERROR(VLOOKUP(AE77,'Cálculos_CGI - SAC FIXA'!A75:K467,6,0),"") -> 555.55556 | AJ77: =IFERROR(VLOOKUP(AE77,[1]Cálculos_PRICE!$A$32:$K$240,11,0),"") -> 942050.28 | AK77: =IFERROR(VLOOKUP(AE77,'Cálculos_CGI - SAC FIXA'!A75:K467,11,0),"") -> 178333.33 | AN77: =AR78-K83 -> 64123.452 | AO77: 40 | AP77: JP | AQ77: 45264 | AR77: 242158.37 | AS77: 257.14 | AT77: 0 | AU77: 3123.84 | AV77: 75.7 | AW77: 3456.68
A78: =IF(IF(AND(A77>0,A77<$I$18),A77+1,0)=0,"",IF(AND(A77>0,A77<$I$18),A77+1,0)) -> 35 | B78: =IFERROR(IF(A78<=$I$18,DATE(YEAR($B$44),MONTH($B$44)+A77,DAY($B$44)),"-"),"") -> 47123 | C78: =IF(A78="","",K77) -> 181111.11 | D78: =C78*$I$20 -> 1974.1111 | E78: =IFERROR(C78+D78,"") -> 183085.22 | F78: =$I$13/$I$18 -> 555.55556 | G78: =IF(A78="","",PMT($I$20,$I$18,$C$44)*-1) -> 2224.912 | H78: =C78*$J$27 -> 41.655556 | I78: =IF(A78="","",IF(K77="","",IF(K77=0,"",$J$28*$I$14))) -> 20 | J78: =IFERROR(SUM(I78+H78+G78),"") -> 2286.5675 | K78: =C78-F78 -> 180555.56 | O78: =IFERROR(F78*$O$39,0) -> 16.666667 | P78: =IF($A78<=$I$18,B78-B77,) -> 31 | Q78: 365 | AA78: =A83 -> 40 | AB78: =IF($AA$36=1,VLOOKUP(AA78,$AE$38:$AK$218,6,0),IF($AA$36=2,VLOOKUP(AA78,$AE$38:$AK$218,4,0),VLOOKUP(AA78,$AE$38:$AK$218,2,0))) -> 16339.222 | AC78: =IF($AA$36=1,VLOOKUP(AA78,$AE$38:$AK$278,7,0),IF($AA$36=2,VLOOKUP(AA78,$AE$38:$AK$278,5,0),VLOOKUP(AA78,$AE$38:$AK$278,3,0))) -> 2285.9286 | AE78: =AA78 -> 40 | AF78: =IFERROR(VLOOKUP(AE78,[1]Cálculos_PRICE!$A$32:$K$212,10,0),"") -> 16339.222 | AG78: =IFERROR(VLOOKUP(AE78,'Cálculos_CGI - SAC FIXA'!A76:K468,10,0),"") -> 2285.9286 | AH78: =IFERROR(VLOOKUP(AE78,[1]Cálculos_PRICE!$A$32:$K$212,6,0),"") -> 1973.4561 | AI78: =IFERROR(VLOOKUP(AE78,'Cálculos_CGI - SAC FIXA'!A76:K468,6,0),"") -> 555.55556 | AJ78: =IFERROR(VLOOKUP(AE78,[1]Cálculos_PRICE!$A$32:$K$240,11,0),"") -> 940076.83 | AK78: =IFERROR(VLOOKUP(AE78,'Cálculos_CGI - SAC FIXA'!A76:K468,11,0),"") -> 177777.78 | AN78: =AR79-K84 -> 64418.558 | AO78: 41 | AP78: JP | AQ78: 45295 | AR78: 241901.23 | AS78: 260.45 | AT78: 0 | AU78: 3120.53 | AV78: 75.64 | AW78: 3456.62
A79: =IF(IF(AND(A78>0,A78<$I$18),A78+1,0)=0,"",IF(AND(A78>0,A78<$I$18),A78+1,0)) -> 36 | B79: =IFERROR(IF(A79<=$I$18,DATE(YEAR($B$44),MONTH($B$44)+A78,DAY($B$44)),"-"),"") -> 47154 | C79: =IF(A79="","",K78) -> 180555.56 | D79: =C79*$I$20 -> 1968.0556 | E79: =IFERROR(C79+D79,"") -> 182523.61 | F79: =$I$13/$I$18 -> 555.55556 | G79: =IF(A79="","",PMT($I$20,$I$18,$C$44)*-1) -> 2224.912 | H79: =C79*$J$27 -> 41.527778 | I79: =IF(A79="","",IF(K78="","",IF(K78=0,"",$J$28*$I$14))) -> 20 | J79: =IFERROR(SUM(I79+H79+G79),"") -> 2286.4397 | K79: =C79-F79 -> 180000 | O79: =IFERROR(F79*$O$39,0) -> 16.666667 | P79: =IF($A79<=$I$18,B79-B78,) -> 31 | Q79: 365 | AA79: =A84 -> 41 | AB79: =IF($AA$36=1,VLOOKUP(AA79,$AE$38:$AK$218,6,0),IF($AA$36=2,VLOOKUP(AA79,$AE$38:$AK$218,4,0),VLOOKUP(AA79,$AE$38:$AK$218,2,0))) -> 16338.783 | AC79: =IF($AA$36=1,VLOOKUP(AA79,$AE$38:$AK$278,7,0),IF($AA$36=2,VLOOKUP(AA79,$AE$38:$AK$278,5,0),VLOOKUP(AA79,$AE$38:$AK$278,3,0))) -> 2285.8009 | AE79: =AA79 -> 41 | AF79: =IFERROR(VLOOKUP(AE79,[1]Cálculos_PRICE!$A$32:$K$212,10,0),"") -> 16338.783 | AG79: =IFERROR(VLOOKUP(AE79,'Cálculos_CGI - SAC FIXA'!A77:K469,10,0),"") -> 2285.8009 | AH79: =IFERROR(VLOOKUP(AE79,[1]Cálculos_PRICE!$A$32:$K$212,6,0),"") -> 2003.058 | AI79: =IFERROR(VLOOKUP(AE79,'Cálculos_CGI - SAC FIXA'!A77:K469,6,0),"") -> 555.55556 | AJ79: =IFERROR(VLOOKUP(AE79,[1]Cálculos_PRICE!$A$32:$K$240,11,0),"") -> 938073.77 | AK79: =IFERROR(VLOOKUP(AE79,'Cálculos_CGI - SAC FIXA'!A77:K469,11,0),"") -> 177222.22 | AN79: =AR80-K85 -> 64710.303 | AO79: 42 | AP79: JP | AQ79: 45326 | AR79: 241640.78 | AS79: 263.81 | AT79: 0 | AU79: 3117.17 | AV79: 75.58 | AW79: 3456.56
A80: =IF(IF(AND(A79>0,A79<$I$18),A79+1,0)=0,"",IF(AND(A79>0,A79<$I$18),A79+1,0)) -> 37 | B80: =IFERROR(IF(A80<=$I$18,DATE(YEAR($B$44),MONTH($B$44)+A79,DAY($B$44)),"-"),"") -> 47182 | C80: =IF(A80="","",K79) -> 180000 | D80: =C80*$I$20 -> 1962 | E80: =IFERROR(C80+D80,"") -> 181962 | F80: =$I$13/$I$18 -> 555.55556 | G80: =IF(A80="","",PMT($I$20,$I$18,$C$44)*-1) -> 2224.912 | H80: =C80*$J$27 -> 41.4 | I80: =IF(A80="","",IF(K79="","",IF(K79=0,"",$J$28*$I$14))) -> 20 | J80: =IFERROR(SUM(I80+H80+G80),"") -> 2286.312 | K80: =C80-F80 -> 179444.44 | O80: =IFERROR(F80*$O$39,0) -> 16.666667 | P80: =IF($A80<=$I$18,B80-B79,) -> 28 | Q80: 365 | AA80: =A85 -> 42 | AB80: =IF($AA$36=1,VLOOKUP(AA80,$AE$38:$AK$218,6,0),IF($AA$36=2,VLOOKUP(AA80,$AE$38:$AK$218,4,0),VLOOKUP(AA80,$AE$38:$AK$218,2,0))) -> 16338.338 | AC80: =IF($AA$36=1,VLOOKUP(AA80,$AE$38:$AK$278,7,0),IF($AA$36=2,VLOOKUP(AA80,$AE$38:$AK$278,5,0),VLOOKUP(AA80,$AE$38:$AK$278,3,0))) -> 2285.6731 | AE80: =AA80 -> 42 | AF80: =IFERROR(VLOOKUP(AE80,[1]Cálculos_PRICE!$A$32:$K$212,10,0),"") -> 16338.338 | AG80: =IFERROR(VLOOKUP(AE80,'Cálculos_CGI - SAC FIXA'!A78:K470,10,0),"") -> 2285.6731 | AH80: =IFERROR(VLOOKUP(AE80,[1]Cálculos_PRICE!$A$32:$K$212,6,0),"") -> 2033.1039 | AI80: =IFERROR(VLOOKUP(AE80,'Cálculos_CGI - SAC FIXA'!A78:K470,6,0),"") -> 555.55556 | AJ80: =IFERROR(VLOOKUP(AE80,[1]Cálculos_PRICE!$A$32:$K$240,11,0),"") -> 936040.67 | AK80: =IFERROR(VLOOKUP(AE80,'Cálculos_CGI - SAC FIXA'!A78:K470,11,0),"") -> 176666.67 | AN80: =AR81-K86 -> 64998.639 | AO80: 43 | AP80: JP | AQ80: 45355 | AR80: 241376.97 | AS80: 267.22 | AT80: 0 | AU80: 3113.76 | AV80: 75.52 | AW80: 3456.5
A81: =IF(IF(AND(A80>0,A80<$I$18),A80+1,0)=0,"",IF(AND(A80>0,A80<$I$18),A80+1,0)) -> 38 | B81: =IFERROR(IF(A81<=$I$18,DATE(YEAR($B$44),MONTH($B$44)+A80,DAY($B$44)),"-"),"") -> 47213 | C81: =IF(A81="","",K80) -> 179444.44 | D81: =C81*$I$20 -> 1955.9444 | E81: =IFERROR(C81+D81,"") -> 181400.39 | F81: =$I$13/$I$18 -> 555.55556 | G81: =IF(A81="","",PMT($I$20,$I$18,$C$44)*-1) -> 2224.912 | H81: =C81*$J$27 -> 41.272222 | I81: =IF(A81="","",IF(K80="","",IF(K80=0,"",$J$28*$I$14))) -> 20 | J81: =IFERROR(SUM(I81+H81+G81),"") -> 2286.1842 | K81: =C81-F81 -> 178888.89 | O81: =IFERROR(F81*$O$39,0) -> 16.666667 | P81: =IF($A81<=$I$18,B81-B80,) -> 31 | Q81: 365 | AA81: =A86 -> 43 | AB81: =IF($AA$36=1,VLOOKUP(AA81,$AE$38:$AK$218,6,0),IF($AA$36=2,VLOOKUP(AA81,$AE$38:$AK$218,4,0),VLOOKUP(AA81,$AE$38:$AK$218,2,0))) -> 16337.886 | AC81: =IF($AA$36=1,VLOOKUP(AA81,$AE$38:$AK$278,7,0),IF($AA$36=2,VLOOKUP(AA81,$AE$38:$AK$278,5,0),VLOOKUP(AA81,$AE$38:$AK$278,3,0))) -> 2285.5453 | AE81: =AA81 -> 43 | AF81: =IFERROR(VLOOKUP(AE81,[1]Cálculos_PRICE!$A$32:$K$212,10,0),"") -> 16337.886 | AG81: =IFERROR(VLOOKUP(AE81,'Cálculos_CGI - SAC FIXA'!A79:K471,10,0),"") -> 2285.5453 | AH81: =IFERROR(VLOOKUP(AE81,[1]Cálculos_PRICE!$A$32:$K$212,6,0),"") -> 2063.6004 | AI81: =IFERROR(VLOOKUP(AE81,'Cálculos_CGI - SAC FIXA'!A79:K471,6,0),"") -> 555.55556 | AJ81: =IFERROR(VLOOKUP(AE81,[1]Cálculos_PRICE!$A$32:$K$240,11,0),"") -> 933977.07 | AK81: =IFERROR(VLOOKUP(AE81,'Cálculos_CGI - SAC FIXA'!A79:K471,11,0),"") -> 176111.11 | AN81: =AR82-K87 -> 65283.534 | AO81: 44 | AP81: JP | AQ81: 45386 | AR81: 241109.75 | AS81: 270.66 | AT81: 0 | AU81: 3110.32 | AV81: 75.46 | AW81: 3456.44
A82: =IF(IF(AND(A81>0,A81<$I$18),A81+1,0)=0,"",IF(AND(A81>0,A81<$I$18),A81+1,0)) -> 39 | B82: =IFERROR(IF(A82<=$I$18,DATE(YEAR($B$44),MONTH($B$44)+A81,DAY($B$44)),"-"),"") -> 47243 | C82: =IF(A82="","",K81) -> 178888.89 | D82: =C82*$I$20 -> 1949.8889 | E82: =IFERROR(C82+D82,"") -> 180838.78 | F82: =$I$13/$I$18 -> 555.55556 | G82: =IF(A82="","",PMT($I$20,$I$18,$C$44)*-1) -> 2224.912 | H82: =C82*$J$27 -> 41.144444 | I82: =IF(A82="","",IF(K81="","",IF(K81=0,"",$J$28*$I$14))) -> 20 | J82: =IFERROR(SUM(I82+H82+G82),"") -> 2286.0564 | K82: =C82-F82 -> 178333.33 | O82: =IFERROR(F82*$O$39,0) -> 16.666667 | P82: =IF($A82<=$I$18,B82-B81,) -> 30 | Q82: 365 | AA82: =A87 -> 44 | AB82: =IF($AA$36=1,VLOOKUP(AA82,$AE$38:$AK$218,6,0),IF($AA$36=2,VLOOKUP(AA82,$AE$38:$AK$218,4,0),VLOOKUP(AA82,$AE$38:$AK$218,2,0))) -> 16337.427 | AC82: =IF($AA$36=1,VLOOKUP(AA82,$AE$38:$AK$278,7,0),IF($AA$36=2,VLOOKUP(AA82,$AE$38:$AK$278,5,0),VLOOKUP(AA82,$AE$38:$AK$278,3,0))) -> 2285.4175 | AE82: =AA82 -> 44 | AF82: =IFERROR(VLOOKUP(AE82,[1]Cálculos_PRICE!$A$32:$K$212,10,0),"") -> 16337.427 | AG82: =IFERROR(VLOOKUP(AE82,'Cálculos_CGI - SAC FIXA'!A80:K472,10,0),"") -> 2285.4175 | AH82: =IFERROR(VLOOKUP(AE82,[1]Cálculos_PRICE!$A$32:$K$212,6,0),"") -> 2094.5544 | AI82: =IFERROR(VLOOKUP(AE82,'Cálculos_CGI - SAC FIXA'!A80:K472,6,0),"") -> 555.55556 | AJ82: =IFERROR(VLOOKUP(AE82,[1]Cálculos_PRICE!$A$32:$K$240,11,0),"") -> 931882.51 | AK82: =IFERROR(VLOOKUP(AE82,'Cálculos_CGI - SAC FIXA'!A80:K472,11,0),"") -> 175555.56 | AN82: =AR83-K88 -> 65564.93 | AO82: 45 | AP82: JP | AQ82: 45416 | AR82: 240839.09 | AS82: 274.16 | AT82: 0 | AU82: 3106.82 | AV82: 75.39 | AW82: 3456.37
A83: =IF(IF(AND(A82>0,A82<$I$18),A82+1,0)=0,"",IF(AND(A82>0,A82<$I$18),A82+1,0)) -> 40 | B83: =IFERROR(IF(A83<=$I$18,DATE(YEAR($B$44),MONTH($B$44)+A82,DAY($B$44)),"-"),"") -> 47274 | C83: =IF(A83="","",K82) -> 178333.33 | D83: =C83*$I$20 -> 1943.8333 | E83: =IFERROR(C83+D83,"") -> 180277.17 | F83: =$I$13/$I$18 -> 555.55556 | G83: =IF(A83="","",PMT($I$20,$I$18,$C$44)*-1) -> 2224.912 | H83: =C83*$J$27 -> 41.016667 | I83: =IF(A83="","",IF(K82="","",IF(K82=0,"",$J$28*$I$14))) -> 20 | J83: =IFERROR(SUM(I83+H83+G83),"") -> 2285.9286 | K83: =C83-F83 -> 177777.78 | O83: =IFERROR(F83*$O$39,0) -> 16.666667 | P83: =IF($A83<=$I$18,B83-B82,) -> 31 | Q83: 365 | AA83: =A88 -> 45 | AB83: =IF($AA$36=1,VLOOKUP(AA83,$AE$38:$AK$218,6,0),IF($AA$36=2,VLOOKUP(AA83,$AE$38:$AK$218,4,0),VLOOKUP(AA83,$AE$38:$AK$218,2,0))) -> 16336.961 | AC83: =IF($AA$36=1,VLOOKUP(AA83,$AE$38:$AK$278,7,0),IF($AA$36=2,VLOOKUP(AA83,$AE$38:$AK$278,5,0),VLOOKUP(AA83,$AE$38:$AK$278,3,0))) -> 2285.2897 | AE83: =AA83 -> 45 | AF83: =IFERROR(VLOOKUP(AE83,[1]Cálculos_PRICE!$A$32:$K$212,10,0),"") -> 16336.961 | AG83: =IFERROR(VLOOKUP(AE83,'Cálculos_CGI - SAC FIXA'!A81:K473,10,0),"") -> 2285.2897 | AH83: =IFERROR(VLOOKUP(AE83,[1]Cálculos_PRICE!$A$32:$K$212,6,0),"") -> 2125.9727 | AI83: =IFERROR(VLOOKUP(AE83,'Cálculos_CGI - SAC FIXA'!A81:K473,6,0),"") -> 555.55556 | AJ83: =IFERROR(VLOOKUP(AE83,[1]Cálculos_PRICE!$A$32:$K$240,11,0),"") -> 929756.54 | AK83: =IFERROR(VLOOKUP(AE83,'Cálculos_CGI - SAC FIXA'!A81:K473,11,0),"") -> 175000 | AN83: =AR84-K89 -> 65842.796 | AO83: 46 | AP83: JP | AQ83: 45447 | AR83: 240564.93 | AS83: 277.69 | AT83: 0 | AU83: 3103.29 | AV83: 75.33 | AW83: 3456.31
A84: =IF(IF(AND(A83>0,A83<$I$18),A83+1,0)=0,"",IF(AND(A83>0,A83<$I$18),A83+1,0)) -> 41 | B84: =IFERROR(IF(A84<=$I$18,DATE(YEAR($B$44),MONTH($B$44)+A83,DAY($B$44)),"-"),"") -> 47304 | C84: =IF(A84="","",K83) -> 177777.78 | D84: =C84*$I$20 -> 1937.7778 | E84: =IFERROR(C84+D84,"") -> 179715.56 | F84: =$I$13/$I$18 -> 555.55556 | G84: =IF(A84="","",PMT($I$20,$I$18,$C$44)*-1) -> 2224.912 | H84: =C84*$J$27 -> 40.888889 | I84: =IF(A84="","",IF(K83="","",IF(K83=0,"",$J$28*$I$14))) -> 20 | J84: =IFERROR(SUM(I84+H84+G84),"") -> 2285.8009 | K84: =C84-F84 -> 177222.22 | O84: =IFERROR(F84*$O$39,0) -> 16.666667 | P84: =IF($A84<=$I$18,B84-B83,) -> 30 | Q84: 365 | AA84: =A89 -> 46 | AB84: =IF($AA$36=1,VLOOKUP(AA84,$AE$38:$AK$218,6,0),IF($AA$36=2,VLOOKUP(AA84,$AE$38:$AK$218,4,0),VLOOKUP(AA84,$AE$38:$AK$218,2,0))) -> 16336.488 | AC84: =IF($AA$36=1,VLOOKUP(AA84,$AE$38:$AK$278,7,0),IF($AA$36=2,VLOOKUP(AA84,$AE$38:$AK$278,5,0),VLOOKUP(AA84,$AE$38:$AK$278,3,0))) -> 2285.162 | AE84: =AA84 -> 46 | AF84: =IFERROR(VLOOKUP(AE84,[1]Cálculos_PRICE!$A$32:$K$212,10,0),"") -> 16336.488 | AG84: =IFERROR(VLOOKUP(AE84,'Cálculos_CGI - SAC FIXA'!A82:K474,10,0),"") -> 2285.162 | AH84: =IFERROR(VLOOKUP(AE84,[1]Cálculos_PRICE!$A$32:$K$212,6,0),"") -> 2157.8623 | AI84: =IFERROR(VLOOKUP(AE84,'Cálculos_CGI - SAC FIXA'!A82:K474,6,0),"") -> 555.55556 | AJ84: =IFERROR(VLOOKUP(AE84,[1]Cálculos_PRICE!$A$32:$K$240,11,0),"") -> 927598.68 | AK84: =IFERROR(VLOOKUP(AE84,'Cálculos_CGI - SAC FIXA'!A82:K474,11,0),"") -> 174444.44 | AN84: =AR85-K90 -> 66117.081 | AO84: 47 | AP84: JP | AQ84: 45477 | AR84: 240287.24 | AS84: 281.27 | AT84: 0 | AU84: 3099.71 | AV84: 75.27 | AW84: 3456.25
A85: =IF(IF(AND(A84>0,A84<$I$18),A84+1,0)=0,"",IF(AND(A84>0,A84<$I$18),A84+1,0)) -> 42 | B85: =IFERROR(IF(A85<=$I$18,DATE(YEAR($B$44),MONTH($B$44)+A84,DAY($B$44)),"-"),"") -> 47335 | C85: =IF(A85="","",K84) -> 177222.22 | D85: =C85*$I$20 -> 1931.7222 | E85: =IFERROR(C85+D85,"") -> 179153.94 | F85: =$I$13/$I$18 -> 555.55556 | G85: =IF(A85="","",PMT($I$20,$I$18,$C$44)*-1) -> 2224.912 | H85: =C85*$J$27 -> 40.761111 | I85: =IF(A85="","",IF(K84="","",IF(K84=0,"",$J$28*$I$14))) -> 20 | J85: =IFERROR(SUM(I85+H85+G85),"") -> 2285.6731 | K85: =C85-F85 -> 176666.67 | O85: =IFERROR(F85*$O$39,0) -> 16.666667 | P85: =IF($A85<=$I$18,B85-B84,) -> 31 | Q85: 365 | AA85: =A90 -> 47 | AB85: =IF($AA$36=1,VLOOKUP(AA85,$AE$38:$AK$218,6,0),IF($AA$36=2,VLOOKUP(AA85,$AE$38:$AK$218,4,0),VLOOKUP(AA85,$AE$38:$AK$218,2,0))) -> 16336.008 | AC85: =IF($AA$36=1,VLOOKUP(AA85,$AE$38:$AK$278,7,0),IF($AA$36=2,VLOOKUP(AA85,$AE$38:$AK$278,5,0),VLOOKUP(AA85,$AE$38:$AK$278,3,0))) -> 2285.0342 | AE85: =AA85 -> 47 | AF85: =IFERROR(VLOOKUP(AE85,[1]Cálculos_PRICE!$A$32:$K$212,10,0),"") -> 16336.008 | AG85: =IFERROR(VLOOKUP(AE85,'Cálculos_CGI - SAC FIXA'!A83:K475,10,0),"") -> 2285.0342 | AH85: =IFERROR(VLOOKUP(AE85,[1]Cálculos_PRICE!$A$32:$K$212,6,0),"") -> 2190.2303 | AI85: =IFERROR(VLOOKUP(AE85,'Cálculos_CGI - SAC FIXA'!A83:K475,6,0),"") -> 555.55556 | AJ85: =IFERROR(VLOOKUP(AE85,[1]Cálculos_PRICE!$A$32:$K$240,11,0),"") -> 925408.45 | AK85: =IFERROR(VLOOKUP(AE85,'Cálculos_CGI - SAC FIXA'!A83:K475,11,0),"") -> 173888.89 | AN85: =AR86-K91 -> 66387.737 | AO85: 48 | AP85: JP | AQ85: 45508 | AR85: 240005.97 | AS85: 284.9 | AT85: 0 | AU85: 3096.08 | AV85: 75.2 | AW85: 3456.18
A86: =IF(IF(AND(A85>0,A85<$I$18),A85+1,0)=0,"",IF(AND(A85>0,A85<$I$18),A85+1,0)) -> 43 | B86: =IFERROR(IF(A86<=$I$18,DATE(YEAR($B$44),MONTH($B$44)+A85,DAY($B$44)),"-"),"") -> 47366 | C86: =IF(A86="","",K85) -> 176666.67 | D86: =C86*$I$20 -> 1925.6667 | E86: =IFERROR(C86+D86,"") -> 178592.33 | F86: =$I$13/$I$18 -> 555.55556 | G86: =IF(A86="","",PMT($I$20,$I$18,$C$44)*-1) -> 2224.912 | H86: =C86*$J$27 -> 40.633333 | I86: =IF(A86="","",IF(K85="","",IF(K85=0,"",$J$28*$I$14))) -> 20 | J86: =IFERROR(SUM(I86+H86+G86),"") -> 2285.5453 | K86: =C86-F86 -> 176111.11 | O86: =IFERROR(F86*$O$39,0) -> 16.666667 | P86: =IF($A86<=$I$18,B86-B85,) -> 31 | Q86: 365 | AA86: =A91 -> 48 | AB86: =IF($AA$36=1,VLOOKUP(AA86,$AE$38:$AK$218,6,0),IF($AA$36=2,VLOOKUP(AA86,$AE$38:$AK$218,4,0),VLOOKUP(AA86,$AE$38:$AK$218,2,0))) -> 16335.521 | AC86: =IF($AA$36=1,VLOOKUP(AA86,$AE$38:$AK$278,7,0),IF($AA$36=2,VLOOKUP(AA86,$AE$38:$AK$278,5,0),VLOOKUP(AA86,$AE$38:$AK$278,3,0))) -> 2284.9064 | AE86: =AA86 -> 48 | AF86: =IFERROR(VLOOKUP(AE86,[1]Cálculos_PRICE!$A$32:$K$212,10,0),"") -> 16335.521 | AG86: =IFERROR(VLOOKUP(AE86,'Cálculos_CGI - SAC FIXA'!A84:K476,10,0),"") -> 2284.9064 | AH86: =IFERROR(VLOOKUP(AE86,[1]Cálculos_PRICE!$A$32:$K$212,6,0),"") -> 2223.0837 | AI86: =IFERROR(VLOOKUP(AE86,'Cálculos_CGI - SAC FIXA'!A84:K476,6,0),"") -> 555.55556 | AJ86: =IFERROR(VLOOKUP(AE86,[1]Cálculos_PRICE!$A$32:$K$240,11,0),"") -> 923185.36 | AK86: =IFERROR(VLOOKUP(AE86,'Cálculos_CGI - SAC FIXA'!A84:K476,11,0),"") -> 173333.33 | AN86: =AR87-K92 -> 66654.712 | AO86: 49 | AP86: JP | AQ86: 45539 | AR86: 239721.07 | AS86: 288.58 | AT86: 0 | AU86: 3092.4 | AV86: 75.14 | AW86: 3456.12
A87: =IF(IF(AND(A86>0,A86<$I$18),A86+1,0)=0,"",IF(AND(A86>0,A86<$I$18),A86+1,0)) -> 44 | B87: =IFERROR(IF(A87<=$I$18,DATE(YEAR($B$44),MONTH($B$44)+A86,DAY($B$44)),"-"),"") -> 47396 | C87: =IF(A87="","",K86) -> 176111.11 | D87: =C87*$I$20 -> 1919.6111 | E87: =IFERROR(C87+D87,"") -> 178030.72 | F87: =$I$13/$I$18 -> 555.55556 | G87: =IF(A87="","",PMT($I$20,$I$18,$C$44)*-1) -> 2224.912 | H87: =C87*$J$27 -> 40.505556 | I87: =IF(A87="","",IF(K86="","",IF(K86=0,"",$J$28*$I$14))) -> 20 | J87: =IFERROR(SUM(I87+H87+G87),"") -> 2285.4175 | K87: =C87-F87 -> 175555.56 | O87: =IFERROR(F87*$O$39,0) -> 16.666667 | P87: =IF($A87<=$I$18,B87-B86,) -> 30 | Q87: 365 | AA87: =A92 -> 49 | AB87: =IF($AA$36=1,VLOOKUP(AA87,$AE$38:$AK$218,6,0),IF($AA$36=2,VLOOKUP(AA87,$AE$38:$AK$218,4,0),VLOOKUP(AA87,$AE$38:$AK$218,2,0))) -> 16335.027 | AC87: =IF($AA$36=1,VLOOKUP(AA87,$AE$38:$AK$278,7,0),IF($AA$36=2,VLOOKUP(AA87,$AE$38:$AK$278,5,0),VLOOKUP(AA87,$AE$38:$AK$278,3,0))) -> 2284.7786 | AE87: =AA87 -> 49 | AF87: =IFERROR(VLOOKUP(AE87,[1]Cálculos_PRICE!$A$32:$K$212,10,0),"") -> 16335.027 | AG87: =IFERROR(VLOOKUP(AE87,'Cálculos_CGI - SAC FIXA'!A85:K477,10,0),"") -> 2284.7786 | AH87: =IFERROR(VLOOKUP(AE87,[1]Cálculos_PRICE!$A$32:$K$212,6,0),"") -> 2256.43 | AI87: =IFERROR(VLOOKUP(AE87,'Cálculos_CGI - SAC FIXA'!A85:K477,6,0),"") -> 555.55556 | AJ87: =IFERROR(VLOOKUP(AE87,[1]Cálculos_PRICE!$A$32:$K$240,11,0),"") -> 920928.93 | AK87: =IFERROR(VLOOKUP(AE87,'Cálculos_CGI - SAC FIXA'!A85:K477,11,0),"") -> 172777.78 | AN87: =AR88-K93 -> 66917.968 | AO87: 50 | AP87: JP | AQ87: 45569 | AR87: 239432.49 | AS87: 292.3 | AT87: 0 | AU87: 3088.68 | AV87: 75.07 | AW87: 3456.05
A88: =IF(IF(AND(A87>0,A87<$I$18),A87+1,0)=0,"",IF(AND(A87>0,A87<$I$18),A87+1,0)) -> 45 | B88: =IFERROR(IF(A88<=$I$18,DATE(YEAR($B$44),MONTH($B$44)+A87,DAY($B$44)),"-"),"") -> 47427 | C88: =IF(A88="","",K87) -> 175555.56 | D88: =C88*$I$20 -> 1913.5556 | E88: =IFERROR(C88+D88,"") -> 177469.11 | F88: =$I$13/$I$18 -> 555.55556 | G88: =IF(A88="","",PMT($I$20,$I$18,$C$44)*-1) -> 2224.912 | H88: =C88*$J$27 -> 40.377778 | I88: =IF(A88="","",IF(K87="","",IF(K87=0,"",$J$28*$I$14))) -> 20 | J88: =IFERROR(SUM(I88+H88+G88),"") -> 2285.2897 | K88: =C88-F88 -> 175000 | O88: =IFERROR(F88*$O$39,0) -> 16.666667 | P88: =IF($A88<=$I$18,B88-B87,) -> 31 | Q88: 365 | S88: Faixa Idade | T88: Alicota | U88: MIP | AA88: =A93 -> 50 | AB88: =IF($AA$36=1,VLOOKUP(AA88,$AE$38:$AK$218,6,0),IF($AA$36=2,VLOOKUP(AA88,$AE$38:$AK$218,4,0),VLOOKUP(AA88,$AE$38:$AK$218,2,0))) -> 16334.525 | AC88: =IF($AA$36=1,VLOOKUP(AA88,$AE$38:$AK$278,7,0),IF($AA$36=2,VLOOKUP(AA88,$AE$38:$AK$278,5,0),VLOOKUP(AA88,$AE$38:$AK$278,3,0))) -> 2284.6509 | AE88: =AA88 -> 50 | AF88: =IFERROR(VLOOKUP(AE88,[1]Cálculos_PRICE!$A$32:$K$212,10,0),"") -> 16334.525 | AG88: =IFERROR(VLOOKUP(AE88,'Cálculos_CGI - SAC FIXA'!A86:K478,10,0),"") -> 2284.6509 | AH88: =IFERROR(VLOOKUP(AE88,[1]Cálculos_PRICE!$A$32:$K$212,6,0),"") -> 2290.2764 | AI88: =IFERROR(VLOOKUP(AE88,'Cálculos_CGI - SAC FIXA'!A86:K478,6,0),"") -> 555.55556 | AJ88: =IFERROR(VLOOKUP(AE88,[1]Cálculos_PRICE!$A$32:$K$240,11,0),"") -> 918638.66 | AK88: =IFERROR(VLOOKUP(AE88,'Cálculos_CGI - SAC FIXA'!A86:K478,11,0),"") -> 172222.22 | AN88: =AR89-K94 -> 67177.453 | AO88: 51 | AP88: JP | AQ88: 45600 | AR88: 239140.19 | AS88: 296.07 | AT88: 0 | AU88: 3084.91 | AV88: 75 | AW88: 3455.98
A89: =IF(IF(AND(A88>0,A88<$I$18),A88+1,0)=0,"",IF(AND(A88>0,A88<$I$18),A88+1,0)) -> 46 | B89: =IFERROR(IF(A89<=$I$18,DATE(YEAR($B$44),MONTH($B$44)+A88,DAY($B$44)),"-"),"") -> 47457 | C89: =IF(A89="","",K88) -> 175000 | D89: =C89*$I$20 -> 1907.5 | E89: =IFERROR(C89+D89,"") -> 176907.5 | F89: =$I$13/$I$18 -> 555.55556 | G89: =IF(A89="","",PMT($I$20,$I$18,$C$44)*-1) -> 2224.912 | H89: =C89*$J$27 -> 40.25 | I89: =IF(A89="","",IF(K88="","",IF(K88=0,"",$J$28*$I$14))) -> 20 | J89: =IFERROR(SUM(I89+H89+G89),"") -> 2285.162 | K89: =C89-F89 -> 174444.44 | O89: =IFERROR(F89*$O$39,0) -> 16.666667 | P89: =IF($A89<=$I$18,B89-B88,) -> 30 | Q89: 365 | S89: 18 | T89: 0.0001284 | U89: Alicota_1 | AA89: =A94 -> 51 | AB89: =IF($AA$36=1,VLOOKUP(AA89,$AE$38:$AK$218,6,0),IF($AA$36=2,VLOOKUP(AA89,$AE$38:$AK$218,4,0),VLOOKUP(AA89,$AE$38:$AK$218,2,0))) -> 16334.016 | AC89: =IF($AA$36=1,VLOOKUP(AA89,$AE$38:$AK$278,7,0),IF($AA$36=2,VLOOKUP(AA89,$AE$38:$AK$278,5,0),VLOOKUP(AA89,$AE$38:$AK$278,3,0))) -> 2284.5231 | AE89: =AA89 -> 51 | AF89: =IFERROR(VLOOKUP(AE89,[1]Cálculos_PRICE!$A$32:$K$212,10,0),"") -> 16334.016 | AG89: =IFERROR(VLOOKUP(AE89,'Cálculos_CGI - SAC FIXA'!A87:K479,10,0),"") -> 2284.5231 | AH89: =IFERROR(VLOOKUP(AE89,[1]Cálculos_PRICE!$A$32:$K$212,6,0),"") -> 2324.6306 | AI89: =IFERROR(VLOOKUP(AE89,'Cálculos_CGI - SAC FIXA'!A87:K479,6,0),"") -> 555.55556 | AJ89: =IFERROR(VLOOKUP(AE89,[1]Cálculos_PRICE!$A$32:$K$240,11,0),"") -> 916314.02 | AK89: =IFERROR(VLOOKUP(AE89,'Cálculos_CGI - SAC FIXA'!A87:K479,11,0),"") -> 171666.67 | AN89: =AR90-K95 -> 67433.119 | AO89: 52 | AP89: JP | AQ89: 45630 | AR89: 238844.12 | AS89: 299.89 | AT89: 0 | AU89: 3081.09 | AV89: 74.93 | AW89: 3455.91
A90: =IF(IF(AND(A89>0,A89<$I$18),A89+1,0)=0,"",IF(AND(A89>0,A89<$I$18),A89+1,0)) -> 47 | B90: =IFERROR(IF(A90<=$I$18,DATE(YEAR($B$44),MONTH($B$44)+A89,DAY($B$44)),"-"),"") -> 47488 | C90: =IF(A90="","",K89) -> 174444.44 | D90: =C90*$I$20 -> 1901.4444 | E90: =IFERROR(C90+D90,"") -> 176345.89 | F90: =$I$13/$I$18 -> 555.55556 | G90: =IF(A90="","",PMT($I$20,$I$18,$C$44)*-1) -> 2224.912 | H90: =C90*$J$27 -> 40.122222 | I90: =IF(A90="","",IF(K89="","",IF(K89=0,"",$J$28*$I$14))) -> 20 | J90: =IFERROR(SUM(I90+H90+G90),"") -> 2285.0342 | K90: =C90-F90 -> 173888.89 | O90: =IFERROR(F90*$O$39,0) -> 16.666667 | P90: =IF($A90<=$I$18,B90-B89,) -> 31 | Q90: 365 | S90: 19 | T90: 0.0001284 | U90: Alicota_1 | AA90: =A95 -> 52 | AB90: =IF($AA$36=1,VLOOKUP(AA90,$AE$38:$AK$218,6,0),IF($AA$36=2,VLOOKUP(AA90,$AE$38:$AK$218,4,0),VLOOKUP(AA90,$AE$38:$AK$218,2,0))) -> 16333.499 | AC90: =IF($AA$36=1,VLOOKUP(AA90,$AE$38:$AK$278,7,0),IF($AA$36=2,VLOOKUP(AA90,$AE$38:$AK$278,5,0),VLOOKUP(AA90,$AE$38:$AK$278,3,0))) -> 2284.3953 | AE90: =AA90 -> 52 | AF90: =IFERROR(VLOOKUP(AE90,[1]Cálculos_PRICE!$A$32:$K$212,10,0),"") -> 16333.499 | AG90: =IFERROR(VLOOKUP(AE90,'Cálculos_CGI - SAC FIXA'!A88:K480,10,0),"") -> 2284.3953 | AH90: =IFERROR(VLOOKUP(AE90,[1]Cálculos_PRICE!$A$32:$K$212,6,0),"") -> 2359.5 | AI90: =IFERROR(VLOOKUP(AE90,'Cálculos_CGI - SAC FIXA'!A88:K480,6,0),"") -> 555.55556 | AJ90: =IFERROR(VLOOKUP(AE90,[1]Cálculos_PRICE!$A$32:$K$240,11,0),"") -> 913954.52 | AK90: =IFERROR(VLOOKUP(AE90,'Cálculos_CGI - SAC FIXA'!A88:K480,11,0),"") -> 171111.11 | AN90: =AR91-K96 -> 67684.914 | AO90: 53 | AP90: JP | AQ90: 45661 | AR90: 238544.23 | AS90: 303.76 | AT90: 0 | AU90: 3077.22 | AV90: 74.87 | AW90: 3455.85
A91: =IF(IF(AND(A90>0,A90<$I$18),A90+1,0)=0,"",IF(AND(A90>0,A90<$I$18),A90+1,0)) -> 48 | B91: =IFERROR(IF(A91<=$I$18,DATE(YEAR($B$44),MONTH($B$44)+A90,DAY($B$44)),"-"),"") -> 47519 | C91: =IF(A91="","",K90) -> 173888.89 | D91: =C91*$I$20 -> 1895.3889 | E91: =IFERROR(C91+D91,"") -> 175784.28 | F91: =$I$13/$I$18 -> 555.55556 | G91: =IF(A91="","",PMT($I$20,$I$18,$C$44)*-1) -> 2224.912 | H91: =C91*$J$27 -> 39.994444 | I91: =IF(A91="","",IF(K90="","",IF(K90=0,"",$J$28*$I$14))) -> 20 | J91: =IFERROR(SUM(I91+H91+G91),"") -> 2284.9064 | K91: =C91-F91 -> 173333.33 | O91: =IFERROR(F91*$O$39,0) -> 16.666667 | P91: =IF($A91<=$I$18,B91-B90,) -> 31 | Q91: 365 | S91: 20 | T91: 0.0001284 | U91: Alicota_1 | AA91: =A96 -> 53 | AB91: =IF($AA$36=1,VLOOKUP(AA91,$AE$38:$AK$218,6,0),IF($AA$36=2,VLOOKUP(AA91,$AE$38:$AK$218,4,0),VLOOKUP(AA91,$AE$38:$AK$218,2,0))) -> 16332.974 | AC91: =IF($AA$36=1,VLOOKUP(AA91,$AE$38:$AK$278,7,0),IF($AA$36=2,VLOOKUP(AA91,$AE$38:$AK$278,5,0),VLOOKUP(AA91,$AE$38:$AK$278,3,0))) -> 2284.2675 | AE91: =AA91 -> 53 | AF91: =IFERROR(VLOOKUP(AE91,[1]Cálculos_PRICE!$A$32:$K$212,10,0),"") -> 16332.974 | AG91: =IFERROR(VLOOKUP(AE91,'Cálculos_CGI - SAC FIXA'!A89:K481,10,0),"") -> 2284.2675 | AH91: =IFERROR(VLOOKUP(AE91,[1]Cálculos_PRICE!$A$32:$K$212,6,0),"") -> 2394.8925 | AI91: =IFERROR(VLOOKUP(AE91,'Cálculos_CGI - SAC FIXA'!A89:K481,6,0),"") -> 555.55556 | AJ91: =IFERROR(VLOOKUP(AE91,[1]Cálculos_PRICE!$A$32:$K$240,11,0),"") -> 911559.63 | AK91: =IFERROR(VLOOKUP(AE91,'Cálculos_CGI - SAC FIXA'!A89:K481,11,0),"") -> 170555.56 | AN91: =AR92-K97 -> 67932.79 | AO91: 54 | AP91: JP | AQ91: 45692 | AR91: 238240.47 | AS91: 307.68 | AT91: 0 | AU91: 3073.3 | AV91: 74.8 | AW91: 3455.78
A92: =IF(IF(AND(A91>0,A91<$I$18),A91+1,0)=0,"",IF(AND(A91>0,A91<$I$18),A91+1,0)) -> 49 | B92: =IFERROR(IF(A92<=$I$18,DATE(YEAR($B$44),MONTH($B$44)+A91,DAY($B$44)),"-"),"") -> 47547 | C92: =IF(A92="","",K91) -> 173333.33 | D92: =C92*$I$20 -> 1889.3333 | E92: =IFERROR(C92+D92,"") -> 175222.67 | F92: =$I$13/$I$18 -> 555.55556 | G92: =IF(A92="","",PMT($I$20,$I$18,$C$44)*-1) -> 2224.912 | H92: =C92*$J$27 -> 39.866667 | I92: =IF(A92="","",IF(K91="","",IF(K91=0,"",$J$28*$I$14))) -> 20 | J92: =IFERROR(SUM(I92+H92+G92),"") -> 2284.7786 | K92: =C92-F92 -> 172777.78 | O92: =IFERROR(F92*$O$39,0) -> 16.666667 | P92: =IF($A92<=$I$18,B92-B91,) -> 28 | Q92: 365 | S92: 21 | T92: 0.0001284 | U92: Alicota_1 | AA92: =A97 -> 54 | AB92: =IF($AA$36=1,VLOOKUP(AA92,$AE$38:$AK$218,6,0),IF($AA$36=2,VLOOKUP(AA92,$AE$38:$AK$218,4,0),VLOOKUP(AA92,$AE$38:$AK$218,2,0))) -> 16332.441 | AC92: =IF($AA$36=1,VLOOKUP(AA92,$AE$38:$AK$278,7,0),IF($AA$36=2,VLOOKUP(AA92,$AE$38:$AK$278,5,0),VLOOKUP(AA92,$AE$38:$AK$278,3,0))) -> 2284.1397 | AE92: =AA92 -> 54 | AF92: =IFERROR(VLOOKUP(AE92,[1]Cálculos_PRICE!$A$32:$K$212,10,0),"") -> 16332.441 | AG92: =IFERROR(VLOOKUP(AE92,'Cálculos_CGI - SAC FIXA'!A90:K482,10,0),"") -> 2284.1397 | AH92: =IFERROR(VLOOKUP(AE92,[1]Cálculos_PRICE!$A$32:$K$212,6,0),"") -> 2430.8159 | AI92: =IFERROR(VLOOKUP(AE92,'Cálculos_CGI - SAC FIXA'!A90:K482,6,0),"") -> 555.55556 | AJ92: =IFERROR(VLOOKUP(AE92,[1]Cálculos_PRICE!$A$32:$K$240,11,0),"") -> 909128.82 | AK92: =IFERROR(VLOOKUP(AE92,'Cálculos_CGI - SAC FIXA'!A90:K482,11,0),"") -> 170000 | AN92: =AR93-K98 -> 68176.696 | AO92: 55 | AP92: JP | AQ92: 45720 | AR92: 237932.79 | AS92: 311.65 | AT92: 0 | AU92: 3069.33 | AV92: 74.72 | AW92: 3455.7
A93: =IF(IF(AND(A92>0,A92<$I$18),A92+1,0)=0,"",IF(AND(A92>0,A92<$I$18),A92+1,0)) -> 50 | B93: =IFERROR(IF(A93<=$I$18,DATE(YEAR($B$44),MONTH($B$44)+A92,DAY($B$44)),"-"),"") -> 47578 | C93: =IF(A93="","",K92) -> 172777.78 | D93: =C93*$I$20 -> 1883.2778 | E93: =IFERROR(C93+D93,"") -> 174661.06 | F93: =$I$13/$I$18 -> 555.55556 | G93: =IF(A93="","",PMT($I$20,$I$18,$C$44)*-1) -> 2224.912 | H93: =C93*$J$27 -> 39.738889 | I93: =IF(A93="","",IF(K92="","",IF(K92=0,"",$J$28*$I$14))) -> 20 | J93: =IFERROR(SUM(I93+H93+G93),"") -> 2284.6509 | K93: =C93-F93 -> 172222.22 | O93: =IFERROR(F93*$O$39,0) -> 16.666667 | P93: =IF($A93<=$I$18,B93-B92,) -> 31 | Q93: 365 | S93: 22 | T93: 0.0001284 | U93: Alicota_1 | AA93: =A98 -> 55 | AB93: =IF($AA$36=1,VLOOKUP(AA93,$AE$38:$AK$218,6,0),IF($AA$36=2,VLOOKUP(AA93,$AE$38:$AK$218,4,0),VLOOKUP(AA93,$AE$38:$AK$218,2,0))) -> 16331.901 | AC93: =IF($AA$36=1,VLOOKUP(AA93,$AE$38:$AK$278,7,0),IF($AA$36=2,VLOOKUP(AA93,$AE$38:$AK$278,5,0),VLOOKUP(AA93,$AE$38:$AK$278,3,0))) -> 2284.012 | AE93: =AA93 -> 55 | AF93: =IFERROR(VLOOKUP(AE93,[1]Cálculos_PRICE!$A$32:$K$212,10,0),"") -> 16331.901 | AG93: =IFERROR(VLOOKUP(AE93,'Cálculos_CGI - SAC FIXA'!A91:K483,10,0),"") -> 2284.012 | AH93: =IFERROR(VLOOKUP(AE93,[1]Cálculos_PRICE!$A$32:$K$212,6,0),"") -> 2467.2781 | AI93: =IFERROR(VLOOKUP(AE93,'Cálculos_CGI - SAC FIXA'!A91:K483,6,0),"") -> 555.55556 | AJ93: =IFERROR(VLOOKUP(AE93,[1]Cálculos_PRICE!$A$32:$K$240,11,0),"") -> 906661.54 | AK93: =IFERROR(VLOOKUP(AE93,'Cálculos_CGI - SAC FIXA'!A91:K483,11,0),"") -> 169444.44 | AN93: =AR94-K99 -> 68416.581 | AO93: 56 | AP93: JP | AQ93: 45751 | AR93: 237621.14 | AS93: 315.67 | AT93: 0 | AU93: 3065.31 | AV93: 74.65 | AW93: 3455.63
A94: =IF(IF(AND(A93>0,A93<$I$18),A93+1,0)=0,"",IF(AND(A93>0,A93<$I$18),A93+1,0)) -> 51 | B94: =IFERROR(IF(A94<=$I$18,DATE(YEAR($B$44),MONTH($B$44)+A93,DAY($B$44)),"-"),"") -> 47608 | C94: =IF(A94="","",K93) -> 172222.22 | D94: =C94*$I$20 -> 1877.2222 | E94: =IFERROR(C94+D94,"") -> 174099.44 | F94: =$I$13/$I$18 -> 555.55556 | G94: =IF(A94="","",PMT($I$20,$I$18,$C$44)*-1) -> 2224.912 | H94: =C94*$J$27 -> 39.611111 | I94: =IF(A94="","",IF(K93="","",IF(K93=0,"",$J$28*$I$14))) -> 20 | J94: =IFERROR(SUM(I94+H94+G94),"") -> 2284.5231 | K94: =C94-F94 -> 171666.67 | O94: =IFERROR(F94*$O$39,0) -> 16.666667 | P94: =IF($A94<=$I$18,B94-B93,) -> 30 | Q94: 365 | S94: 23 | T94: 0.0001284 | U94: Alicota_1 | AA94: =A99 -> 56 | AB94: =IF($AA$36=1,VLOOKUP(AA94,$AE$38:$AK$218,6,0),IF($AA$36=2,VLOOKUP(AA94,$AE$38:$AK$218,4,0),VLOOKUP(AA94,$AE$38:$AK$218,2,0))) -> 16331.352 | AC94: =IF($AA$36=1,VLOOKUP(AA94,$AE$38:$AK$278,7,0),IF($AA$36=2,VLOOKUP(AA94,$AE$38:$AK$278,5,0),VLOOKUP(AA94,$AE$38:$AK$278,3,0))) -> 2283.8842 | AE94: =AA94 -> 56 | AF94: =IFERROR(VLOOKUP(AE94,[1]Cálculos_PRICE!$A$32:$K$212,10,0),"") -> 16331.352 | AG94: =IFERROR(VLOOKUP(AE94,'Cálculos_CGI - SAC FIXA'!A92:K484,10,0),"") -> 2283.8842 | AH94: =IFERROR(VLOOKUP(AE94,[1]Cálculos_PRICE!$A$32:$K$212,6,0),"") -> 2504.2873 | AI94: =IFERROR(VLOOKUP(AE94,'Cálculos_CGI - SAC FIXA'!A92:K484,6,0),"") -> 555.55556 | AJ94: =IFERROR(VLOOKUP(AE94,[1]Cálculos_PRICE!$A$32:$K$240,11,0),"") -> 904157.25 | AK94: =IFERROR(VLOOKUP(AE94,'Cálculos_CGI - SAC FIXA'!A92:K484,11,0),"") -> 168888.89 | AN94: =AR95-K100 -> 68652.397 | AO94: 57 | AP94: JP | AQ94: 45781 | AR94: 237305.47 | AS94: 319.74 | AT94: 0 | AU94: 3061.24 | AV94: 74.58 | AW94: 3455.56
A95: =IF(IF(AND(A94>0,A94<$I$18),A94+1,0)=0,"",IF(AND(A94>0,A94<$I$18),A94+1,0)) -> 52 | B95: =IFERROR(IF(A95<=$I$18,DATE(YEAR($B$44),MONTH($B$44)+A94,DAY($B$44)),"-"),"") -> 47639 | C95: =IF(A95="","",K94) -> 171666.67 | D95: =C95*$I$20 -> 1871.1667 | E95: =IFERROR(C95+D95,"") -> 173537.83 | F95: =$I$13/$I$18 -> 555.55556 | G95: =IF(A95="","",PMT($I$20,$I$18,$C$44)*-1) -> 2224.912 | H95: =C95*$J$27 -> 39.483333 | I95: =IF(A95="","",IF(K94="","",IF(K94=0,"",$J$28*$I$14))) -> 20 | J95: =IFERROR(SUM(I95+H95+G95),"") -> 2284.3953 | K95: =C95-F95 -> 171111.11 | O95: =IFERROR(F95*$O$39,0) -> 16.666667 | P95: =IF($A95<=$I$18,B95-B94,) -> 31 | Q95: 365 | S95: 24 | T95: 0.0001284 | U95: Alicota_1 | AA95: =A100 -> 57 | AB95: =IF($AA$36=1,VLOOKUP(AA95,$AE$38:$AK$218,6,0),IF($AA$36=2,VLOOKUP(AA95,$AE$38:$AK$218,4,0),VLOOKUP(AA95,$AE$38:$AK$218,2,0))) -> 16330.795 | AC95: =IF($AA$36=1,VLOOKUP(AA95,$AE$38:$AK$278,7,0),IF($AA$36=2,VLOOKUP(AA95,$AE$38:$AK$278,5,0),VLOOKUP(AA95,$AE$38:$AK$278,3,0))) -> 2283.7564 | AE95: =AA95 -> 57 | AF95: =IFERROR(VLOOKUP(AE95,[1]Cálculos_PRICE!$A$32:$K$212,10,0),"") -> 16330.795 | AG95: =IFERROR(VLOOKUP(AE95,'Cálculos_CGI - SAC FIXA'!A93:K485,10,0),"") -> 2283.7564 | AH95: =IFERROR(VLOOKUP(AE95,[1]Cálculos_PRICE!$A$32:$K$212,6,0),"") -> 2541.8516 | AI95: =IFERROR(VLOOKUP(AE95,'Cálculos_CGI - SAC FIXA'!A93:K485,6,0),"") -> 555.55556 | AJ95: =IFERROR(VLOOKUP(AE95,[1]Cálculos_PRICE!$A$32:$K$240,11,0),"") -> 901615.4 | AK95: =IFERROR(VLOOKUP(AE95,'Cálculos_CGI - SAC FIXA'!A93:K485,11,0),"") -> 168333.33 | AN95: =AR96-K101 -> 68884.092 | AO95: 58 | AP95: JP | AQ95: 45812 | AR95: 236985.73 | AS95: 323.86 | AT95: 0 | AU95: 3057.12 | AV95: 74.51 | AW95: 3455.49
A96: =IF(IF(AND(A95>0,A95<$I$18),A95+1,0)=0,"",IF(AND(A95>0,A95<$I$18),A95+1,0)) -> 53 | B96: =IFERROR(IF(A96<=$I$18,DATE(YEAR($B$44),MONTH($B$44)+A95,DAY($B$44)),"-"),"") -> 47669 | C96: =IF(A96="","",K95) -> 171111.11 | D96: =C96*$I$20 -> 1865.1111 | E96: =IFERROR(C96+D96,"") -> 172976.22 | F96: =$I$13/$I$18 -> 555.55556 | G96: =IF(A96="","",PMT($I$20,$I$18,$C$44)*-1) -> 2224.912 | H96: =C96*$J$27 -> 39.355556 | I96: =IF(A96="","",IF(K95="","",IF(K95=0,"",$J$28*$I$14))) -> 20 | J96: =IFERROR(SUM(I96+H96+G96),"") -> 2284.2675 | K96: =C96-F96 -> 170555.56 | O96: =IFERROR(F96*$O$39,0) -> 16.666667 | P96: =IF($A96<=$I$18,B96-B95,) -> 30 | Q96: 365 | S96: 25 | T96: 0.0001284 | U96: Alicota_1 | AA96: =A101 -> 58 | AB96: =IF($AA$36=1,VLOOKUP(AA96,$AE$38:$AK$218,6,0),IF($AA$36=2,VLOOKUP(AA96,$AE$38:$AK$218,4,0),VLOOKUP(AA96,$AE$38:$AK$218,2,0))) -> 16330.23 | AC96: =IF($AA$36=1,VLOOKUP(AA96,$AE$38:$AK$278,7,0),IF($AA$36=2,VLOOKUP(AA96,$AE$38:$AK$278,5,0),VLOOKUP(AA96,$AE$38:$AK$278,3,0))) -> 2283.6286 | AE96: =AA96 -> 58 | AF96: =IFERROR(VLOOKUP(AE96,[1]Cálculos_PRICE!$A$32:$K$212,10,0),"") -> 16330.23 | AG96: =IFERROR(VLOOKUP(AE96,'Cálculos_CGI - SAC FIXA'!A94:K486,10,0),"") -> 2283.6286 | AH96: =IFERROR(VLOOKUP(AE96,[1]Cálculos_PRICE!$A$32:$K$212,6,0),"") -> 2579.9794 | AI96: =IFERROR(VLOOKUP(AE96,'Cálculos_CGI - SAC FIXA'!A94:K486,6,0),"") -> 555.55556 | AJ96: =IFERROR(VLOOKUP(AE96,[1]Cálculos_PRICE!$A$32:$K$240,11,0),"") -> 899035.42 | AK96: =IFERROR(VLOOKUP(AE96,'Cálculos_CGI - SAC FIXA'!A94:K486,11,0),"") -> 167777.78 | AN96: =AR97-K102 -> 69111.608 | AO96: 59 | AP96: JP | AQ96: 45842 | AR96: 236661.87 | AS96: 328.04 | AT96: 0 | AU96: 3052.94 | AV96: 74.43 | AW96: 3455.41
A97: =IF(IF(AND(A96>0,A96<$I$18),A96+1,0)=0,"",IF(AND(A96>0,A96<$I$18),A96+1,0)) -> 54 | B97: =IFERROR(IF(A97<=$I$18,DATE(YEAR($B$44),MONTH($B$44)+A96,DAY($B$44)),"-"),"") -> 47700 | C97: =IF(A97="","",K96) -> 170555.56 | D97: =C97*$I$20 -> 1859.0556 | E97: =IFERROR(C97+D97,"") -> 172414.61 | F97: =$I$13/$I$18 -> 555.55556 | G97: =IF(A97="","",PMT($I$20,$I$18,$C$44)*-1) -> 2224.912 | H97: =C97*$J$27 -> 39.227778 | I97: =IF(A97="","",IF(K96="","",IF(K96=0,"",$J$28*$I$14))) -> 20 | J97: =IFERROR(SUM(I97+H97+G97),"") -> 2284.1397 | K97: =C97-F97 -> 170000 | O97: =IFERROR(F97*$O$39,0) -> 16.666667 | P97: =IF($A97<=$I$18,B97-B96,) -> 31 | Q97: 365 | S97: 26 | T97: 0.0001284 | U97: Alicota_2 | AA97: =A102 -> 59 | AB97: =IF($AA$36=1,VLOOKUP(AA97,$AE$38:$AK$218,6,0),IF($AA$36=2,VLOOKUP(AA97,$AE$38:$AK$218,4,0),VLOOKUP(AA97,$AE$38:$AK$218,2,0))) -> 16329.656 | AC97: =IF($AA$36=1,VLOOKUP(AA97,$AE$38:$AK$278,7,0),IF($AA$36=2,VLOOKUP(AA97,$AE$38:$AK$278,5,0),VLOOKUP(AA97,$AE$38:$AK$278,3,0))) -> 2283.5009 | AE97: =AA97 -> 59 | AF97: =IFERROR(VLOOKUP(AE97,[1]Cálculos_PRICE!$A$32:$K$212,10,0),"") -> 16329.656 | AG97: =IFERROR(VLOOKUP(AE97,'Cálculos_CGI - SAC FIXA'!A95:K487,10,0),"") -> 2283.5009 | AH97: =IFERROR(VLOOKUP(AE97,[1]Cálculos_PRICE!$A$32:$K$212,6,0),"") -> 2618.6791 | AI97: =IFERROR(VLOOKUP(AE97,'Cálculos_CGI - SAC FIXA'!A95:K487,6,0),"") -> 555.55556 | AJ97: =IFERROR(VLOOKUP(AE97,[1]Cálculos_PRICE!$A$32:$K$240,11,0),"") -> 896416.74 | AK97: =IFERROR(VLOOKUP(AE97,'Cálculos_CGI - SAC FIXA'!A95:K487,11,0),"") -> 167222.22 | AN97: =AR98-K103 -> 69334.893 | AO97: 60 | AP97: JP | AQ97: 45873 | AR97: 236333.83 | AS97: 332.27 | AT97: 0 | AU97: 3048.71 | AV97: 74.36 | AW97: 3455.34
A98: =IF(IF(AND(A97>0,A97<$I$18),A97+1,0)=0,"",IF(AND(A97>0,A97<$I$18),A97+1,0)) -> 55 | B98: =IFERROR(IF(A98<=$I$18,DATE(YEAR($B$44),MONTH($B$44)+A97,DAY($B$44)),"-"),"") -> 47731 | C98: =IF(A98="","",K97) -> 170000 | D98: =C98*$I$20 -> 1853 | E98: =IFERROR(C98+D98,"") -> 171853 | F98: =$I$13/$I$18 -> 555.55556 | G98: =IF(A98="","",PMT($I$20,$I$18,$C$44)*-1) -> 2224.912 | H98: =C98*$J$27 -> 39.1 | I98: =IF(A98="","",IF(K97="","",IF(K97=0,"",$J$28*$I$14))) -> 20 | J98: =IFERROR(SUM(I98+H98+G98),"") -> 2284.012 | K98: =C98-F98 -> 169444.44 | O98: =IFERROR(F98*$O$39,0) -> 16.666667 | P98: =IF($A98<=$I$18,B98-B97,) -> 31 | Q98: 365 | S98: 27 | T98: 0.0001284 | U98: Alicota_2 | AA98: =A103 -> 60 | AB98: =IF($AA$36=1,VLOOKUP(AA98,$AE$38:$AK$218,6,0),IF($AA$36=2,VLOOKUP(AA98,$AE$38:$AK$218,4,0),VLOOKUP(AA98,$AE$38:$AK$218,2,0))) -> 16329.073 | AC98: =IF($AA$36=1,VLOOKUP(AA98,$AE$38:$AK$278,7,0),IF($AA$36=2,VLOOKUP(AA98,$AE$38:$AK$278,5,0),VLOOKUP(AA98,$AE$38:$AK$278,3,0))) -> 2283.3731 | AE98: =AA98 -> 60 | AF98: =IFERROR(VLOOKUP(AE98,[1]Cálculos_PRICE!$A$32:$K$212,10,0),"") -> 16329.073 | AG98: =IFERROR(VLOOKUP(AE98,'Cálculos_CGI - SAC FIXA'!A96:K488,10,0),"") -> 2283.3731 | AH98: =IFERROR(VLOOKUP(AE98,[1]Cálculos_PRICE!$A$32:$K$212,6,0),"") -> 2657.9593 | AI98: =IFERROR(VLOOKUP(AE98,'Cálculos_CGI - SAC FIXA'!A96:K488,6,0),"") -> 555.55556 | AJ98: =IFERROR(VLOOKUP(AE98,[1]Cálculos_PRICE!$A$32:$K$240,11,0),"") -> 893758.78 | AK98: =IFERROR(VLOOKUP(AE98,'Cálculos_CGI - SAC FIXA'!A96:K488,11,0),"") -> 166666.67 | AN98: =AR99-K104 -> 69553.889 | AO98: 61 | AP98: JP | AQ98: 45904 | AR98: 236001.56 | AS98: 336.56 | AT98: 0 | AU98: 3044.42 | AV98: 74.28 | AW98: 3455.26
A99: =IF(IF(AND(A98>0,A98<$I$18),A98+1,0)=0,"",IF(AND(A98>0,A98<$I$18),A98+1,0)) -> 56 | B99: =IFERROR(IF(A99<=$I$18,DATE(YEAR($B$44),MONTH($B$44)+A98,DAY($B$44)),"-"),"") -> 47761 | C99: =IF(A99="","",K98) -> 169444.44 | D99: =C99*$I$20 -> 1846.9444 | E99: =IFERROR(C99+D99,"") -> 171291.39 | F99: =$I$13/$I$18 -> 555.55556 | G99: =IF(A99="","",PMT($I$20,$I$18,$C$44)*-1) -> 2224.912 | H99: =C99*$J$27 -> 38.972222 | I99: =IF(A99="","",IF(K98="","",IF(K98=0,"",$J$28*$I$14))) -> 20 | J99: =IFERROR(SUM(I99+H99+G99),"") -> 2283.8842 | K99: =C99-F99 -> 168888.89 | O99: =IFERROR(F99*$O$39,0) -> 16.666667 | P99: =IF($A99<=$I$18,B99-B98,) -> 30 | Q99: 365 | S99: 28 | T99: 0.0001284 | U99: Alicota_2 | AA99: =A104 -> 61 | AB99: =IF($AA$36=1,VLOOKUP(AA99,$AE$38:$AK$218,6,0),IF($AA$36=2,VLOOKUP(AA99,$AE$38:$AK$218,4,0),VLOOKUP(AA99,$AE$38:$AK$218,2,0))) -> 16328.482 | AC99: =IF($AA$36=1,VLOOKUP(AA99,$AE$38:$AK$278,7,0),IF($AA$36=2,VLOOKUP(AA99,$AE$38:$AK$278,5,0),VLOOKUP(AA99,$AE$38:$AK$278,3,0))) -> 2283.2453 | AE99: =AA99 -> 61 | AF99: =IFERROR(VLOOKUP(AE99,[1]Cálculos_PRICE!$A$32:$K$212,10,0),"") -> 16328.482 | AG99: =IFERROR(VLOOKUP(AE99,'Cálculos_CGI - SAC FIXA'!A97:K489,10,0),"") -> 2283.2453 | AH99: =IFERROR(VLOOKUP(AE99,[1]Cálculos_PRICE!$A$32:$K$212,6,0),"") -> 2697.8287 | AI99: =IFERROR(VLOOKUP(AE99,'Cálculos_CGI - SAC FIXA'!A97:K489,6,0),"") -> 555.55556 | AJ99: =IFERROR(VLOOKUP(AE99,[1]Cálculos_PRICE!$A$32:$K$240,11,0),"") -> 891060.95 | AK99: =IFERROR(VLOOKUP(AE99,'Cálculos_CGI - SAC FIXA'!A97:K489,11,0),"") -> 166111.11 | AN99: =AR100-K105 -> 69768.544 | AO99: 62 | AP99: JP | AQ99: 45934 | AR99: 235665 | AS99: 340.9 | AT99: 0 | AU99: 3040.08 | AV99: 74.2 | AW99: 3455.18
A100: =IF(IF(AND(A99>0,A99<$I$18),A99+1,0)=0,"",IF(AND(A99>0,A99<$I$18),A99+1,0)) -> 57 | B100: =IFERROR(IF(A100<=$I$18,DATE(YEAR($B$44),MONTH($B$44)+A99,DAY($B$44)),"-"),"") -> 47792 | C100: =IF(A100="","",K99) -> 168888.89 | D100: =C100*$I$20 -> 1840.8889 | E100: =IFERROR(C100+D100,"") -> 170729.78 | F100: =$I$13/$I$18 -> 555.55556 | G100: =IF(A100="","",PMT($I$20,$I$18,$C$44)*-1) -> 2224.912 | H100: =C100*$J$27 -> 38.844444 | I100: =IF(A100="","",IF(K99="","",IF(K99=0,"",$J$28*$I$14))) -> 20 | J100: =IFERROR(SUM(I100+H100+G100),"") -> 2283.7564 | K100: =C100-F100 -> 168333.33 | O100: =IFERROR(F100*$O$39,0) -> 16.666667 | P100: =IF($A100<=$I$18,B100-B99,) -> 31 | Q100: 365 | S100: 29 | T100: 0.0001284 | U100: Alicota_2 | AA100: =A105 -> 62 | AB100: =IF($AA$36=1,VLOOKUP(AA100,$AE$38:$AK$218,6,0),IF($AA$36=2,VLOOKUP(AA100,$AE$38:$AK$218,4,0),VLOOKUP(AA100,$AE$38:$AK$218,2,0))) -> 16327.882 | AC100: =IF($AA$36=1,VLOOKUP(AA100,$AE$38:$AK$278,7,0),IF($AA$36=2,VLOOKUP(AA100,$AE$38:$AK$278,5,0),VLOOKUP(AA100,$AE$38:$AK$278,3,0))) -> 2283.1175 | AE100: =AA100 -> 62 | AF100: =IFERROR(VLOOKUP(AE100,[1]Cálculos_PRICE!$A$32:$K$212,10,0),"") -> 16327.882 | AG100: =IFERROR(VLOOKUP(AE100,'Cálculos_CGI - SAC FIXA'!A98:K490,10,0),"") -> 2283.1175 | AH100: =IFERROR(VLOOKUP(AE100,[1]Cálculos_PRICE!$A$32:$K$212,6,0),"") -> 2738.2961 | AI100: =IFERROR(VLOOKUP(AE100,'Cálculos_CGI - SAC FIXA'!A98:K490,6,0),"") -> 555.55556 | AJ100: =IFERROR(VLOOKUP(AE100,[1]Cálculos_PRICE!$A$32:$K$240,11,0),"") -> 888322.66 | AK100: =IFERROR(VLOOKUP(AE100,'Cálculos_CGI - SAC FIXA'!A98:K490,11,0),"") -> 165555.56 | AN100: =AR101-K106 -> 69978.8 | AO100: 63 | AP100: JP | AQ100: 45965 | AR100: 235324.1 | AS100: 345.3 | AT100: 0 | AU100: 3035.68 | AV100: 74.12 | AW100: 3455.1
... A151: =IF(IF(AND(A150>0,A150<$I$18),A150+1,0)=0,"",IF(AND(A150>0,A150<$I$18),A150+1,0)) -> 108 | B151: =IFERROR(IF(A151<=$I$18,DATE(YEAR($B$44),MONTH($B$44)+A150,DAY($B$44)),"-"),"") -> 49345 | C151: =IF(A151="","",K150) -> 140555.56 | D151: =C151*$I$20 -> 1532.0556 | E151: =IFERROR(C151+D151,"") -> 142087.61 | F151: =$I$13/$I$18 -> 555.55556 | G151: =IF(A151="","",PMT($I$20,$I$18,$C$44)*-1) -> 2224.912 | H151: =C151*$J$27 -> 32.327778 | I151: =IF(A151="","",IF(K150="","",IF(K150=0,"",$J$28*$I$14))) -> 20 | J151: =IFERROR(SUM(I151+H151+G151),"") -> 2277.2397 | K151: =C151-F151 -> 140000 | O151: =IFERROR(F151*$O$39,0) -> 16.666667 | P151: =IF($A151<=$I$18,B151-B150,) -> 31 | Q151: 365 | S151: 80 | T151: 0.011433 | U151: Alicota_9 | AA151: =A156 -> 113 | AB151: =IF($AA$36=1,VLOOKUP(AA151,$AE$38:$AK$218,6,0),IF($AA$36=2,VLOOKUP(AA151,$AE$38:$AK$218,4,0),VLOOKUP(AA151,$AE$38:$AK$218,2,0))) -> 16281.728 | AC151: =IF($AA$36=1,VLOOKUP(AA151,$AE$38:$AK$278,7,0),IF($AA$36=2,VLOOKUP(AA151,$AE$38:$AK$278,5,0),VLOOKUP(AA151,$AE$38:$AK$278,3,0))) -> 2276.6009 | AE151: =AA151 -> 113 | AF151: =IFERROR(VLOOKUP(AE151,[1]Cálculos_PRICE!$A$32:$K$212,10,0),"") -> 16281.728 | AG151: =IFERROR(VLOOKUP(AE151,'Cálculos_CGI - SAC FIXA'!A149:K541,10,0),"") -> 2276.6009 | AH151: =IFERROR(VLOOKUP(AE151,[1]Cálculos_PRICE!$A$32:$K$212,6,0),"") -> 5851.2488 | AI151: =IFERROR(VLOOKUP(AE151,'Cálculos_CGI - SAC FIXA'!A149:K541,6,0),"") -> 555.55556 | AJ151: =IFERROR(VLOOKUP(AE151,[1]Cálculos_PRICE!$A$32:$K$240,11,0),"") -> 677679.53 | AK151: =IFERROR(VLOOKUP(AE151,'Cálculos_CGI - SAC FIXA'!A149:K541,11,0),"") -> 137222.22 | AN151: =AR152-K157 -> 73297.213 | AO151: 114 | AP151: JP | AQ151: 47518 | AR151: 210627.76 | AS151: 663.88 | AT151: 0 | AU151: 2717.1 | AV151: 68.44 | AW151: 3449.42
A152: =IF(IF(AND(A151>0,A151<$I$18),A151+1,0)=0,"",IF(AND(A151>0,A151<$I$18),A151+1,0)) -> 109 | B152: =IFERROR(IF(A152<=$I$18,DATE(YEAR($B$44),MONTH($B$44)+A151,DAY($B$44)),"-"),"") -> 49373 | C152: =IF(A152="","",K151) -> 140000 | D152: =C152*$I$20 -> 1526 | E152: =IFERROR(C152+D152,"") -> 141526 | F152: =$I$13/$I$18 -> 555.55556 | G152: =IF(A152="","",PMT($I$20,$I$18,$C$44)*-1) -> 2224.912 | H152: =C152*$J$27 -> 32.2 | I152: =IF(A152="","",IF(K151="","",IF(K151=0,"",$J$28*$I$14))) -> 20 | J152: =IFERROR(SUM(I152+H152+G152),"") -> 2277.112 | K152: =C152-F152 -> 139444.44 | O152: =IFERROR(F152*$O$39,0) -> 16.666667 | P152: =IF($A152<=$I$18,B152-B151,) -> 28 | Q152: 365 | AA152: =A157 -> 114 | AB152: =IF($AA$36=1,VLOOKUP(AA152,$AE$38:$AK$218,6,0),IF($AA$36=2,VLOOKUP(AA152,$AE$38:$AK$218,4,0),VLOOKUP(AA152,$AE$38:$AK$218,2,0))) -> 16280.426 | AC152: =IF($AA$36=1,VLOOKUP(AA152,$AE$38:$AK$278,7,0),IF($AA$36=2,VLOOKUP(AA152,$AE$38:$AK$278,5,0),VLOOKUP(AA152,$AE$38:$AK$278,3,0))) -> 2276.4731 | AE152: =AA152 -> 114 | AF152: =IFERROR(VLOOKUP(AE152,[1]Cálculos_PRICE!$A$32:$K$212,10,0),"") -> 16280.426 | AG152: =IFERROR(VLOOKUP(AE152,'Cálculos_CGI - SAC FIXA'!A150:K542,10,0),"") -> 2276.4731 | AH152: =IFERROR(VLOOKUP(AE152,[1]Cálculos_PRICE!$A$32:$K$212,6,0),"") -> 5939.0175 | AI152: =IFERROR(VLOOKUP(AE152,'Cálculos_CGI - SAC FIXA'!A150:K542,6,0),"") -> 555.55556 | AJ152: =IFERROR(VLOOKUP(AE152,[1]Cálculos_PRICE!$A$32:$K$240,11,0),"") -> 671740.51 | AK152: =IFERROR(VLOOKUP(AE152,'Cálculos_CGI - SAC FIXA'!A150:K542,11,0),"") -> 136666.67 | AN152: =AR153-K158 -> 73180.319 | AO152: 115 | AP152: JP | AQ152: 47546 | AR152: 209963.88 | AS152: 672.45 | AT152: 0 | AU152: 2708.53 | AV152: 68.29 | AW152: 3449.27
A153: =IF(IF(AND(A152>0,A152<$I$18),A152+1,0)=0,"",IF(AND(A152>0,A152<$I$18),A152+1,0)) -> 110 | B153: =IFERROR(IF(A153<=$I$18,DATE(YEAR($B$44),MONTH($B$44)+A152,DAY($B$44)),"-"),"") -> 49404 | C153: =IF(A153="","",K152) -> 139444.44 | D153: =C153*$I$20 -> 1519.9444 | E153: =IFERROR(C153+D153,"") -> 140964.39 | F153: =$I$13/$I$18 -> 555.55556 | G153: =IF(A153="","",PMT($I$20,$I$18,$C$44)*-1) -> 2224.912 | H153: =C153*$J$27 -> 32.072222 | I153: =IF(A153="","",IF(K152="","",IF(K152=0,"",$J$28*$I$14))) -> 20 | J153: =IFERROR(SUM(I153+H153+G153),"") -> 2276.9842 | K153: =C153-F153 -> 138888.89 | O153: =IFERROR(F153*$O$39,0) -> 16.666667 | P153: =IF($A153<=$I$18,B153-B152,) -> 31 | Q153: 365 | AA153: =A158 -> 115 | AB153: =IF($AA$36=1,VLOOKUP(AA153,$AE$38:$AK$218,6,0),IF($AA$36=2,VLOOKUP(AA153,$AE$38:$AK$218,4,0),VLOOKUP(AA153,$AE$38:$AK$218,2,0))) -> 16279.105 | AC153: =IF($AA$36=1,VLOOKUP(AA153,$AE$38:$AK$278,7,0),IF($AA$36=2,VLOOKUP(AA153,$AE$38:$AK$278,5,0),VLOOKUP(AA153,$AE$38:$AK$278,3,0))) -> 2276.3453 | AE153: =AA153 -> 115 | AF153: =IFERROR(VLOOKUP(AE153,[1]Cálculos_PRICE!$A$32:$K$212,10,0),"") -> 16279.105 | AG153: =IFERROR(VLOOKUP(AE153,'Cálculos_CGI - SAC FIXA'!A151:K543,10,0),"") -> 2276.3453 | AH153: =IFERROR(VLOOKUP(AE153,[1]Cálculos_PRICE!$A$32:$K$212,6,0),"") -> 6028.1028 | AI153: =IFERROR(VLOOKUP(AE153,'Cálculos_CGI - SAC FIXA'!A151:K543,6,0),"") -> 555.55556 | AJ153: =IFERROR(VLOOKUP(AE153,[1]Cálculos_PRICE!$A$32:$K$240,11,0),"") -> 665712.41 | AK153: =IFERROR(VLOOKUP(AE153,'Cálculos_CGI - SAC FIXA'!A151:K543,11,0),"") -> 136111.11 | AN153: =AR154-K159 -> 73054.754 | AO153: 116 | AP153: JP | AQ153: 47577 | AR153: 209291.43 | AS153: 681.12 | AT153: 0 | AU153: 2699.86 | AV153: 68.14 | AW153: 3449.12
A154: =IF(IF(AND(A153>0,A153<$I$18),A153+1,0)=0,"",IF(AND(A153>0,A153<$I$18),A153+1,0)) -> 111 | B154: =IFERROR(IF(A154<=$I$18,DATE(YEAR($B$44),MONTH($B$44)+A153,DAY($B$44)),"-"),"") -> 49434 | C154: =IF(A154="","",K153) -> 138888.89 | D154: =C154*$I$20 -> 1513.8889 | E154: =IFERROR(C154+D154,"") -> 140402.78 | F154: =$I$13/$I$18 -> 555.55556 | G154: =IF(A154="","",PMT($I$20,$I$18,$C$44)*-1) -> 2224.912 | H154: =C154*$J$27 -> 31.944444 | I154: =IF(A154="","",IF(K153="","",IF(K153=0,"",$J$28*$I$14))) -> 20 | J154: =IFERROR(SUM(I154+H154+G154),"") -> 2276.8564 | K154: =C154-F154 -> 138333.33 | O154: =IFERROR(F154*$O$39,0) -> 16.666667 | P154: =IF($A154<=$I$18,B154-B153,) -> 30 | Q154: 365 | AA154: =A159 -> 116 | AB154: =IF($AA$36=1,VLOOKUP(AA154,$AE$38:$AK$218,6,0),IF($AA$36=2,VLOOKUP(AA154,$AE$38:$AK$218,4,0),VLOOKUP(AA154,$AE$38:$AK$218,2,0))) -> 16277.765 | AC154: =IF($AA$36=1,VLOOKUP(AA154,$AE$38:$AK$278,7,0),IF($AA$36=2,VLOOKUP(AA154,$AE$38:$AK$278,5,0),VLOOKUP(AA154,$AE$38:$AK$278,3,0))) -> 2276.2175 | AE154: =AA154 -> 116 | AF154: =IFERROR(VLOOKUP(AE154,[1]Cálculos_PRICE!$A$32:$K$212,10,0),"") -> 16277.765 | AG154: =IFERROR(VLOOKUP(AE154,'Cálculos_CGI - SAC FIXA'!A152:K544,10,0),"") -> 2276.2175 | AH154: =IFERROR(VLOOKUP(AE154,[1]Cálculos_PRICE!$A$32:$K$212,6,0),"") -> 6118.5243 | AI154: =IFERROR(VLOOKUP(AE154,'Cálculos_CGI - SAC FIXA'!A152:K544,6,0),"") -> 555.55556 | AJ154: =IFERROR(VLOOKUP(AE154,[1]Cálculos_PRICE!$A$32:$K$240,11,0),"") -> 659593.88 | AK154: =IFERROR(VLOOKUP(AE154,'Cálculos_CGI - SAC FIXA'!A152:K544,11,0),"") -> 135555.56 | AN154: =AR155-K160 -> 72920.4 | AO154: 117 | AP154: JP | AQ154: 47607 | AR154: 208610.31 | AS154: 689.91 | AT154: 0 | AU154: 2691.07 | AV154: 67.98 | AW154: 3448.96
A155: =IF(IF(AND(A154>0,A154<$I$18),A154+1,0)=0,"",IF(AND(A154>0,A154<$I$18),A154+1,0)) -> 112 | B155: =IFERROR(IF(A155<=$I$18,DATE(YEAR($B$44),MONTH($B$44)+A154,DAY($B$44)),"-"),"") -> 49465 | C155: =IF(A155="","",K154) -> 138333.33 | D155: =C155*$I$20 -> 1507.8333 | E155: =IFERROR(C155+D155,"") -> 139841.17 | F155: =$I$13/$I$18 -> 555.55556 | G155: =IF(A155="","",PMT($I$20,$I$18,$C$44)*-1) -> 2224.912 | H155: =C155*$J$27 -> 31.816667 | I155: =IF(A155="","",IF(K154="","",IF(K154=0,"",$J$28*$I$14))) -> 20 | J155: =IFERROR(SUM(I155+H155+G155),"") -> 2276.7286 | K155: =C155-F155 -> 137777.78 | O155: =IFERROR(F155*$O$39,0) -> 16.666667 | P155: =IF($A155<=$I$18,B155-B154,) -> 31 | Q155: 365 | AA155: =A160 -> 117 | AB155: =IF($AA$36=1,VLOOKUP(AA155,$AE$38:$AK$218,6,0),IF($AA$36=2,VLOOKUP(AA155,$AE$38:$AK$218,4,0),VLOOKUP(AA155,$AE$38:$AK$218,2,0))) -> 16276.404 | AC155: =IF($AA$36=1,VLOOKUP(AA155,$AE$38:$AK$278,7,0),IF($AA$36=2,VLOOKUP(AA155,$AE$38:$AK$278,5,0),VLOOKUP(AA155,$AE$38:$AK$278,3,0))) -> 2276.0897 | AE155: =AA155 -> 117 | AF155: =IFERROR(VLOOKUP(AE155,[1]Cálculos_PRICE!$A$32:$K$212,10,0),"") -> 16276.404 | AG155: =IFERROR(VLOOKUP(AE155,'Cálculos_CGI - SAC FIXA'!A153:K545,10,0),"") -> 2276.0897 | AH155: =IFERROR(VLOOKUP(AE155,[1]Cálculos_PRICE!$A$32:$K$212,6,0),"") -> 6210.3022 | AI155: =IFERROR(VLOOKUP(AE155,'Cálculos_CGI - SAC FIXA'!A153:K545,6,0),"") -> 555.55556 | AJ155: =IFERROR(VLOOKUP(AE155,[1]Cálculos_PRICE!$A$32:$K$240,11,0),"") -> 653383.58 | AK155: =IFERROR(VLOOKUP(AE155,'Cálculos_CGI - SAC FIXA'!A153:K545,11,0),"") -> 135000 | AN155: =AR156-K161 -> 72777.146 | AO155: 118 | AP155: JP | AQ155: 47638 | AR155: 207920.4 | AS155: 698.81 | AT155: 0 | AU155: 2682.17 | AV155: 67.82 | AW155: 3448.8
A156: =IF(IF(AND(A155>0,A155<$I$18),A155+1,0)=0,"",IF(AND(A155>0,A155<$I$18),A155+1,0)) -> 113 | B156: =IFERROR(IF(A156<=$I$18,DATE(YEAR($B$44),MONTH($B$44)+A155,DAY($B$44)),"-"),"") -> 49495 | C156: =IF(A156="","",K155) -> 137777.78 | D156: =C156*$I$20 -> 1501.7778 | E156: =IFERROR(C156+D156,"") -> 139279.56 | F156: =$I$13/$I$18 -> 555.55556 | G156: =IF(A156="","",PMT($I$20,$I$18,$C$44)*-1) -> 2224.912 | H156: =C156*$J$27 -> 31.688889 | I156: =IF(A156="","",IF(K155="","",IF(K155=0,"",$J$28*$I$14))) -> 20 | J156: =IFERROR(SUM(I156+H156+G156),"") -> 2276.6009 | K156: =C156-F156 -> 137222.22 | O156: =IFERROR(F156*$O$39,0) -> 16.666667 | P156: =IF($A156<=$I$18,B156-B155,) -> 30 | Q156: 365 | AA156: =A161 -> 118 | AB156: =IF($AA$36=1,VLOOKUP(AA156,$AE$38:$AK$218,6,0),IF($AA$36=2,VLOOKUP(AA156,$AE$38:$AK$218,4,0),VLOOKUP(AA156,$AE$38:$AK$218,2,0))) -> 16275.023 | AC156: =IF($AA$36=1,VLOOKUP(AA156,$AE$38:$AK$278,7,0),IF($AA$36=2,VLOOKUP(AA156,$AE$38:$AK$278,5,0),VLOOKUP(AA156,$AE$38:$AK$278,3,0))) -> 2275.962 | AE156: =AA156 -> 118 | AF156: =IFERROR(VLOOKUP(AE156,[1]Cálculos_PRICE!$A$32:$K$212,10,0),"") -> 16275.023 | AG156: =IFERROR(VLOOKUP(AE156,'Cálculos_CGI - SAC FIXA'!A154:K546,10,0),"") -> 2275.962 | AH156: =IFERROR(VLOOKUP(AE156,[1]Cálculos_PRICE!$A$32:$K$212,6,0),"") -> 6303.4567 | AI156: =IFERROR(VLOOKUP(AE156,'Cálculos_CGI - SAC FIXA'!A154:K546,6,0),"") -> 555.55556 | AJ156: =IFERROR(VLOOKUP(AE156,[1]Cálculos_PRICE!$A$32:$K$240,11,0),"") -> 647080.12 | AK156: =IFERROR(VLOOKUP(AE156,'Cálculos_CGI - SAC FIXA'!A154:K546,11,0),"") -> 134444.44 | AN156: =AR157-K162 -> 72624.881 | AO156: 119 | AP156: JP | AQ156: 47668 | AR156: 207221.59 | AS156: 707.82 | AT156: 0 | AU156: 2673.16 | AV156: 67.66 | AW156: 3448.64
A157: =IF(IF(AND(A156>0,A156<$I$18),A156+1,0)=0,"",IF(AND(A156>0,A156<$I$18),A156+1,0)) -> 114 | B157: =IFERROR(IF(A157<=$I$18,DATE(YEAR($B$44),MONTH($B$44)+A156,DAY($B$44)),"-"),"") -> 49526 | C157: =IF(A157="","",K156) -> 137222.22 | D157: =C157*$I$20 -> 1495.7222 | E157: =IFERROR(C157+D157,"") -> 138717.94 | F157: =$I$13/$I$18 -> 555.55556 | G157: =IF(A157="","",PMT($I$20,$I$18,$C$44)*-1) -> 2224.912 | H157: =C157*$J$27 -> 31.561111 | I157: =IF(A157="","",IF(K156="","",IF(K156=0,"",$J$28*$I$14))) -> 20 | J157: =IFERROR(SUM(I157+H157+G157),"") -> 2276.4731 | K157: =C157-F157 -> 136666.67 | O157: =IFERROR(F157*$O$39,0) -> 16.666667 | P157: =IF($A157<=$I$18,B157-B156,) -> 31 | Q157: 365 | AA157: =A162 -> 119 | AB157: =IF($AA$36=1,VLOOKUP(AA157,$AE$38:$AK$218,6,0),IF($AA$36=2,VLOOKUP(AA157,$AE$38:$AK$218,4,0),VLOOKUP(AA157,$AE$38:$AK$218,2,0))) -> 16273.621 | AC157: =IF($AA$36=1,VLOOKUP(AA157,$AE$38:$AK$278,7,0),IF($AA$36=2,VLOOKUP(AA157,$AE$38:$AK$278,5,0),VLOOKUP(AA157,$AE$38:$AK$278,3,0))) -> 2275.8342 | AE157: =AA157 -> 119 | AF157: =IFERROR(VLOOKUP(AE157,[1]Cálculos_PRICE!$A$32:$K$212,10,0),"") -> 16273.621 | AG157: =IFERROR(VLOOKUP(AE157,'Cálculos_CGI - SAC FIXA'!A155:K547,10,0),"") -> 2275.8342 | AH157: =IFERROR(VLOOKUP(AE157,[1]Cálculos_PRICE!$A$32:$K$212,6,0),"") -> 6398.0086 | AI157: =IFERROR(VLOOKUP(AE157,'Cálculos_CGI - SAC FIXA'!A155:K547,6,0),"") -> 555.55556 | AJ157: =IFERROR(VLOOKUP(AE157,[1]Cálculos_PRICE!$A$32:$K$240,11,0),"") -> 640682.11 | AK157: =IFERROR(VLOOKUP(AE157,'Cálculos_CGI - SAC FIXA'!A155:K547,11,0),"") -> 133888.89 | AN157: =AR158-K163 -> 72463.487 | AO157: 120 | AP157: JP | AQ157: 47699 | AR157: 206513.77 | AS157: 716.95 | AT157: 0 | AU157: 2664.03 | AV157: 67.5 | AW157: 3448.48
...

Sheet Cálculos_CGI e Fin
D2: Produto | I2: Tipo Imóvel
D3: Crédito Com Garantia de Imóvel - CGI | I3: Loja Comercial
D5: Valor do Crédito Bruto | G5: Valor Estimado do Imóvel | I5: LTV | J5: Prazo | K5: Sistema Amortização
D6: 1000000 | G6: 3000000 | I6: =IFERROR(D6/G6,"") -> 0.33333333 | J6: 240 | K6: PRICE
D8: Carencia em meses | F8: Nome cliente | I8: Nascimento | J8: Seguradora | K8: Renda Familiar Min.
D9: 3 | F9: - | I9: 27368 | J9: EXCELSIOR | K9: =IF(D9>0,VLOOKUP(D9+1,B58:K299,10,0)/36%,VLOOKUP(D9+1,B58:K299,10,0)/36%) -> 39915.199
D14: =IF(J16="","LTV Máximo ou Condição de Negócio fora da Politica de Crédito da Instuição Financeira","")
D15: Valores da Operação | K15: %
D16: Valor Principal do Crédito | J16: =IF( I9="","",VALOR_CREDITO_BRUTO) -> 1000000 | K16: --- | P16: LTV | Q16: 49.99% | R16: 0.6 | S16: 0.7
D17: Valor Estimado do Valor do Imóvel | J17: =IF(J16="","",G6) -> 3000000 | P17: PRICE | Q17: 0.0109 | R17: 0.0109 | S17: 0.0109
D18: Valor Total das Despesas acessórias | J18: =IF(J16="","",IF(J6="",0,3980+3450)) -> 7430 | K18: =IFERROR(IF(J6="",0,J18/J16),"") -> 0.00743 | P18: SAC | Q18: 0.0109 | R18: 0.0109 | S18: 0.0109
D19: Valor Total do IOF no ato da liberação do Crédito | J19: 0 | K19: =IF(J16="","",IFERROR(J19/J16,0)) -> 0 | P19: PRICE | Q19: 0.0099 | R19: 0.0099 | S19: 0.0099
D20: Valor Liquido a ser Liberado ao Emitente ou Vendedor | J20: =IFERROR(J16-J18-J19,"") -> 992570 | K20: =IF(J16="","",IFERROR(J20/J16,0)) -> 0.99257 | P20: SAC | Q20: 0.0099 | R20: 0.0099 | S20: 0.0099
D21: Prazo da Operação | J21: =IF(J16="","",J6) -> 240 | P21: Crédito Com Garantia de Imóvel - CGI
D22: Taxa Nominal - Mensal | J22: 0.0129 | P22: Financiamento Imobiliário - Aquisição
D23: Taxa Nominal - Anual | J23: =IFERROR(J22*12,"") -> 0.1548 | P23: Terreno Com Construção Concluída - TCC
D24: Taxa Efetiva - Mensal | K24: 0.0129
D25: Taxa Efetiva - Anual | J25: =(1+(TAXA))^12-1 -> 0.16626933 | P25: Financiamento Imobiliário - Aquisição TCC
D26: Sistema de Amortização | J26: =SISTEMA_AMORTIZAÇÃO -> PRICE
D27: Data de Vencimento da Primeira Prestação | J27: =VLOOKUP(B60,B58:C299,2,0) -> 46086
D28: Data de Vencimento da Última Prestação | J28: =IFERROR(VLOOKUP(J21,B41:C428,2,0),"") -> 53363
D29: =IF(D9>0,"Valor do prêmio de Seguro - 1ª Prestação (MIP + DFI)","Valor da Prestação (Amortização + Juros)") -> Valor do prêmio de Seguro - 1ª Prestação (MIP + DFI) | J29: =IF(D9>0,SUM(I60:J60),IF(D9>0,VLOOKUP(D9+1,$B$60:$H$72,7,0),IF(J16="","",IF(SISTEMA_AMORTIZAÇÃO=PRICE_PRE,(PMT(TAXA,PRAZO,VALOR_CREDITO_BRUTO)*-1), IF(SISTEMA_AMORTIZAÇÃO=PRICE_POS,(PMT(TAXA,PRAZO,VALOR_CREDITO_BRUTO)*-1), IF(SISTEMA_AMORTIZAÇÃO=SAC_PRE,(VALOR_CREDITO_BRUTO/PRAZO)+(VALOR_CREDITO_BRUTO*TAXA), IF(SISTEMA_AMORTIZAÇÃO=SAC_POS,(VALOR_CREDITO_BRUTO/PRAZO)+(VALOR_CREDITO_BRUTO*TAXA)))))))) -> 564
D30: =IF(D9>0,"Valor Total da Prestação mensal - posterior ao período de carência (Amortização + Juros + MIP + DFI)","Valor Total da Prestação mensal (Amortização + Juros + MIP + DFI)") -> Valor Total da Prestação mensal - posterior ao período de carência (Amortização + Juros + MIP + DFI) | J30: =IF(D9>0,VLOOKUP(D9+1,B60:K72,10,0),IF(J16="","",IFERROR(J29+J32+J33,0))) -> 14369.471 | K30: =IF(K31="","","Observação") -> Observação
D31: =IF(D9>0,"Data de Vencimento da 1ª Prestação mensal posterior periódo de Carência","Data de Vencimento da 1ª Prestação mensal sem Carência") -> Data de Vencimento da 1ª Prestação mensal posterior periódo de Carência | J31: =VLOOKUP(D9+1,B58:C299,2,0) -> 46178 | K31: =IF( I9="","Pendente data de Nascimento", IF( AND( J9="Zurich", ((TODAY()-I9)/365.25)>=65, VALOR_CREDITO_BRUTO>=4000000 ), "Necessário DPS", IF( AND( J9="Zurich", ((TODAY()-I9)/365.25)>65, ((TODAY()-I9)/365.25)<=75, VALOR_CREDITO_BRUTO>=2500000 ), "Necessário DPS", IF( AND( J9="Zurich", ((TODAY()-I9)/365.25)>75, VALOR_CREDITO_BRUTO>=1000000 ), "Necessário DPS", IF( AND( J9="Zurich", VALOR_CREDITO_BRUTO>4000000 ), "Necessário DPS", IF( AND( J9="Excelsior", OR( VALOR_ESTIMADO_IMÓVEL>2300000, VALOR_CREDITO_BRUTO>2300000 ) ), "Máximo permitido é de R$ 2.3MM", IF( AND( ((TODAY()-I9)/365.25)>=55, J9="Excelsior", OR( VALOR_CREDITO_BRUTO>=1000000, VALOR_ESTIMADO_IMÓVEL>=1000000 ) ), "Necessário DPS", IF( AND( ((TODAY()-I9)/365.25)>=55, J9="Excelsior", OR( VALOR_ESTIMADO_IMÓVEL>2300000, VALOR_CREDITO_BRUTO>2300000 ) ), "Necessário DPS e Máximo permitido é de R$ 2.3MM", IF( AND( ((TODAY()-I9)/365.25)<55, J9="Excelsior", VALOR_CREDITO_BRUTO<1000000, VALOR_ESTIMADO_IMÓVEL<=1000000 ), "", "" ) ) ) ) ) ) ) )) -> Máximo permitido é de R$ 2.3MM
D32: =IF(D9>0,"Valor do Prêmio de Seguro MIP (Morte e Invalidez Permanente) 1ª Prestação","Valor do Prêmio de Seguro MIP (Morte e Invalidez Permanente)") -> Valor do Prêmio de Seguro MIP (Morte e Invalidez Permanente) 1ª Prestação | J32: =$I$60 -> 342 | K32: =IF(AND(VALOR_CREDITO_BRUTO>10000000,J9="ZURICH"),"0,017100%",IF(J9="EXCELSIOR","0,0171%","0,017100%")) -> 0,0171%
D33: Valor do Prêmio de Seguro DFI (Danos Físicos ao Imóvel) 1ª Prestação | J33: =$J$60 -> 222 | K33: =IF(AND(VALOR_ESTIMADO_IMÓVEL>10000000,J9="ZURICH"),"0,003900%",IF(J9="EXCELSIOR","0,0037%","0,003000%")) -> 0,0037%
D35: CET - Custo Efetitvo Total | J35: =AG424 -> 0.17187437
P41: Formulas de Cálculo IOF | V41: Formulas de Cálculo Idade
Q43: Calculo IOF | U43: Part | V43: Faixa Idade | W43: Idade | X43: Alicota | Y43: DFI | Z43: % de Comp. Renda
P44: Acima de 12meses | Q44: 0.03 | R44: =SUM(Q72:Q419) -> 30984.079 | S44: =SUM(R44:R46) -> 34912.599 | U44: 1° Part | V44: =[1]Capa!P6 -> 29586 | W44: =IF($V$44="","",INT((TODAY())-$V$44)/365.25) -> 45.097878 | X44: =IF(AND(W44>=U64,W44<U65),W64,IF(AND(W44>=U65,W44<U66),W65,IF(AND(W44>=U66,W44<U67),W66,IF(AND(W44>=U67,W44<U68),W67,IF(AND(W44>=U68,W44<U69),W68,IF(AND(W44>=U69,W44<U70),W69,IF(AND(W44>=U70,W44<U71),W70,IF(AND(W44>=U71,W44<U72),W71,IF(AND(W44>=U72,W44<V72),W72,""))))))))) -> 0.00023 | Y44: 4e-05
P45: Valor Financiado | Q45: 0.0038 | R45: =ROUNDUP(Q45*$D$59,2) -> 3800 | U45: 2° Part
P46: Até 12 meses | Q46: 8.2e-05 | R46: =SUM(Q60:Q71) -> 128.52 | U46: 3° Part
D47: Valores Meramente ilustrativos para efeitos de Simulação Inicial
D48: Não Representa - Aprovação de Crédito
D49: A planilha definitiva será enviada posteriormente por ocasião da formalização da operação do Agente Financeiro
B58: Parc | C58: Vencimento | D58: Saldo Inicial | E58: Juros | F58: Saldo Atualizado | G58: Amortização | H58: Prestação Mensal | I58: MIP Morte Invalidez Permanente | J58: DFI Danos Físico do Imóvel | K58: Prestação Mensal Total | L58: Saldo Devedor | N58: =IF(D9>0,"LTV Saldo Carência","") -> LTV Saldo Carência | Q58: IOF DIÁRIO | R58: DIAS | S58: DIAS_SOMA | U58: 4° Part | AC58: TAXA JUROS | AF58: CET s/seguro | AG58: CET c/seguro
B59: 0 | C59: =TODAY() -> 46058 | D59: =J16 -> 1000000 | H59: =-D59 -> -1000000 | K59: =J20*-1 -> -992570 | L59: =D59 -> 1000000 | U59: 5° Part | AC59: 0 | AD59: =J16*-1 -> -1000000 | AE59: =C59 -> 46058 | AF59: =J20*-1 -> -992570 | AG59: =AF59 -> -992570
A60: =J21 -> 240 | B60: =IF(AND(B59=0,B59<$J$21),B59+1,0) -> 1 | C60: =IFERROR(IF(B60<=$J$21,DATE(YEAR(C59),MONTH(C59)+1,DAY(C59)),""),"") -> 46086 | D60: =IF(B60="","",L59) -> 1000000 | E60: =IFERROR((D60*J22),"") -> 12900 | F60: =IFERROR((D60+E60),"") -> 1012900 | G60: =IF($D$9>=B60,0,IFERROR(IF(C60="","",IF(SISTEMA_AMORTIZAÇÃO=PRICE_PRE,H60-E60, IF(SISTEMA_AMORTIZAÇÃO=SAC_PRE,D60/A60, IF(SISTEMA_AMORTIZAÇÃO=SAC_POS,D60/A60)))),"")) -> 0 | H60: =IF(D9>0,0,IF(J16="","",IF(SISTEMA_AMORTIZAÇÃO=PRICE_PRE,(PMT(TAXA,A60,-$D60,)), IF(SISTEMA_AMORTIZAÇÃO=PRICE_POS,(PMT(TAXA,A60,$D60)*-1), IF(SISTEMA_AMORTIZAÇÃO=SAC_PRE,(D60/A60)+(D60*TAXA), IF(SISTEMA_AMORTIZAÇÃO=SAC_POS,(D60/A60)+(D60*TAXA))))))) -> 0 | I60: =IFERROR(D60*$K$32,"")*2 -> 342 | J60: =IF(B60="","",IF(L59="","",IF(L59=0,"",$K$33*$J$17)))*2 -> 222 | K60: =IFERROR(SUM(J60+I60+H60),"") -> 564 | L60: =IF(D9>0,SUM(D60:E60),IFERROR(D60-G60,"")) -> 1012900 | N60: =IF($D$9>=B60,L60/$J$17,"") -> 0.33763333 | Q60: =ROUNDUP(G60*$Q$46*S60,2) -> 0 | R60: =IF($B60<=$J$21,C60-C59,) -> 28 | S60: =IF($B60<=$J$21,$C60-$C$59,) -> 28 | U60: 6° Part | AC60: 30 | AD60: =IF(H60="",0,H60) -> 0 | AE60: =IF(C60="",0,C60) -> 46086 | AF60: =IF(AD60="",0,AD60) -> 0 | AG60: =IF(K60="",0,K60) -> 564
A61: =IFERROR(IF(A60-1<1,"",A60-1),"") -> 239 | B61: =IF(IF(AND(B60>0,B60<$J$21),B60+1,0)=0,"",IF(AND(B60>0,B60<$J$21),B60+1,0)) -> 2 | C61: =IFERROR(IF(B61<=$J$21,DATE(YEAR(C60),MONTH(C60)+1,DAY(C60)),""),"") -> 46117 | D61: =IF(B61="","",L60) -> 1012900 | E61: =IFERROR(D61*TAXA,"") -> 13066.41 | F61: =IFERROR(D61+E61,"") -> 1025966.4 | G61: =IF($D$9>=B61,0,IFERROR(IF(C61="","",IF(SISTEMA_AMORTIZAÇÃO=PRICE_PRE,H61-E61, IF(SISTEMA_AMORTIZAÇÃO=SAC_PRE,D61/A61, IF(SISTEMA_AMORTIZAÇÃO=SAC_POS,D61/A61)))),"")) -> 0 | H61: =IF($D$9>=B61,0,IF(D61="","", IF(SISTEMA_AMORTIZAÇÃO=PRICE_PRE,(PMT(TAXA,A61,$D61,)*-1), IF(SISTEMA_AMORTIZAÇÃO=SAC_POS,(D61/A61)+(D61*TAXA))))) -> 0 | I61: =IFERROR(D61*$K$32,"") -> 173.2059 | J61: =IF(B61="","",IF(L60="","",IF(L60=0,"",$K$33*$J$17))) -> 111 | K61: =IFERROR(SUM(J61+I61+H61),"") -> 284.2059 | L61: =IF($D$9>=B61,SUM(D61:E61),IFERROR(D61-G61,"")) -> 1025966.4 | N61: =IF($D$9>=B61,L61/$J$17,"") -> 0.3419888 | Q61: =ROUNDUP(G61*$Q$46*S61,2) -> 0 | R61: =IF($B61<=$J$21,C61-C60,) -> 31 | S61: =IF($B61<=$J$21,$C61-$C$59,) -> 59 | U61: 7° Part | AC61: 60 | AD61: =IF(H61="",0,H61) -> 0 | AE61: =IF(C61="",0,C61) -> 46117 | AF61: =IF(AD61="",0,AD61) -> 0 | AG61: =IF(K61="",0,K61) -> 284.2059
A62: =IFERROR(IF(A61-1<1,"",A61-1),"") -> 238 | B62: =IF(IF(AND(B61>0,B61<$J$21),B61+1,0)=0,"",IF(AND(B61>0,B61<$J$21),B61+1,0)) -> 3 | C62: =IFERROR(IF(B62<=$J$21,DATE(YEAR(C61),MONTH(C61)+1,DAY(C61)),""),"") -> 46147 | D62: =IF(B62="","",L61) -> 1025966.4 | E62: =IFERROR(D62*TAXA,"") -> 13234.967 | F62: =IFERROR(D62+E62,"") -> 1039201.4 | G62: =IF($D$9>=B62,0,IFERROR(IF(C62="","",IF(SISTEMA_AMORTIZAÇÃO=PRICE_PRE,H62-E62, IF(SISTEMA_AMORTIZAÇÃO=SAC_PRE,D62/A62, IF(SISTEMA_AMORTIZAÇÃO=SAC_POS,D62/A62)))),"")) -> 0 | H62: =IF($D$9>=B62,0,IF(D62="","", IF(SISTEMA_AMORTIZAÇÃO=PRICE_PRE,(PMT(TAXA,A62,$D62,)*-1), IF(SISTEMA_AMORTIZAÇÃO=SAC_POS,(D62/A62)+(D62*TAXA))))) -> 0 | I62: =IFERROR(D62*$K$32,"") -> 175.44026 | J62: =IF(B62="","",IF(L61="","",IF(L61=0,"",$K$33*$J$17))) -> 111 | K62: =IFERROR(SUM(J62+I62+H62),"") -> 286.44026 | L62: =IF($D$9>=B62,SUM(D62:E62),IFERROR(D62-G62,"")) -> 1039201.4 | N62: =IF($D$9>=B62,L62/$J$17,"") -> 0.34640046 | Q62: =ROUNDUP(G62*$Q$46*S62,2) -> 0 | R62: =IF($B62<=$J$21,C62-C61,) -> 30 | S62: =IF($B62<=$J$21,$C62-$C$59,) -> 89 | U62: 8° Part | AC62: 90 | AD62: =IF(H62="",0,H62) -> 0 | AE62: =IF(C62="",0,C62) -> 46147 | AF62: =IF(AD62="",0,AD62) -> 0 | AG62: =IF(K62="",0,K62) -> 286.44026
A63: =IFERROR(IF(A62-1<1,"",A62-1),"") -> 237 | B63: =IF(IF(AND(B62>0,B62<$J$21),B62+1,0)=0,"",IF(AND(B62>0,B62<$J$21),B62+1,0)) -> 4 | C63: =IFERROR(IF(B63<=$J$21,DATE(YEAR(C62),MONTH(C62)+1,DAY(C62)),""),"") -> 46178 | D63: =IF(B63="","",L62) -> 1039201.4 | E63: =IFERROR(D63*TAXA,"") -> 13405.698 | F63: =IFERROR(D63+E63,"") -> 1052607.1 | G63: =IF($D$9>=B63,0,IFERROR(IF(C63="","",IF(SISTEMA_AMORTIZAÇÃO=PRICE_PRE,H63-E63, IF(SISTEMA_AMORTIZAÇÃO=SAC_PRE,D63/A63, IF(SISTEMA_AMORTIZAÇÃO=SAC_POS,D63/A63)))),"")) -> 675.07028 | H63: =IF($D$9>=B63,0,IF(D63="","", IF(SISTEMA_AMORTIZAÇÃO=PRICE_PRE,(PMT(TAXA,A63,$D63,)*-1), IF(SISTEMA_AMORTIZAÇÃO=SAC_POS,(D63/A63)+(D63*TAXA))))) -> 14080.768 | I63: =IFERROR(D63*$K$32,"") -> 177.70344 | J63: =IF(B63="","",IF(L62="","",IF(L62=0,"",$K$33*$J$17))) -> 111 | K63: =IFERROR(SUM(J63+I63+H63),"") -> 14369.471 | L63: =IF($D$9>=B63,SUM(D63:E63),IFERROR(D63-G63,"")) -> 1038526.3 | N63: =IF($D$9>=B63,L63/$J$17,"") | Q63: =ROUNDUP(G63*$Q$46*S63,2) -> 6.65 | R63: =IF($B63<=$J$21,C63-C62,) -> 31 | S63: =IF($B63<=$J$21,$C63-$C$59,) -> 120 | U63: Faixa Idade | W63: Alicota | X63: DFI | AC63: 120 | AD63: =IF(H63="",0,H63) -> 14080.768 | AE63: =IF(C63="",0,C63) -> 46178 | AF63: =IF(AD63="",0,AD63) -> 14080.768 | AG63: =IF(K63="",0,K63) -> 14369.471
A64: =IFERROR(IF(A63-1<1,"",A63-1),"") -> 236 | B64: =IF(IF(AND(B63>0,B63<$J$21),B63+1,0)=0,"",IF(AND(B63>0,B63<$J$21),B63+1,0)) -> 5 | C64: =IFERROR(IF(B64<=$J$21,DATE(YEAR(C63),MONTH(C63)+1,DAY(C63)),""),"") -> 46208 | D64: =IF(B64="","",L63) -> 1038526.3 | E64: =IFERROR(D64*TAXA,"") -> 13396.989 | F64: =IFERROR(D64+E64,"") -> 1051923.3 | G64: =IF($D$9>=B64,0,IFERROR(IF(C64="","",IF(SISTEMA_AMORTIZAÇÃO=PRICE_PRE,H64-E64, IF(SISTEMA_AMORTIZAÇÃO=SAC_PRE,D64/A64, IF(SISTEMA_AMORTIZAÇÃO=SAC_POS,D64/A64)))),"")) -> 683.77868 | H64: =IF($D$9>=B64,0,IF(D64="","", IF(SISTEMA_AMORTIZAÇÃO=PRICE_PRE,(PMT(TAXA,A64,$D64,)*-1), IF(SISTEMA_AMORTIZAÇÃO=SAC_POS,(D64/A64)+(D64*TAXA))))) -> 14080.768 | I64: =IFERROR(D64*$K$32,"") -> 177.588 | J64: =IF(B64="","",IF(L63="","",IF(L63=0,"",$K$33*$J$17))) -> 111 | K64: =IFERROR(SUM(J64+I64+H64),"") -> 14369.356 | L64: =IF($D$9>=B64,SUM(D64:E64),IFERROR(D64-G64,"")) -> 1037842.5 | N64: =IF($D$9>=B64,L64/$J$17,"") | Q64: =ROUNDUP(G64*$Q$46*S64,2) -> 8.42 | R64: =IF($B64<=$J$21,C64-C63,) -> 30 | S64: =IF($B64<=$J$21,$C64-$C$59,) -> 150 | U64: 18 | V64: 25 | W64: 0.00023 | X64: Alicota_1 | AC64: 150 | AD64: =IF(H64="",0,H64) -> 14080.768 | AE64: =IF(C64="",0,C64) -> 46208 | AF64: =IF(AD64="",0,AD64) -> 14080.768 | AG64: =IF(K64="",0,K64) -> 14369.356
A65: =IFERROR(IF(A64-1<1,"",A64-1),"") -> 235 | B65: =IF(IF(AND(B64>0,B64<$J$21),B64+1,0)=0,"",IF(AND(B64>0,B64<$J$21),B64+1,0)) -> 6 | C65: =IFERROR(IF(B65<=$J$21,DATE(YEAR(C64),MONTH(C64)+1,DAY(C64)),""),"") -> 46239 | D65: =IF(B65="","",L64) -> 1037842.5 | E65: =IFERROR(D65*TAXA,"") -> 13388.169 | F65: =IFERROR(D65+E65,"") -> 1051230.7 | G65: =IF($D$9>=B65,0,IFERROR(IF(C65="","",IF(SISTEMA_AMORTIZAÇÃO=PRICE_PRE,H65-E65, IF(SISTEMA_AMORTIZAÇÃO=SAC_PRE,D65/A65, IF(SISTEMA_AMORTIZAÇÃO=SAC_POS,D65/A65)))),"")) -> 692.59943 | H65: =IF($D$9>=B65,0,IF(D65="","", IF(SISTEMA_AMORTIZAÇÃO=PRICE_PRE,(PMT(TAXA,A65,$D65,)*-1), IF(SISTEMA_AMORTIZAÇÃO=SAC_POS,(D65/A65)+(D65*TAXA))))) -> 14080.768 | I65: =IFERROR(D65*$K$32,"") -> 177.47107 | J65: =IF(B65="","",IF(L64="","",IF(L64=0,"",$K$33*$J$17))) -> 111 | K65: =IFERROR(SUM(J65+I65+H65),"") -> 14369.239 | L65: =IF($D$9>=B65,SUM(D65:E65),IFERROR(D65-G65,"")) -> 1037149.9 | N65: =IF($D$9>=B65,L65/$J$17,"") | Q65: =ROUNDUP(G65*$Q$46*S65,2) -> 10.28 | R65: =IF($B65<=$J$21,C65-C64,) -> 31 | S65: =IF($B65<=$J$21,$C65-$C$59,) -> 181 | U65: 26 | V65: 30 | W65: 0.00023 | X65: Alicota_2 | AC65: 180 | AD65: =IF(H65="",0,H65) -> 14080.768 | AE65: =IF(C65="",0,C65) -> 46239 | AF65: =IF(AD65="",0,AD65) -> 14080.768 | AG65: =IF(K65="",0,K65) -> 14369.239
A66: =IFERROR(IF(A65-1<1,"",A65-1),"") -> 234 | B66: =IF(IF(AND(B65>0,B65<$J$21),B65+1,0)=0,"",IF(AND(B65>0,B65<$J$21),B65+1,0)) -> 7 | C66: =IFERROR(IF(B66<=$J$21,DATE(YEAR(C65),MONTH(C65)+1,DAY(C65)),""),"") -> 46270 | D66: =IF(B66="","",L65) -> 1037149.9 | E66: =IFERROR(D66*TAXA,"") -> 13379.234 | F66: =IFERROR(D66+E66,"") -> 1050529.2 | G66: =IF($D$9>=B66,0,IFERROR(IF(C66="","",IF(SISTEMA_AMORTIZAÇÃO=PRICE_PRE,H66-E66, IF(SISTEMA_AMORTIZAÇÃO=SAC_PRE,D66/A66, IF(SISTEMA_AMORTIZAÇÃO=SAC_POS,D66/A66)))),"")) -> 701.53396 | H66: =IF($D$9>=B66,0,IF(D66="","", IF(SISTEMA_AMORTIZAÇÃO=PRICE_PRE,(PMT(TAXA,A66,$D66,)*-1), IF(SISTEMA_AMORTIZAÇÃO=SAC_POS,(D66/A66)+(D66*TAXA))))) -> 14080.768 | I66: =IFERROR(D66*$K$32,"") -> 177.35264 | J66: =IF(B66="","",IF(L65="","",IF(L65=0,"",$K$33*$J$17))) -> 111 | K66: =IFERROR(SUM(J66+I66+H66),"") -> 14369.121 | L66: =IF($D$9>=B66,SUM(D66:E66),IFERROR(D66-G66,"")) -> 1036448.4 | N66: =IF($D$9>=B66,L66/$J$17,"") | Q66: =ROUNDUP(G66*$Q$46*S66,2) -> 12.2 | R66: =IF($B66<=$J$21,C66-C65,) -> 31 | S66: =IF($B66<=$J$21,$C66-$C$59,) -> 212 | U66: 31 | V66: 35 | W66: 0.00023 | X66: Alicota_3 | AC66: 210 | AD66: =IF(H66="",0,H66) -> 14080.768 | AE66: =IF(C66="",0,C66) -> 46270 | AF66: =IF(AD66="",0,AD66) -> 14080.768 | AG66: =IF(K66="",0,K66) -> 14369.121
A67: =IFERROR(IF(A66-1<1,"",A66-1),"") -> 233 | B67: =IF(IF(AND(B66>0,B66<$J$21),B66+1,0)=0,"",IF(AND(B66>0,B66<$J$21),B66+1,0)) -> 8 | C67: =IFERROR(IF(B67<=$J$21,DATE(YEAR(C66),MONTH(C66)+1,DAY(C66)),""),"") -> 46300 | D67: =IF(B67="","",L66) -> 1036448.4 | E67: =IFERROR(D67*TAXA,"") -> 13370.184 | F67: =IFERROR(D67+E67,"") -> 1049818.6 | G67: =IF($D$9>=B67,0,IFERROR(IF(C67="","",IF(SISTEMA_AMORTIZAÇÃO=PRICE_PRE,H67-E67, IF(SISTEMA_AMORTIZAÇÃO=SAC_PRE,D67/A67, IF(SISTEMA_AMORTIZAÇÃO=SAC_POS,D67/A67)))),"")) -> 710.58375 | H67: =IF($D$9>=B67,0,IF(D67="","", IF(SISTEMA_AMORTIZAÇÃO=PRICE_PRE,(PMT(TAXA,A67,$D67,)*-1), IF(SISTEMA_AMORTIZAÇÃO=SAC_POS,(D67/A67)+(D67*TAXA))))) -> 14080.768 | I67: =IFERROR(D67*$K$32,"") -> 177.23268 | J67: =IF(B67="","",IF(L66="","",IF(L66=0,"",$K$33*$J$17))) -> 111 | K67: =IFERROR(SUM(J67+I67+H67),"") -> 14369.001 | L67: =IF($D$9>=B67,SUM(D67:E67),IFERROR(D67-G67,"")) -> 1035737.8 | N67: =IF($D$9>=B67,L67/$J$17,"") | Q67: =ROUNDUP(G67*$Q$46*S67,2) -> 14.11 | R67: =IF($B67<=$J$21,C67-C66,) -> 30 | S67: =IF($B67<=$J$21,$C67-$C$59,) -> 242 | U67: 36 | V67: 40 | W67: 0.00023 | X67: Alicota_4 | AC67: 240 | AD67: =IF(H67="",0,H67) -> 14080.768 | AE67: =IF(C67="",0,C67) -> 46300 | AF67: =IF(AD67="",0,AD67) -> 14080.768 | AG67: =IF(K67="",0,K67) -> 14369.001
A68: =IFERROR(IF(A67-1<1,"",A67-1),"") -> 232 | B68: =IF(IF(AND(B67>0,B67<$J$21),B67+1,0)=0,"",IF(AND(B67>0,B67<$J$21),B67+1,0)) -> 9 | C68: =IFERROR(IF(B68<=$J$21,DATE(YEAR(C67),MONTH(C67)+1,DAY(C67)),""),"") -> 46331 | D68: =IF(B68="","",L67) -> 1035737.8 | E68: =IFERROR(D68*TAXA,"") -> 13361.018 | F68: =IFERROR(D68+E68,"") -> 1049098.8 | G68: =IF($D$9>=B68,0,IFERROR(IF(C68="","",IF(SISTEMA_AMORTIZAÇÃO=PRICE_PRE,H68-E68, IF(SISTEMA_AMORTIZAÇÃO=SAC_PRE,D68/A68, IF(SISTEMA_AMORTIZAÇÃO=SAC_POS,D68/A68)))),"")) -> 719.75028 | H68: =IF($D$9>=B68,0,IF(D68="","", IF(SISTEMA_AMORTIZAÇÃO=PRICE_PRE,(PMT(TAXA,A68,$D68,)*-1), IF(SISTEMA_AMORTIZAÇÃO=SAC_POS,(D68/A68)+(D68*TAXA))))) -> 14080.768 | I68: =IFERROR(D68*$K$32,"") -> 177.11117 | J68: =IF(B68="","",IF(L67="","",IF(L67=0,"",$K$33*$J$17))) -> 111 | K68: =IFERROR(SUM(J68+I68+H68),"") -> 14368.879 | L68: =IF($D$9>=B68,SUM(D68:E68),IFERROR(D68-G68,"")) -> 1035018.1 | N68: =IF($D$9>=B68,L68/$J$17,"") | Q68: =ROUNDUP(G68*$Q$46*S68,2) -> 16.12 | R68: =IF($B68<=$J$21,C68-C67,) -> 31 | S68: =IF($B68<=$J$21,$C68-$C$59,) -> 273 | U68: 41 | V68: 50 | W68: 0.00023 | X68: Alicota_5 | AC68: 270 | AD68: =IF(H68="",0,H68) -> 14080.768 | AE68: =IF(C68="",0,C68) -> 46331 | AF68: =IF(AD68="",0,AD68) -> 14080.768 | AG68: =IF(K68="",0,K68) -> 14368.879
A69: =IFERROR(IF(A68-1<1,"",A68-1),"") -> 231 | B69: =IF(IF(AND(B68>0,B68<$J$21),B68+1,0)=0,"",IF(AND(B68>0,B68<$J$21),B68+1,0)) -> 10 | C69: =IFERROR(IF(B69<=$J$21,DATE(YEAR(C68),MONTH(C68)+1,DAY(C68)),""),"") -> 46361 | D69: =IF(B69="","",L68) -> 1035018.1 | E69: =IFERROR(D69*TAXA,"") -> 13351.733 | F69: =IFERROR(D69+E69,"") -> 1048369.8 | G69: =IF($D$9>=B69,0,IFERROR(IF(C69="","",IF(SISTEMA_AMORTIZAÇÃO=PRICE_PRE,H69-E69, IF(SISTEMA_AMORTIZAÇÃO=SAC_PRE,D69/A69, IF(SISTEMA_AMORTIZAÇÃO=SAC_POS,D69/A69)))),"")) -> 729.03506 | H69: =IF($D$9>=B69,0,IF(D69="","", IF(SISTEMA_AMORTIZAÇÃO=PRICE_PRE,(PMT(TAXA,A69,$D69,)*-1), IF(SISTEMA_AMORTIZAÇÃO=SAC_POS,(D69/A69)+(D69*TAXA))))) -> 14080.768 | I69: =IFERROR(D69*$K$32,"") -> 176.98809 | J69: =IF(B69="","",IF(L68="","",IF(L68=0,"",$K$33*$J$17))) -> 111 | K69: =IFERROR(SUM(J69+I69+H69),"") -> 14368.756 | L69: =IF($D$9>=B69,SUM(D69:E69),IFERROR(D69-G69,"")) -> 1034289 | N69: =IF($D$9>=B69,L69/$J$17,"") | Q69: =ROUNDUP(G69*$Q$46*S69,2) -> 18.12 | R69: =IF($B69<=$J$21,C69-C68,) -> 30 | S69: =IF($B69<=$J$21,$C69-$C$59,) -> 303 | U69: 51 | V69: 60 | W69: 0.00023 | X69: Alicota_6 | AC69: 300 | AD69: =IF(H69="",0,H69) -> 14080.768 | AE69: =IF(C69="",0,C69) -> 46361 | AF69: =IF(AD69="",0,AD69) -> 14080.768 | AG69: =IF(K69="",0,K69) -> 14368.756
A70: =IFERROR(IF(A69-1<1,"",A69-1),"") -> 230 | B70: =IF(IF(AND(B69>0,B69<$J$21),B69+1,0)=0,"",IF(AND(B69>0,B69<$J$21),B69+1,0)) -> 11 | C70: =IFERROR(IF(B70<=$J$21,DATE(YEAR(C69),MONTH(C69)+1,DAY(C69)),""),"") -> 46392 | D70: =IF(B70="","",L69) -> 1034289 | E70: =IFERROR(D70*TAXA,"") -> 13342.328 | F70: =IFERROR(D70+E70,"") -> 1047631.4 | G70: =IF($D$9>=B70,0,IFERROR(IF(C70="","",IF(SISTEMA_AMORTIZAÇÃO=PRICE_PRE,H70-E70, IF(SISTEMA_AMORTIZAÇÃO=SAC_PRE,D70/A70, IF(SISTEMA_AMORTIZAÇÃO=SAC_POS,D70/A70)))),"")) -> 738.43961 | H70: =IF($D$9>=B70,0,IF(D70="","", IF(SISTEMA_AMORTIZAÇÃO=PRICE_PRE,(PMT(TAXA,A70,$D70,)*-1), IF(SISTEMA_AMORTIZAÇÃO=SAC_POS,(D70/A70)+(D70*TAXA))))) -> 14080.768 | I70: =IFERROR(D70*$K$32,"") -> 176.86342 | J70: =IF(B70="","",IF(L69="","",IF(L69=0,"",$K$33*$J$17))) -> 111 | K70: =IFERROR(SUM(J70+I70+H70),"") -> 14368.631 | L70: =IF($D$9>=B70,SUM(D70:E70),IFERROR(D70-G70,"")) -> 1033550.6 | N70: =IF($D$9>=B70,L70/$J$17,"") | Q70: =ROUNDUP(G70*$Q$46*S70,2) -> 20.23 | R70: =IF($B70<=$J$21,C70-C69,) -> 31 | S70: =IF($B70<=$J$21,$C70-$C$59,) -> 334 | U70: 61 | V70: 70 | W70: 0.00023 | X70: Alicota_7 | AC70: 330 | AD70: =IF(H70="",0,H70) -> 14080.768 | AE70: =IF(C70="",0,C70) -> 46392 | AF70: =IF(AD70="",0,AD70) -> 14080.768 | AG70: =IF(K70="",0,K70) -> 14368.631
A71: =IFERROR(IF(A70-1<1,"",A70-1),"") -> 229 | B71: =IF(IF(AND(B70>0,B70<$J$21),B70+1,0)=0,"",IF(AND(B70>0,B70<$J$21),B70+1,0)) -> 12 | C71: =IFERROR(IF(B71<=$J$21,DATE(YEAR(C70),MONTH(C70)+1,DAY(C70)),""),"") -> 46423 | D71: =IF(B71="","",L70) -> 1033550.6 | E71: =IFERROR(D71*TAXA,"") -> 13332.803 | F71: =IFERROR(D71+E71,"") -> 1046883.4 | G71: =IF($D$9>=B71,0,IFERROR(IF(C71="","",IF(SISTEMA_AMORTIZAÇÃO=PRICE_PRE,H71-E71, IF(SISTEMA_AMORTIZAÇÃO=SAC_PRE,D71/A71, IF(SISTEMA_AMORTIZAÇÃO=SAC_POS,D71/A71)))),"")) -> 747.96548 | H71: =IF($D$9>=B71,0,IF(D71="","", IF(SISTEMA_AMORTIZAÇÃO=PRICE_PRE,(PMT(TAXA,A71,$D71,)*-1), IF(SISTEMA_AMORTIZAÇÃO=SAC_POS,(D71/A71)+(D71*TAXA))))) -> 14080.768 | I71: =IFERROR(D71*$K$32,"") -> 176.73715 | J71: =IF(B71="","",IF(L70="","",IF(L70=0,"",$K$33*$J$17))) -> 111 | K71: =IFERROR(SUM(J71+I71+H71),"") -> 14368.505 | L71: =IF($D$9>=B71,SUM(D71:E71),IFERROR(D71-G71,"")) -> 1032802.6 | N71: =IF($D$9>=B71,L71/$J$17,"") | Q71: =ROUNDUP(G71*$Q$46*S71,2) -> 22.39 | R71: =IF($B71<=$J$21,C71-C70,) -> 31 | S71: =IF($B71<=$J$21,$C71-$C$59,) -> 365 | U71: 71 | V71: 75 | W71: 0.00023 | X71: Alicota_8 | AC71: 360 | AD71: =IF(H71="",0,H71) -> 14080.768 | AE71: =IF(C71="",0,C71) -> 46423 | AF71: =IF(AD71="",0,AD71) -> 14080.768 | AG71: =IF(K71="",0,K71) -> 14368.505
A72: =IFERROR(IF(A71-1<1,"",A71-1),"") -> 228 | B72: =IF(IF(AND(B71>0,B71<$J$21),B71+1,0)=0,"",IF(AND(B71>0,B71<$J$21),B71+1,0)) -> 13 | C72: =IFERROR(IF(B72<=$J$21,DATE(YEAR(C71),MONTH(C71)+1,DAY(C71)),""),"") -> 46451 | D72: =IF(B72="","",L71) -> 1032802.6 | E72: =IFERROR(D72*TAXA,"") -> 13323.154 | F72: =IFERROR(D72+E72,"") -> 1046125.8 | G72: =IF($D$9>=B72,0,IFERROR(IF(C72="","",IF(SISTEMA_AMORTIZAÇÃO=PRICE_PRE,H72-E72, IF(SISTEMA_AMORTIZAÇÃO=SAC_PRE,D72/A72, IF(SISTEMA_AMORTIZAÇÃO=SAC_POS,D72/A72,)))),"")) -> 757.61423 | H72: =IF($D$9>=B72,0,IF(D72="","", IF(SISTEMA_AMORTIZAÇÃO=PRICE_PRE,(PMT(TAXA,A72,$D72,)*-1), IF(SISTEMA_AMORTIZAÇÃO=SAC_POS,(D72/A72)+(D72*TAXA))))) -> 14080.768 | I72: =IFERROR(D72*$K$32,"") -> 176.60925 | J72: =IF(B72="","",IF(L71="","",IF(L71=0,"",$K$33*$J$17))) -> 111 | K72: =IFERROR(SUM(J72+I72+H72),"") -> 14368.377 | L72: =IFERROR(D72-G72,"") -> 1032045 | Q72: =IFERROR(G72*$Q$44,0) -> 22.728427 | R72: =IF($B72<=$J$21,C72-C71,) -> 28 | S72: 365 | U72: 76 | V72: 80.4 | W72: 0.00023 | X72: Alicota_9 | AC72: 390 | AD72: =IF(H72="",0,H72) -> 14080.768 | AE72: =IF(C72="",0,C72) -> 46451 | AF72: =IF(AD72="",0,AD72) -> 14080.768 | AG72: =IF(K72="",0,K72) -> 14368.377
A73: =IFERROR(IF(A72-1<1,"",A72-1),"") -> 227 | B73: =IF(IF(AND(B72>0,B72<$J$21),B72+1,0)=0,"",IF(AND(B72>0,B72<$J$21),B72+1,0)) -> 14 | C73: =IFERROR(IF(B73<=$J$21,DATE(YEAR(C72),MONTH(C72)+1,DAY(C72)),""),"") -> 46482 | D73: =IF(B73="","",L72) -> 1032045 | E73: =IFERROR(D73*TAXA,"") -> 13313.381 | F73: =IFERROR(D73+E73,"") -> 1045358.4 | G73: =IF($D$9>=B73,0,IFERROR(IF(C73="","",IF(SISTEMA_AMORTIZAÇÃO=PRICE_PRE,H73-E73, IF(SISTEMA_AMORTIZAÇÃO=SAC_PRE,D73/A73, IF(SISTEMA_AMORTIZAÇÃO=SAC_POS,D73/A73,)))),"")) -> 767.38746 | H73: =IF($D$9>=B73,0,IF(D73="","", IF(SISTEMA_AMORTIZAÇÃO=PRICE_PRE,(PMT(TAXA,A73,$D73,)*-1), IF(SISTEMA_AMORTIZAÇÃO=SAC_POS,(D73/A73)+(D73*TAXA))))) -> 14080.768 | I73: =IFERROR(D73*$K$32,"") -> 176.4797 | J73: =IF(B73="","",IF(L72="","",IF(L72=0,"",$K$33*$J$17))) -> 111 | K73: =IFERROR(SUM(J73+I73+H73),"") -> 14368.248 | L73: =IFERROR(D73-G73,"") -> 1031277.6 | Q73: =IFERROR(G73*$Q$44,0) -> 23.021624 | R73: =IF($B73<=$J$21,C73-C72,) -> 31 | S73: 365 | AC73: 420 | AD73: =IF(H73="",0,H73) -> 14080.768 | AE73: =IF(C73="",0,C73) -> 46482 | AF73: =IF(AD73="",0,AD73) -> 14080.768 | AG73: =IF(K73="",0,K73) -> 14368.248
A74: =IFERROR(IF(A73-1<1,"",A73-1),"") -> 226 | B74: =IF(IF(AND(B73>0,B73<$J$21),B73+1,0)=0,"",IF(AND(B73>0,B73<$J$21),B73+1,0)) -> 15 | C74: =IFERROR(IF(B74<=$J$21,DATE(YEAR(C73),MONTH(C73)+1,DAY(C73)),""),"") -> 46512 | D74: =IF(B74="","",L73) -> 1031277.6 | E74: =IFERROR(D74*TAXA,"") -> 13303.481 | F74: =IFERROR(D74+E74,"") -> 1044581.1 | G74: =IF($D$9>=B74,0,IFERROR(IF(C74="","",IF(SISTEMA_AMORTIZAÇÃO=PRICE_PRE,H74-E74, IF(SISTEMA_AMORTIZAÇÃO=SAC_PRE,D74/A74, IF(SISTEMA_AMORTIZAÇÃO=SAC_POS,D74/A74,)))),"")) -> 777.28676 | H74: =IF($D$9>=B74,0,IF(D74="","", IF(SISTEMA_AMORTIZAÇÃO=PRICE_PRE,(PMT(TAXA,A74,$D74,)*-1), IF(SISTEMA_AMORTIZAÇÃO=SAC_POS,(D74/A74)+(D74*TAXA))))) -> 14080.768 | I74: =IFERROR(D74*$K$32,"") -> 176.34847 | J74: =IF(B74="","",IF(L73="","",IF(L73=0,"",$K$33*$J$17))) -> 111 | K74: =IFERROR(SUM(J74+I74+H74),"") -> 14368.117 | L74: =IFERROR(D74-G74,"") -> 1030500.3 | Q74: =IFERROR(G74*$Q$44,0) -> 23.318603 | R74: =IF($B74<=$J$21,C74-C73,) -> 30 | S74: 365 | U74: COBRA IOF | AC74: 450 | AD74: =IF(H74="",0,H74) -> 14080.768 | AE74: =IF(C74="",0,C74) -> 46512 | AF74: =IF(AD74="",0,AD74) -> 14080.768 | AG74: =IF(K74="",0,K74) -> 14368.117
A75: =IFERROR(IF(A74-1<1,"",A74-1),"") -> 225 | B75: =IF(IF(AND(B74>0,B74<$J$21),B74+1,0)=0,"",IF(AND(B74>0,B74<$J$21),B74+1,0)) -> 16 | C75: =IFERROR(IF(B75<=$J$21,DATE(YEAR(C74),MONTH(C74)+1,DAY(C74)),""),"") -> 46543 | D75: =IF(B75="","",L74) -> 1030500.3 | E75: =IFERROR(D75*TAXA,"") -> 13293.454 | F75: =IFERROR(D75+E75,"") -> 1043793.8 | G75: =IF($D$9>=B75,0,IFERROR(IF(C75="","",IF(SISTEMA_AMORTIZAÇÃO=PRICE_PRE,H75-E75, IF(SISTEMA_AMORTIZAÇÃO=SAC_PRE,D75/A75, IF(SISTEMA_AMORTIZAÇÃO=SAC_POS,D75/A75,)))),"")) -> 787.31376 | H75: =IF($D$9>=B75,0,IF(D75="","", IF(SISTEMA_AMORTIZAÇÃO=PRICE_PRE,(PMT(TAXA,A75,$D75,)*-1), IF(SISTEMA_AMORTIZAÇÃO=SAC_POS,(D75/A75)+(D75*TAXA))))) -> 14080.768 | I75: =IFERROR(D75*$K$32,"") -> 176.21556 | J75: =IF(B75="","",IF(L74="","",IF(L74=0,"",$K$33*$J$17))) -> 111 | K75: =IFERROR(SUM(J75+I75+H75),"") -> 14367.984 | L75: =IFERROR(D75-G75,"") -> 1029713 | Q75: =IFERROR(G75*$Q$44,0) -> 23.619413 | R75: =IF($B75<=$J$21,C75-C74,) -> 31 | S75: 365 | U75: FCTO-AQUIS | Z75: IOF | AA75: LTV | AC75: 480 | AD75: =IF(H75="",0,H75) -> 14080.768 | AE75: =IF(C75="",0,C75) -> 46543 | AF75: =IF(AD75="",0,AD75) -> 14080.768 | AG75: =IF(K75="",0,K75) -> 14367.984
A76: =IFERROR(IF(A75-1<1,"",A75-1),"") -> 224 | B76: =IF(IF(AND(B75>0,B75<$J$21),B75+1,0)=0,"",IF(AND(B75>0,B75<$J$21),B75+1,0)) -> 17 | C76: =IFERROR(IF(B76<=$J$21,DATE(YEAR(C75),MONTH(C75)+1,DAY(C75)),""),"") -> 46573 | D76: =IF(B76="","",L75) -> 1029713 | E76: =IFERROR(D76*TAXA,"") -> 13283.298 | F76: =IFERROR(D76+E76,"") -> 1042996.3 | G76: =IF($D$9>=B76,0,IFERROR(IF(C76="","",IF(SISTEMA_AMORTIZAÇÃO=PRICE_PRE,H76-E76, IF(SISTEMA_AMORTIZAÇÃO=SAC_PRE,D76/A76, IF(SISTEMA_AMORTIZAÇÃO=SAC_POS,D76/A76,)))),"")) -> 797.4701 | H76: =IF($D$9>=B76,0,IF(D76="","", IF(SISTEMA_AMORTIZAÇÃO=PRICE_PRE,(PMT(TAXA,A76,$D76,)*-1), IF(SISTEMA_AMORTIZAÇÃO=SAC_POS,(D76/A76)+(D76*TAXA))))) -> 14080.768 | I76: =IFERROR(D76*$K$32,"") -> 176.08093 | J76: =IF(B76="","",IF(L75="","",IF(L75=0,"",$K$33*$J$17))) -> 111 | K76: =IFERROR(SUM(J76+I76+H76),"") -> 14367.849 | L76: =IFERROR(D76-G76,"") -> 1028915.5 | Q76: =IFERROR(G76*$Q$44,0) -> 23.924103 | R76: =IF($B76<=$J$21,C76-C75,) -> 30 | S76: 365 | U76: 1 - RESIDENCIAL - CASA | Z76: NÃO | AA76: 0.7 | AC76: 510 | AD76: =IF(H76="",0,H76) -> 14080.768 | AE76: =IF(C76="",0,C76) -> 46573 | AF76: =IF(AD76="",0,AD76) -> 14080.768 | AG76: =IF(K76="",0,K76) -> 14367.849
A77: =IFERROR(IF(A76-1<1,"",A76-1),"") -> 223 | B77: =IF(IF(AND(B76>0,B76<$J$21),B76+1,0)=0,"",IF(AND(B76>0,B76<$J$21),B76+1,0)) -> 18 | C77: =IFERROR(IF(B77<=$J$21,DATE(YEAR(C76),MONTH(C76)+1,DAY(C76)),""),"") -> 46604 | D77: =IF(B77="","",L76) -> 1028915.5 | E77: =IFERROR(D77*TAXA,"") -> 13273.011 | F77: =IFERROR(D77+E77,"") -> 1042188.6 | G77: =IF($D$9>=B77,0,IFERROR(IF(C77="","",IF(SISTEMA_AMORTIZAÇÃO=PRICE_PRE,H77-E77, IF(SISTEMA_AMORTIZAÇÃO=SAC_PRE,D77/A77, IF(SISTEMA_AMORTIZAÇÃO=SAC_POS,D77/A77,)))),"")) -> 807.75747 | H77: =IF($D$9>=B77,0,IF(D77="","", IF(SISTEMA_AMORTIZAÇÃO=PRICE_PRE,(PMT(TAXA,A77,$D77,)*-1), IF(SISTEMA_AMORTIZAÇÃO=SAC_POS,(D77/A77)+(D77*TAXA))))) -> 14080.768 | I77: =IFERROR(D77*$K$32,"") -> 175.94456 | J77: =IF(B77="","",IF(L76="","",IF(L76=0,"",$K$33*$J$17))) -> 111 | K77: =IFERROR(SUM(J77+I77+H77),"") -> 14367.713 | L77: =IFERROR(D77-G77,"") -> 1028107.8 | Q77: =IFERROR(G77*$Q$44,0) -> 24.232724 | R77: =IF($B77<=$J$21,C77-C76,) -> 31 | S77: 365 | U77: 2 - RESIDENCIAL - APARTAMENTO | Z77: NÃO | AA77: 0.7 | AC77: 540 | AD77: =IF(H77="",0,H77) -> 14080.768 | AE77: =IF(C77="",0,C77) -> 46604 | AF77: =IF(AD77="",0,AD77) -> 14080.768 | AG77: =IF(K77="",0,K77) -> 14367.713
A78: =IFERROR(IF(A77-1<1,"",A77-1),"") -> 222 | B78: =IF(IF(AND(B77>0,B77<$J$21),B77+1,0)=0,"",IF(AND(B77>0,B77<$J$21),B77+1,0)) -> 19 | C78: =IFERROR(IF(B78<=$J$21,DATE(YEAR(C77),MONTH(C77)+1,DAY(C77)),""),"") -> 46635 | D78: =IF(B78="","",L77) -> 1028107.8 | E78: =IFERROR(D78*TAXA,"") -> 13262.59 | F78: =IFERROR(D78+E78,"") -> 1041370.4 | G78: =IF($D$9>=B78,0,IFERROR(IF(C78="","",IF(SISTEMA_AMORTIZAÇÃO=PRICE_PRE,H78-E78, IF(SISTEMA_AMORTIZAÇÃO=SAC_PRE,D78/A78, IF(SISTEMA_AMORTIZAÇÃO=SAC_POS,D78/A78,)))),"")) -> 818.17754 | H78: =IF($D$9>=B78,0,IF(D78="","", IF(SISTEMA_AMORTIZAÇÃO=PRICE_PRE,(PMT(TAXA,A78,$D78,)*-1), IF(SISTEMA_AMORTIZAÇÃO=SAC_POS,(D78/A78)+(D78*TAXA))))) -> 14080.768 | I78: =IFERROR(D78*$K$32,"") -> 175.80643 | J78: =IF(B78="","",IF(L77="","",IF(L77=0,"",$K$33*$J$17))) -> 111 | K78: =IFERROR(SUM(J78+I78+H78),"") -> 14367.574 | L78: =IFERROR(D78-G78,"") -> 1027289.6 | Q78: =IFERROR(G78*$Q$44,0) -> 24.545326 | R78: =IF($B78<=$J$21,C78-C77,) -> 31 | S78: 365 | U78: 3 - COMERCIAL - LOJA | Z78: SIM | AA78: 0.5 | AC78: 570 | AD78: =IF(H78="",0,H78) -> 14080.768 | AE78: =IF(C78="",0,C78) -> 46635 | AF78: =IF(AD78="",0,AD78) -> 14080.768 | AG78: =IF(K78="",0,K78) -> 14367.574
A79: =IFERROR(IF(A78-1<1,"",A78-1),"") -> 221 | B79: =IF(IF(AND(B78>0,B78<$J$21),B78+1,0)=0,"",IF(AND(B78>0,B78<$J$21),B78+1,0)) -> 20 | C79: =IFERROR(IF(B79<=$J$21,DATE(YEAR(C78),MONTH(C78)+1,DAY(C78)),""),"") -> 46665 | D79: =IF(B79="","",L78) -> 1027289.6 | E79: =IFERROR(D79*TAXA,"") -> 13252.036 | F79: =IFERROR(D79+E79,"") -> 1040541.6 | G79: =IF($D$9>=B79,0,IFERROR(IF(C79="","",IF(SISTEMA_AMORTIZAÇÃO=PRICE_PRE,H79-E79, IF(SISTEMA_AMORTIZAÇÃO=SAC_PRE,D79/A79, IF(SISTEMA_AMORTIZAÇÃO=SAC_POS,D79/A79,)))),"")) -> 828.73203 | H79: =IF($D$9>=B79,0,IF(D79="","", IF(SISTEMA_AMORTIZAÇÃO=PRICE_PRE,(PMT(TAXA,A79,$D79,)*-1), IF(SISTEMA_AMORTIZAÇÃO=SAC_POS,(D79/A79)+(D79*TAXA))))) -> 14080.768 | I79: =IFERROR(D79*$K$32,"") -> 175.66652 | J79: =IF(B79="","",IF(L78="","",IF(L78=0,"",$K$33*$J$17))) -> 111 | K79: =IFERROR(SUM(J79+I79+H79),"") -> 14367.435 | L79: =IFERROR(D79-G79,"") -> 1026460.9 | Q79: =IFERROR(G79*$Q$44,0) -> 24.861961 | R79: =IF($B79<=$J$21,C79-C78,) -> 30 | S79: 365 | U79: 4 - COMERCIAL - SALA COMERCIAL | Z79: SIM | AA79: 0.5 | AC79: 600 | AD79: =IF(H79="",0,H79) -> 14080.768 | AE79: =IF(C79="",0,C79) -> 46665 | AF79: =IF(AD79="",0,AD79) -> 14080.768 | AG79: =IF(K79="",0,K79) -> 14367.435
A80: =IFERROR(IF(A79-1<1,"",A79-1),"") -> 220 | B80: =IF(IF(AND(B79>0,B79<$J$21),B79+1,0)=0,"",IF(AND(B79>0,B79<$J$21),B79+1,0)) -> 21 | C80: =IFERROR(IF(B80<=$J$21,DATE(YEAR(C79),MONTH(C79)+1,DAY(C79)),""),"") -> 46696 | D80: =IF(B80="","",L79) -> 1026460.9 | E80: =IFERROR(D80*TAXA,"") -> 13241.345 | F80: =IFERROR(D80+E80,"") -> 1039702.2 | G80: =IF($D$9>=B80,0,IFERROR(IF(C80="","",IF(SISTEMA_AMORTIZAÇÃO=PRICE_PRE,H80-E80, IF(SISTEMA_AMORTIZAÇÃO=SAC_PRE,D80/A80, IF(SISTEMA_AMORTIZAÇÃO=SAC_POS,D80/A80,)))),"")) -> 839.42267 | H80: =IF($D$9>=B80,0,IF(D80="","", IF(SISTEMA_AMORTIZAÇÃO=PRICE_PRE,(PMT(TAXA,A80,$D80,)*-1), IF(SISTEMA_AMORTIZAÇÃO=SAC_POS,(D80/A80)+(D80*TAXA))))) -> 14080.768 | I80: =IFERROR(D80*$K$32,"") -> 175.52481 | J80: =IF(B80="","",IF(L79="","",IF(L79=0,"",$K$33*$J$17))) -> 111 | K80: =IFERROR(SUM(J80+I80+H80),"") -> 14367.293 | L80: =IFERROR(D80-G80,"") -> 1025621.5 | Q80: =IFERROR(G80*$Q$44,0) -> 25.18268 | R80: =IF($B80<=$J$21,C80-C79,) -> 31 | S80: 365 | U80: 5 - MISTO - COMERCIAL / RESIDENCIAL | Z80: SIM | AA80: 0.5 | AC80: 630 | AD80: =IF(H80="",0,H80) -> 14080.768 | AE80: =IF(C80="",0,C80) -> 46696 | AF80: =IF(AD80="",0,AD80) -> 14080.768 | AG80: =IF(K80="",0,K80) -> 14367.293
A81: =IFERROR(IF(A80-1<1,"",A80-1),"") -> 219 | B81: =IF(IF(AND(B80>0,B80<$J$21),B80+1,0)=0,"",IF(AND(B80>0,B80<$J$21),B80+1,0)) -> 22 | C81: =IFERROR(IF(B81<=$J$21,DATE(YEAR(C80),MONTH(C80)+1,DAY(C80)),""),"") -> 46726 | D81: =IF(B81="","",L80) -> 1025621.5 | E81: =IFERROR(D81*TAXA,"") -> 13230.517 | F81: =IFERROR(D81+E81,"") -> 1038852 | G81: =IF($D$9>=B81,0,IFERROR(IF(C81="","",IF(SISTEMA_AMORTIZAÇÃO=PRICE_PRE,H81-E81, IF(SISTEMA_AMORTIZAÇÃO=SAC_PRE,D81/A81, IF(SISTEMA_AMORTIZAÇÃO=SAC_POS,D81/A81,)))),"")) -> 850.25122 | H81: =IF($D$9>=B81,0,IF(D81="","", IF(SISTEMA_AMORTIZAÇÃO=PRICE_PRE,(PMT(TAXA,A81,$D81,)*-1), IF(SISTEMA_AMORTIZAÇÃO=SAC_POS,(D81/A81)+(D81*TAXA))))) -> 14080.768 | I81: =IFERROR(D81*$K$32,"") -> 175.38127 | J81: =IF(B81="","",IF(L80="","",IF(L80=0,"",$K$33*$J$17))) -> 111 | K81: =IFERROR(SUM(J81+I81+H81),"") -> 14367.149 | L81: =IFERROR(D81-G81,"") -> 1024771.2 | Q81: =IFERROR(G81*$Q$44,0) -> 25.507537 | R81: =IF($B81<=$J$21,C81-C80,) -> 30 | S81: 365 | U81: 6 - IMOVEL VERANEIO | Z81: NÃO | AA81: 0.7 | AC81: 660 | AD81: =IF(H81="",0,H81) -> 14080.768 | AE81: =IF(C81="",0,C81) -> 46726 | AF81: =IF(AD81="",0,AD81) -> 14080.768 | AG81: =IF(K81="",0,K81) -> 14367.149
A82: =IFERROR(IF(A81-1<1,"",A81-1),"") -> 218 | B82: =IF(IF(AND(B81>0,B81<$J$21),B81+1,0)=0,"",IF(AND(B81>0,B81<$J$21),B81+1,0)) -> 23 | C82: =IFERROR(IF(B82<=$J$21,DATE(YEAR(C81),MONTH(C81)+1,DAY(C81)),""),"") -> 46757 | D82: =IF(B82="","",L81) -> 1024771.2 | E82: =IFERROR(D82*TAXA,"") -> 13219.549 | F82: =IFERROR(D82+E82,"") -> 1037990.8 | G82: =IF($D$9>=B82,0,IFERROR(IF(C82="","",IF(SISTEMA_AMORTIZAÇÃO=PRICE_PRE,H82-E82, IF(SISTEMA_AMORTIZAÇÃO=SAC_PRE,D82/A82, IF(SISTEMA_AMORTIZAÇÃO=SAC_POS,D82/A82,)))),"")) -> 861.21946 | H82: =IF($D$9>=B82,0,IF(D82="","", IF(SISTEMA_AMORTIZAÇÃO=PRICE_PRE,(PMT(TAXA,A82,$D82,)*-1), IF(SISTEMA_AMORTIZAÇÃO=SAC_POS,(D82/A82)+(D82*TAXA))))) -> 14080.768 | I82: =IFERROR(D82*$K$32,"") -> 175.23588 | J82: =IF(B82="","",IF(L81="","",IF(L81=0,"",$K$33*$J$17))) -> 111 | K82: =IFERROR(SUM(J82+I82+H82),"") -> 14367.004 | L82: =IFERROR(D82-G82,"") -> 1023910 | Q82: =IFERROR(G82*$Q$44,0) -> 25.836584 | R82: =IF($B82<=$J$21,C82-C81,) -> 31 | S82: 365 | U82: 7 - TERRENO + CONSTRUÇÃO CONCLUÍDA | Z82: SIM | AA82: 0.5 | AC82: 690 | AD82: =IF(H82="",0,H82) -> 14080.768 | AE82: =IF(C82="",0,C82) -> 46757 | AF82: =IF(AD82="",0,AD82) -> 14080.768 | AG82: =IF(K82="",0,K82) -> 14367.004
A83: =IFERROR(IF(A82-1<1,"",A82-1),"") -> 217 | B83: =IF(IF(AND(B82>0,B82<$J$21),B82+1,0)=0,"",IF(AND(B82>0,B82<$J$21),B82+1,0)) -> 24 | C83: =IFERROR(IF(B83<=$J$21,DATE(YEAR(C82),MONTH(C82)+1,DAY(C82)),""),"") -> 46788 | D83: =IF(B83="","",L82) -> 1023910 | E83: =IFERROR(D83*TAXA,"") -> 13208.439 | F83: =IFERROR(D83+E83,"") -> 1037118.4 | G83: =IF($D$9>=B83,0,IFERROR(IF(C83="","",IF(SISTEMA_AMORTIZAÇÃO=PRICE_PRE,H83-E83, IF(SISTEMA_AMORTIZAÇÃO=SAC_PRE,D83/A83, IF(SISTEMA_AMORTIZAÇÃO=SAC_POS,D83/A83,)))),"")) -> 872.3292 | H83: =IF($D$9>=B83,0,IF(D83="","", IF(SISTEMA_AMORTIZAÇÃO=PRICE_PRE,(PMT(TAXA,A83,$D83,)*-1), IF(SISTEMA_AMORTIZAÇÃO=SAC_POS,(D83/A83)+(D83*TAXA))))) -> 14080.768 | I83: =IFERROR(D83*$K$32,"") -> 175.08861 | J83: =IF(B83="","",IF(L82="","",IF(L82=0,"",$K$33*$J$17))) -> 111 | K83: =IFERROR(SUM(J83+I83+H83),"") -> 14366.857 | L83: =IFERROR(D83-G83,"") -> 1023037.7 | Q83: =IFERROR(G83*$Q$44,0) -> 26.169876 | R83: =IF($B83<=$J$21,C83-C82,) -> 31 | S83: 365 | U83: COBRA IOF | AC83: 720 | AD83: =IF(H83="",0,H83) -> 14080.768 | AE83: =IF(C83="",0,C83) -> 46788 | AF83: =IF(AD83="",0,AD83) -> 14080.768 | AG83: =IF(K83="",0,K83) -> 14366.857
A84: =IFERROR(IF(A83-1<1,"",A83-1),"") -> 216 | B84: =IF(IF(AND(B83>0,B83<$J$21),B83+1,0)=0,"",IF(AND(B83>0,B83<$J$21),B83+1,0)) -> 25 | C84: =IFERROR(IF(B84<=$J$21,DATE(YEAR(C83),MONTH(C83)+1,DAY(C83)),""),"") -> 46817 | D84: =IF(B84="","",L83) -> 1023037.7 | E84: =IFERROR(D84*TAXA,"") -> 13197.186 | F84: =IFERROR(D84+E84,"") -> 1036234.8 | G84: =IF($D$9>=B84,0,IFERROR(IF(C84="","",IF(SISTEMA_AMORTIZAÇÃO=PRICE_PRE,H84-E84, IF(SISTEMA_AMORTIZAÇÃO=SAC_PRE,D84/A84, IF(SISTEMA_AMORTIZAÇÃO=SAC_POS,D84/A84,)))),"")) -> 883.58224 | H84: =IF($D$9>=B84,0,IF(D84="","", IF(SISTEMA_AMORTIZAÇÃO=PRICE_PRE,(PMT(TAXA,A84,$D84,)*-1), IF(SISTEMA_AMORTIZAÇÃO=SAC_POS,(D84/A84)+(D84*TAXA))))) -> 14080.768 | I84: =IFERROR(D84*$K$32,"") -> 174.93944 | J84: =IF(B84="","",IF(L83="","",IF(L83=0,"",$K$33*$J$17))) -> 111 | K84: =IFERROR(SUM(J84+I84+H84),"") -> 14366.707 | L84: =IFERROR(D84-G84,"") -> 1022154.1 | Q84: =IFERROR(G84*$Q$44,0) -> 26.507467 | R84: =IF($B84<=$J$21,C84-C83,) -> 29 | S84: 365 | U84: CGI | Z84: IOF | AA84: LTV | AC84: 750 | AD84: =IF(H84="",0,H84) -> 14080.768 | AE84: =IF(C84="",0,C84) -> 46817 | AF84: =IF(AD84="",0,AD84) -> 14080.768 | AG84: =IF(K84="",0,K84) -> 14366.707
A85: =IFERROR(IF(A84-1<1,"",A84-1),"") -> 215 | B85: =IF(IF(AND(B84>0,B84<$J$21),B84+1,0)=0,"",IF(AND(B84>0,B84<$J$21),B84+1,0)) -> 26 | C85: =IFERROR(IF(B85<=$J$21,DATE(YEAR(C84),MONTH(C84)+1,DAY(C84)),""),"") -> 46848 | D85: =IF(B85="","",L84) -> 1022154.1 | E85: =IFERROR(D85*TAXA,"") -> 13185.788 | F85: =IFERROR(D85+E85,"") -> 1035339.9 | G85: =IF($D$9>=B85,0,IFERROR(IF(C85="","",IF(SISTEMA_AMORTIZAÇÃO=PRICE_PRE,H85-E85, IF(SISTEMA_AMORTIZAÇÃO=SAC_PRE,D85/A85, IF(SISTEMA_AMORTIZAÇÃO=SAC_POS,D85/A85,)))),"")) -> 894.98045 | H85: =IF($D$9>=B85,0,IF(D85="","", IF(SISTEMA_AMORTIZAÇÃO=PRICE_PRE,(PMT(TAXA,A85,$D85,)*-1), IF(SISTEMA_AMORTIZAÇÃO=SAC_POS,(D85/A85)+(D85*TAXA))))) -> 14080.768 | I85: =IFERROR(D85*$K$32,"") -> 174.78835 | J85: =IF(B85="","",IF(L84="","",IF(L84=0,"",$K$33*$J$17))) -> 111 | K85: =IFERROR(SUM(J85+I85+H85),"") -> 14366.556 | L85: =IFERROR(D85-G85,"") -> 1021259.1 | Q85: =IFERROR(G85*$Q$44,0) -> 26.849414 | R85: =IF($B85<=$J$21,C85-C84,) -> 31 | S85: 365 | U85: 1 - RESIDENCIAL - CASA | Z85: SIM | AA85: 0.6 | AC85: 780 | AD85: =IF(H85="",0,H85) -> 14080.768 | AE85: =IF(C85="",0,C85) -> 46848 | AF85: =IF(AD85="",0,AD85) -> 14080.768 | AG85: =IF(K85="",0,K85) -> 14366.556
A86: =IFERROR(IF(A85-1<1,"",A85-1),"") -> 214 | B86: =IF(IF(AND(B85>0,B85<$J$21),B85+1,0)=0,"",IF(AND(B85>0,B85<$J$21),B85+1,0)) -> 27 | C86: =IFERROR(IF(B86<=$J$21,DATE(YEAR(C85),MONTH(C85)+1,DAY(C85)),""),"") -> 46878 | D86: =IF(B86="","",L85) -> 1021259.1 | E86: =IFERROR(D86*TAXA,"") -> 13174.242 | F86: =IFERROR(D86+E86,"") -> 1034433.3 | G86: =IF($D$9>=B86,0,IFERROR(IF(C86="","",IF(SISTEMA_AMORTIZAÇÃO=PRICE_PRE,H86-E86, IF(SISTEMA_AMORTIZAÇÃO=SAC_PRE,D86/A86, IF(SISTEMA_AMORTIZAÇÃO=SAC_POS,D86/A86,)))),"")) -> 906.5257 | H86: =IF($D$9>=B86,0,IF(D86="","", IF(SISTEMA_AMORTIZAÇÃO=PRICE_PRE,(PMT(TAXA,A86,$D86,)*-1), IF(SISTEMA_AMORTIZAÇÃO=SAC_POS,(D86/A86)+(D86*TAXA))))) -> 14080.768 | I86: =IFERROR(D86*$K$32,"") -> 174.63531 | J86: =IF(B86="","",IF(L85="","",IF(L85=0,"",$K$33*$J$17))) -> 111 | K86: =IFERROR(SUM(J86+I86+H86),"") -> 14366.403 | L86: =IFERROR(D86-G86,"") -> 1020352.6 | Q86: =IFERROR(G86*$Q$44,0) -> 27.195771 | R86: =IF($B86<=$J$21,C86-C85,) -> 30 | S86: 365 | U86: 2 - RESIDENCIAL - APARTAMENTO | Z86: SIM | AA86: 0.6 | AC86: 810 | AD86: =IF(H86="",0,H86) -> 14080.768 | AE86: =IF(C86="",0,C86) -> 46878 | AF86: =IF(AD86="",0,AD86) -> 14080.768 | AG86: =IF(K86="",0,K86) -> 14366.403
A87: =IFERROR(IF(A86-1<1,"",A86-1),"") -> 213 | B87: =IF(IF(AND(B86>0,B86<$J$21),B86+1,0)=0,"",IF(AND(B86>0,B86<$J$21),B86+1,0)) -> 28 | C87: =IFERROR(IF(B87<=$J$21,DATE(YEAR(C86),MONTH(C86)+1,DAY(C86)),""),"") -> 46909 | D87: =IF(B87="","",L86) -> 1020352.6 | E87: =IFERROR(D87*TAXA,"") -> 13162.548 | F87: =IFERROR(D87+E87,"") -> 1033515.1 | G87: =IF($D$9>=B87,0,IFERROR(IF(C87="","",IF(SISTEMA_AMORTIZAÇÃO=PRICE_PRE,H87-E87, IF(SISTEMA_AMORTIZAÇÃO=SAC_PRE,D87/A87, IF(SISTEMA_AMORTIZAÇÃO=SAC_POS,D87/A87,)))),"")) -> 918.21988 | H87: =IF($D$9>=B87,0,IF(D87="","", IF(SISTEMA_AMORTIZAÇÃO=PRICE_PRE,(PMT(TAXA,A87,$D87,)*-1), IF(SISTEMA_AMORTIZAÇÃO=SAC_POS,(D87/A87)+(D87*TAXA))))) -> 14080.768 | I87: =IFERROR(D87*$K$32,"") -> 174.48029 | J87: =IF(B87="","",IF(L86="","",IF(L86=0,"",$K$33*$J$17))) -> 111 | K87: =IFERROR(SUM(J87+I87+H87),"") -> 14366.248 | L87: =IFERROR(D87-G87,"") -> 1019434.4 | Q87: =IFERROR(G87*$Q$44,0) -> 27.546596 | R87: =IF($B87<=$J$21,C87-C86,) -> 31 | S87: 365 | U87: 3 - COMERCIAL - LOJA | Z87: SIM | AA87: 0.6 | AC87: 840 | AD87: =IF(H87="",0,H87) -> 14080.768 | AE87: =IF(C87="",0,C87) -> 46909 | AF87: =IF(AD87="",0,AD87) -> 14080.768 | AG87: =IF(K87="",0,K87) -> 14366.248
A88: =IFERROR(IF(A87-1<1,"",A87-1),"") -> 212 | B88: =IF(IF(AND(B87>0,B87<$J$21),B87+1,0)=0,"",IF(AND(B87>0,B87<$J$21),B87+1,0)) -> 29 | C88: =IFERROR(IF(B88<=$J$21,DATE(YEAR(C87),MONTH(C87)+1,DAY(C87)),""),"") -> 46939 | D88: =IF(B88="","",L87) -> 1019434.4 | E88: =IFERROR(D88*TAXA,"") -> 13150.703 | F88: =IFERROR(D88+E88,"") -> 1032585.1 | G88: =IF($D$9>=B88,0,IFERROR(IF(C88="","",IF(SISTEMA_AMORTIZAÇÃO=PRICE_PRE,H88-E88, IF(SISTEMA_AMORTIZAÇÃO=SAC_PRE,D88/A88, IF(SISTEMA_AMORTIZAÇÃO=SAC_POS,D88/A88,)))),"")) -> 930.06492 | H88: =IF($D$9>=B88,0,IF(D88="","", IF(SISTEMA_AMORTIZAÇÃO=PRICE_PRE,(PMT(TAXA,A88,$D88,)*-1), IF(SISTEMA_AMORTIZAÇÃO=SAC_POS,(D88/A88)+(D88*TAXA))))) -> 14080.768 | I88: =IFERROR(D88*$K$32,"") -> 174.32327 | J88: =IF(B88="","",IF(L87="","",IF(L87=0,"",$K$33*$J$17))) -> 111 | K88: =IFERROR(SUM(J88+I88+H88),"") -> 14366.091 | L88: =IFERROR(D88-G88,"") -> 1018504.3 | Q88: =IFERROR(G88*$Q$44,0) -> 27.901948 | R88: =IF($B88<=$J$21,C88-C87,) -> 30 | S88: 365 | U88: 4 - COMERCIAL - SALA COMERCIAL | Z88: SIM | AA88: 0.6 | AC88: 870 | AD88: =IF(H88="",0,H88) -> 14080.768 | AE88: =IF(C88="",0,C88) -> 46939 | AF88: =IF(AD88="",0,AD88) -> 14080.768 | AG88: =IF(K88="",0,K88) -> 14366.091
A89: =IFERROR(IF(A88-1<1,"",A88-1),"") -> 211 | B89: =IF(IF(AND(B88>0,B88<$J$21),B88+1,0)=0,"",IF(AND(B88>0,B88<$J$21),B88+1,0)) -> 30 | C89: =IFERROR(IF(B89<=$J$21,DATE(YEAR(C88),MONTH(C88)+1,DAY(C88)),""),"") -> 46970 | D89: =IF(B89="","",L88) -> 1018504.3 | E89: =IFERROR(D89*TAXA,"") -> 13138.705 | F89: =IFERROR(D89+E89,"") -> 1031643 | G89: =IF($D$9>=B89,0,IFERROR(IF(C89="","",IF(SISTEMA_AMORTIZAÇÃO=PRICE_PRE,H89-E89, IF(SISTEMA_AMORTIZAÇÃO=SAC_PRE,D89/A89, IF(SISTEMA_AMORTIZAÇÃO=SAC_POS,D89/A89,)))),"")) -> 942.06276 | H89: =IF($D$9>=B89,0,IF(D89="","", IF(SISTEMA_AMORTIZAÇÃO=PRICE_PRE,(PMT(TAXA,A89,$D89,)*-1), IF(SISTEMA_AMORTIZAÇÃO=SAC_POS,(D89/A89)+(D89*TAXA))))) -> 14080.768 | I89: =IFERROR(D89*$K$32,"") -> 174.16423 | J89: =IF(B89="","",IF(L88="","",IF(L88=0,"",$K$33*$J$17))) -> 111 | K89: =IFERROR(SUM(J89+I89+H89),"") -> 14365.932 | L89: =IFERROR(D89-G89,"") -> 1017562.2 | Q89: =IFERROR(G89*$Q$44,0) -> 28.261883 | R89: =IF($B89<=$J$21,C89-C88,) -> 31 | S89: 365 | U89: 5 - MISTO - COMERCIAL / RESIDENCIAL | Z89: SIM | AA89: 0.6 | AC89: 900 | AD89: =IF(H89="",0,H89) -> 14080.768 | AE89: =IF(C89="",0,C89) -> 46970 | AF89: =IF(AD89="",0,AD89) -> 14080.768 | AG89: =IF(K89="",0,K89) -> 14365.932
A90: =IFERROR(IF(A89-1<1,"",A89-1),"") -> 210 | B90: =IF(IF(AND(B89>0,B89<$J$21),B89+1,0)=0,"",IF(AND(B89>0,B89<$J$21),B89+1,0)) -> 31 | C90: =IFERROR(IF(B90<=$J$21,DATE(YEAR(C89),MONTH(C89)+1,DAY(C89)),""),"") -> 47001 | D90: =IF(B90="","",L89) -> 1017562.2 | E90: =IFERROR(D90*TAXA,"") -> 13126.553 | F90: =IFERROR(D90+E90,"") -> 1030688.8 | G90: =IF($D$9>=B90,0,IFERROR(IF(C90="","",IF(SISTEMA_AMORTIZAÇÃO=PRICE_PRE,H90-E90, IF(SISTEMA_AMORTIZAÇÃO=SAC_PRE,D90/A90, IF(SISTEMA_AMORTIZAÇÃO=SAC_POS,D90/A90,)))),"")) -> 954.21537 | H90: =IF($D$9>=B90,0,IF(D90="","", IF(SISTEMA_AMORTIZAÇÃO=PRICE_PRE,(PMT(TAXA,A90,$D90,)*-1), IF(SISTEMA_AMORTIZAÇÃO=SAC_POS,(D90/A90)+(D90*TAXA))))) -> 14080.768 | I90: =IFERROR(D90*$K$32,"") -> 174.00314 | J90: =IF(B90="","",IF(L89="","",IF(L89=0,"",$K$33*$J$17))) -> 111 | K90: =IFERROR(SUM(J90+I90+H90),"") -> 14365.771 | L90: =IFERROR(D90-G90,"") -> 1016608 | Q90: =IFERROR(G90*$Q$44,0) -> 28.626461 | R90: =IF($B90<=$J$21,C90-C89,) -> 31 | S90: 365 | U90: 6 - IMOVEL VERANEIO | Z90: SIM | AA90: 0.6 | AC90: 930 | AD90: =IF(H90="",0,H90) -> 14080.768 | AE90: =IF(C90="",0,C90) -> 47001 | AF90: =IF(AD90="",0,AD90) -> 14080.768 | AG90: =IF(K90="",0,K90) -> 14365.771
A91: =IFERROR(IF(A90-1<1,"",A90-1),"") -> 209 | B91: =IF(IF(AND(B90>0,B90<$J$21),B90+1,0)=0,"",IF(AND(B90>0,B90<$J$21),B90+1,0)) -> 32 | C91: =IFERROR(IF(B91<=$J$21,DATE(YEAR(C90),MONTH(C90)+1,DAY(C90)),""),"") -> 47031 | D91: =IF(B91="","",L90) -> 1016608 | E91: =IFERROR(D91*TAXA,"") -> 13114.243 | F91: =IFERROR(D91+E91,"") -> 1029722.3 | G91: =IF($D$9>=B91,0,IFERROR(IF(C91="","",IF(SISTEMA_AMORTIZAÇÃO=PRICE_PRE,H91-E91, IF(SISTEMA_AMORTIZAÇÃO=SAC_PRE,D91/A91, IF(SISTEMA_AMORTIZAÇÃO=SAC_POS,D91/A91,)))),"")) -> 966.52474 | H91: =IF($D$9>=B91,0,IF(D91="","", IF(SISTEMA_AMORTIZAÇÃO=PRICE_PRE,(PMT(TAXA,A91,$D91,)*-1), IF(SISTEMA_AMORTIZAÇÃO=SAC_POS,(D91/A91)+(D91*TAXA))))) -> 14080.768 | I91: =IFERROR(D91*$K$32,"") -> 173.83997 | J91: =IF(B91="","",IF(L90="","",IF(L90=0,"",$K$33*$J$17))) -> 111 | K91: =IFERROR(SUM(J91+I91+H91),"") -> 14365.608 | L91: =IFERROR(D91-G91,"") -> 1015641.5 | Q91: =IFERROR(G91*$Q$44,0) -> 28.995742 | R91: =IF($B91<=$J$21,C91-C90,) -> 30 | S91: 365 | U91: 7 - TERRENO + CONSTRUÇÃO CONCLUÍDA | Z91: SIM | AA91: 0.6 | AC91: 960 | AD91: =IF(H91="",0,H91) -> 14080.768 | AE91: =IF(C91="",0,C91) -> 47031 | AF91: =IF(AD91="",0,AD91) -> 14080.768 | AG91: =IF(K91="",0,K91) -> 14365.608
A92: =IFERROR(IF(A91-1<1,"",A91-1),"") -> 208 | B92: =IF(IF(AND(B91>0,B91<$J$21),B91+1,0)=0,"",IF(AND(B91>0,B91<$J$21),B91+1,0)) -> 33 | C92: =IFERROR(IF(B92<=$J$21,DATE(YEAR(C91),MONTH(C91)+1,DAY(C91)),""),"") -> 47062 | D92: =IF(B92="","",L91) -> 1015641.5 | E92: =IFERROR(D92*TAXA,"") -> 13101.775 | F92: =IFERROR(D92+E92,"") -> 1028743.3 | G92: =IF($D$9>=B92,0,IFERROR(IF(C92="","",IF(SISTEMA_AMORTIZAÇÃO=PRICE_PRE,H92-E92, IF(SISTEMA_AMORTIZAÇÃO=SAC_PRE,D92/A92, IF(SISTEMA_AMORTIZAÇÃO=SAC_POS,D92/A92,)))),"")) -> 978.99291 | H92: =IF($D$9>=B92,0,IF(D92="","", IF(SISTEMA_AMORTIZAÇÃO=PRICE_PRE,(PMT(TAXA,A92,$D92,)*-1), IF(SISTEMA_AMORTIZAÇÃO=SAC_POS,(D92/A92)+(D92*TAXA))))) -> 14080.768 | I92: =IFERROR(D92*$K$32,"") -> 173.67469 | J92: =IF(B92="","",IF(L91="","",IF(L91=0,"",$K$33*$J$17))) -> 111 | K92: =IFERROR(SUM(J92+I92+H92),"") -> 14365.443 | L92: =IFERROR(D92-G92,"") -> 1014662.5 | Q92: =IFERROR(G92*$Q$44,0) -> 29.369787 | R92: =IF($B92<=$J$21,C92-C91,) -> 31 | S92: 365 | AC92: 990 | AD92: =IF(H92="",0,H92) -> 14080.768 | AE92: =IF(C92="",0,C92) -> 47062 | AF92: =IF(AD92="",0,AD92) -> 14080.768 | AG92: =IF(K92="",0,K92) -> 14365.443
A93: =IFERROR(IF(A92-1<1,"",A92-1),"") -> 207 | B93: =IF(IF(AND(B92>0,B92<$J$21),B92+1,0)=0,"",IF(AND(B92>0,B92<$J$21),B92+1,0)) -> 34 | C93: =IFERROR(IF(B93<=$J$21,DATE(YEAR(C92),MONTH(C92)+1,DAY(C92)),""),"") -> 47092 | D93: =IF(B93="","",L92) -> 1014662.5 | E93: =IFERROR(D93*TAXA,"") -> 13089.146 | F93: =IFERROR(D93+E93,"") -> 1027751.6 | G93: =IF($D$9>=B93,0,IFERROR(IF(C93="","",IF(SISTEMA_AMORTIZAÇÃO=PRICE_PRE,H93-E93, IF(SISTEMA_AMORTIZAÇÃO=SAC_PRE,D93/A93, IF(SISTEMA_AMORTIZAÇÃO=SAC_POS,D93/A93,)))),"")) -> 991.62192 | H93: =IF($D$9>=B93,0,IF(D93="","", IF(SISTEMA_AMORTIZAÇÃO=PRICE_PRE,(PMT(TAXA,A93,$D93,)*-1), IF(SISTEMA_AMORTIZAÇÃO=SAC_POS,(D93/A93)+(D93*TAXA))))) -> 14080.768 | I93: =IFERROR(D93*$K$32,"") -> 173.50729 | J93: =IF(B93="","",IF(L92="","",IF(L92=0,"",$K$33*$J$17))) -> 111 | K93: =IFERROR(SUM(J93+I93+H93),"") -> 14365.275 | L93: =IFERROR(D93-G93,"") -> 1013670.9 | Q93: =IFERROR(G93*$Q$44,0) -> 29.748658 | R93: =IF($B93<=$J$21,C93-C92,) -> 30 | S93: 365 | AC93: 1020 | AD93: =IF(H93="",0,H93) -> 14080.768 | AE93: =IF(C93="",0,C93) -> 47092 | AF93: =IF(AD93="",0,AD93) -> 14080.768 | AG93: =IF(K93="",0,K93) -> 14365.275
A94: =IFERROR(IF(A93-1<1,"",A93-1),"") -> 206 | B94: =IF(IF(AND(B93>0,B93<$J$21),B93+1,0)=0,"",IF(AND(B93>0,B93<$J$21),B93+1,0)) -> 35 | C94: =IFERROR(IF(B94<=$J$21,DATE(YEAR(C93),MONTH(C93)+1,DAY(C93)),""),"") -> 47123 | D94: =IF(B94="","",L93) -> 1013670.9 | E94: =IFERROR(D94*TAXA,"") -> 13076.354 | F94: =IFERROR(D94+E94,"") -> 1026747.2 | G94: =IF($D$9>=B94,0,IFERROR(IF(C94="","",IF(SISTEMA_AMORTIZAÇÃO=PRICE_PRE,H94-E94, IF(SISTEMA_AMORTIZAÇÃO=SAC_PRE,D94/A94, IF(SISTEMA_AMORTIZAÇÃO=SAC_POS,D94/A94,)))),"")) -> 1004.4138 | H94: =IF($D$9>=B94,0,IF(D94="","", IF(SISTEMA_AMORTIZAÇÃO=PRICE_PRE,(PMT(TAXA,A94,$D94,)*-1), IF(SISTEMA_AMORTIZAÇÃO=SAC_POS,(D94/A94)+(D94*TAXA))))) -> 14080.768 | I94: =IFERROR(D94*$K$32,"") -> 173.33772 | J94: =IF(B94="","",IF(L93="","",IF(L93=0,"",$K$33*$J$17))) -> 111 | K94: =IFERROR(SUM(J94+I94+H94),"") -> 14365.106 | L94: =IFERROR(D94-G94,"") -> 1012666.5 | Q94: =IFERROR(G94*$Q$44,0) -> 30.132415 | R94: =IF($B94<=$J$21,C94-C93,) -> 31 | S94: 365 | AC94: 1050 | AD94: =IF(H94="",0,H94) -> 14080.768 | AE94: =IF(C94="",0,C94) -> 47123 | AF94: =IF(AD94="",0,AD94) -> 14080.768 | AG94: =IF(K94="",0,K94) -> 14365.106
A95: =IFERROR(IF(A94-1<1,"",A94-1),"") -> 205 | B95: =IF(IF(AND(B94>0,B94<$J$21),B94+1,0)=0,"",IF(AND(B94>0,B94<$J$21),B94+1,0)) -> 36 | C95: =IFERROR(IF(B95<=$J$21,DATE(YEAR(C94),MONTH(C94)+1,DAY(C94)),""),"") -> 47154 | D95: =IF(B95="","",L94) -> 1012666.5 | E95: =IFERROR(D95*TAXA,"") -> 13063.397 | F95: =IFERROR(D95+E95,"") -> 1025729.9 | G95: =IF($D$9>=B95,0,IFERROR(IF(C95="","",IF(SISTEMA_AMORTIZAÇÃO=PRICE_PRE,H95-E95, IF(SISTEMA_AMORTIZAÇÃO=SAC_PRE,D95/A95, IF(SISTEMA_AMORTIZAÇÃO=SAC_POS,D95/A95,)))),"")) -> 1017.3708 | H95: =IF($D$9>=B95,0,IF(D95="","", IF(SISTEMA_AMORTIZAÇÃO=PRICE_PRE,(PMT(TAXA,A95,$D95,)*-1), IF(SISTEMA_AMORTIZAÇÃO=SAC_POS,(D95/A95)+(D95*TAXA))))) -> 14080.768 | I95: =IFERROR(D95*$K$32,"") -> 173.16596 | J95: =IF(B95="","",IF(L94="","",IF(L94=0,"",$K$33*$J$17))) -> 111 | K95: =IFERROR(SUM(J95+I95+H95),"") -> 14364.934 | L95: =IFERROR(D95-G95,"") -> 1011649.1 | Q95: =IFERROR(G95*$Q$44,0) -> 30.521124 | R95: =IF($B95<=$J$21,C95-C94,) -> 31 | S95: 365 | AC95: 1080 | AD95: =IF(H95="",0,H95) -> 14080.768 | AE95: =IF(C95="",0,C95) -> 47154 | AF95: =IF(AD95="",0,AD95) -> 14080.768 | AG95: =IF(K95="",0,K95) -> 14364.934
A96: =IFERROR(IF(A95-1<1,"",A95-1),"") -> 204 | B96: =IF(IF(AND(B95>0,B95<$J$21),B95+1,0)=0,"",IF(AND(B95>0,B95<$J$21),B95+1,0)) -> 37 | C96: =IFERROR(IF(B96<=$J$21,DATE(YEAR(C95),MONTH(C95)+1,DAY(C95)),""),"") -> 47182 | D96: =IF(B96="","",L95) -> 1011649.1 | E96: =IFERROR(D96*TAXA,"") -> 13050.273 | F96: =IFERROR(D96+E96,"") -> 1024699.4 | G96: =IF($D$9>=B96,0,IFERROR(IF(C96="","",IF(SISTEMA_AMORTIZAÇÃO=PRICE_PRE,H96-E96, IF(SISTEMA_AMORTIZAÇÃO=SAC_PRE,D96/A96, IF(SISTEMA_AMORTIZAÇÃO=SAC_POS,D96/A96,)))),"")) -> 1030.4949 | H96: =IF($D$9>=B96,0,IF(D96="","", IF(SISTEMA_AMORTIZAÇÃO=PRICE_PRE,(PMT(TAXA,A96,$D96,)*-1), IF(SISTEMA_AMORTIZAÇÃO=SAC_POS,(D96/A96)+(D96*TAXA))))) -> 14080.768 | I96: =IFERROR(D96*$K$32,"") -> 172.99199 | J96: =IF(B96="","",IF(L95="","",IF(L95=0,"",$K$33*$J$17))) -> 111 | K96: =IFERROR(SUM(J96+I96+H96),"") -> 14364.76 | L96: =IFERROR(D96-G96,"") -> 1010618.6 | Q96: =IFERROR(G96*$Q$44,0) -> 30.914846 | R96: =IF($B96<=$J$21,C96-C95,) -> 28 | S96: 365 | AC96: 1110 | AD96: =IF(H96="",0,H96) -> 14080.768 | AE96: =IF(C96="",0,C96) -> 47182 | AF96: =IF(AD96="",0,AD96) -> 14080.768 | AG96: =IF(K96="",0,K96) -> 14364.76
A97: =IFERROR(IF(A96-1<1,"",A96-1),"") -> 203 | B97: =IF(IF(AND(B96>0,B96<$J$21),B96+1,0)=0,"",IF(AND(B96>0,B96<$J$21),B96+1,0)) -> 38 | C97: =IFERROR(IF(B97<=$J$21,DATE(YEAR(C96),MONTH(C96)+1,DAY(C96)),""),"") -> 47213 | D97: =IF(B97="","",L96) -> 1010618.6 | E97: =IFERROR(D97*TAXA,"") -> 13036.98 | F97: =IFERROR(D97+E97,"") -> 1023655.6 | G97: =IF($D$9>=B97,0,IFERROR(IF(C97="","",IF(SISTEMA_AMORTIZAÇÃO=PRICE_PRE,H97-E97, IF(SISTEMA_AMORTIZAÇÃO=SAC_PRE,D97/A97, IF(SISTEMA_AMORTIZAÇÃO=SAC_POS,D97/A97,)))),"")) -> 1043.7883 | H97: =IF($D$9>=B97,0,IF(D97="","", IF(SISTEMA_AMORTIZAÇÃO=PRICE_PRE,(PMT(TAXA,A97,$D97,)*-1), IF(SISTEMA_AMORTIZAÇÃO=SAC_POS,(D97/A97)+(D97*TAXA))))) -> 14080.768 | I97: =IFERROR(D97*$K$32,"") -> 172.81578 | J97: =IF(B97="","",IF(L96="","",IF(L96=0,"",$K$33*$J$17))) -> 111 | K97: =IFERROR(SUM(J97+I97+H97),"") -> 14364.584 | L97: =IFERROR(D97-G97,"") -> 1009574.8 | Q97: =IFERROR(G97*$Q$44,0) -> 31.313648 | R97: =IF($B97<=$J$21,C97-C96,) -> 31 | S97: 365 | AC97: 1140 | AD97: =IF(H97="",0,H97) -> 14080.768 | AE97: =IF(C97="",0,C97) -> 47213 | AF97: =IF(AD97="",0,AD97) -> 14080.768 | AG97: =IF(K97="",0,K97) -> 14364.584
A98: =IFERROR(IF(A97-1<1,"",A97-1),"") -> 202 | B98: =IF(IF(AND(B97>0,B97<$J$21),B97+1,0)=0,"",IF(AND(B97>0,B97<$J$21),B97+1,0)) -> 39 | C98: =IFERROR(IF(B98<=$J$21,DATE(YEAR(C97),MONTH(C97)+1,DAY(C97)),""),"") -> 47243 | D98: =IF(B98="","",L97) -> 1009574.8 | E98: =IFERROR(D98*TAXA,"") -> 13023.515 | F98: =IFERROR(D98+E98,"") -> 1022598.3 | G98: =IF($D$9>=B98,0,IFERROR(IF(C98="","",IF(SISTEMA_AMORTIZAÇÃO=PRICE_PRE,H98-E98, IF(SISTEMA_AMORTIZAÇÃO=SAC_PRE,D98/A98, IF(SISTEMA_AMORTIZAÇÃO=SAC_POS,D98/A98,)))),"")) -> 1057.2531 | H98: =IF($D$9>=B98,0,IF(D98="","", IF(SISTEMA_AMORTIZAÇÃO=PRICE_PRE,(PMT(TAXA,A98,$D98,)*-1), IF(SISTEMA_AMORTIZAÇÃO=SAC_POS,(D98/A98)+(D98*TAXA))))) -> 14080.768 | I98: =IFERROR(D98*$K$32,"") -> 172.63729 | J98: =IF(B98="","",IF(L97="","",IF(L97=0,"",$K$33*$J$17))) -> 111 | K98: =IFERROR(SUM(J98+I98+H98),"") -> 14364.405 | L98: =IFERROR(D98-G98,"") -> 1008517.5 | Q98: =IFERROR(G98*$Q$44,0) -> 31.717594 | R98: =IF($B98<=$J$21,C98-C97,) -> 30 | S98: 365 | AC98: 1170 | AD98: =IF(H98="",0,H98) -> 14080.768 | AE98: =IF(C98="",0,C98) -> 47243 | AF98: =IF(AD98="",0,AD98) -> 14080.768 | AG98: =IF(K98="",0,K98) -> 14364.405
A99: =IFERROR(IF(A98-1<1,"",A98-1),"") -> 201 | B99: =IF(IF(AND(B98>0,B98<$J$21),B98+1,0)=0,"",IF(AND(B98>0,B98<$J$21),B98+1,0)) -> 40 | C99: =IFERROR(IF(B99<=$J$21,DATE(YEAR(C98),MONTH(C98)+1,DAY(C98)),""),"") -> 47274 | D99: =IF(B99="","",L98) -> 1008517.5 | E99: =IFERROR(D99*TAXA,"") -> 13009.876 | F99: =IFERROR(D99+E99,"") -> 1021527.4 | G99: =IF($D$9>=B99,0,IFERROR(IF(C99="","",IF(SISTEMA_AMORTIZAÇÃO=PRICE_PRE,H99-E99, IF(SISTEMA_AMORTIZAÇÃO=SAC_PRE,D99/A99, IF(SISTEMA_AMORTIZAÇÃO=SAC_POS,D99/A99,)))),"")) -> 1070.8917 | H99: =IF($D$9>=B99,0,IF(D99="","", IF(SISTEMA_AMORTIZAÇÃO=PRICE_PRE,(PMT(TAXA,A99,$D99,)*-1), IF(SISTEMA_AMORTIZAÇÃO=SAC_POS,(D99/A99)+(D99*TAXA))))) -> 14080.768 | I99: =IFERROR(D99*$K$32,"") -> 172.4565 | J99: =IF(B99="","",IF(L98="","",IF(L98=0,"",$K$33*$J$17))) -> 111 | K99: =IFERROR(SUM(J99+I99+H99),"") -> 14364.225 | L99: =IFERROR(D99-G99,"") -> 1007446.7 | Q99: =IFERROR(G99*$Q$44,0) -> 32.126751 | R99: =IF($B99<=$J$21,C99-C98,) -> 31 | S99: 365 | AC99: 1200 | AD99: =IF(H99="",0,H99) -> 14080.768 | AE99: =IF(C99="",0,C99) -> 47274 | AF99: =IF(AD99="",0,AD99) -> 14080.768 | AG99: =IF(K99="",0,K99) -> 14364.225
A100: =IFERROR(IF(A99-1<1,"",A99-1),"") -> 200 | B100: =IF(IF(AND(B99>0,B99<$J$21),B99+1,0)=0,"",IF(AND(B99>0,B99<$J$21),B99+1,0)) -> 41 | C100: =IFERROR(IF(B100<=$J$21,DATE(YEAR(C99),MONTH(C99)+1,DAY(C99)),""),"") -> 47304 | D100: =IF(B100="","",L99) -> 1007446.7 | E100: =IFERROR(D100*TAXA,"") -> 12996.062 | F100: =IFERROR(D100+E100,"") -> 1020442.7 | G100: =IF($D$9>=B100,0,IFERROR(IF(C100="","",IF(SISTEMA_AMORTIZAÇÃO=PRICE_PRE,H100-E100, IF(SISTEMA_AMORTIZAÇÃO=SAC_PRE,D100/A100, IF(SISTEMA_AMORTIZAÇÃO=SAC_POS,D100/A100,)))),"")) -> 1084.7062 | H100: =IF($D$9>=B100,0,IF(D100="","", IF(SISTEMA_AMORTIZAÇÃO=PRICE_PRE,(PMT(TAXA,A100,$D100,)*-1), IF(SISTEMA_AMORTIZAÇÃO=SAC_POS,(D100/A100)+(D100*TAXA))))) -> 14080.768 | I100: =IFERROR(D100*$K$32,"") -> 172.27338 | J100: =IF(B100="","",IF(L99="","",IF(L99=0,"",$K$33*$J$17))) -> 111 | K100: =IFERROR(SUM(J100+I100+H100),"") -> 14364.041 | L100: =IFERROR(D100-G100,"") -> 1006361.9 | Q100: =IFERROR(G100*$Q$44,0) -> 32.541186 | R100: =IF($B100<=$J$21,C100-C99,) -> 30 | S100: 365 | AC100: 1230 | AD100: =IF(H100="",0,H100) -> 14080.768 | AE100: =IF(C100="",0,C100) -> 47304 | AF100: =IF(AD100="",0,AD100) -> 14080.768 | AG100: =IF(K100="",0,K100) -> 14364.041
A101: =IFERROR(IF(A100-1<1,"",A100-1),"") -> 199 | B101: =IF(IF(AND(B100>0,B100<$J$21),B100+1,0)=0,"",IF(AND(B100>0,B100<$J$21),B100+1,0)) -> 42 | C101: =IFERROR(IF(B101<=$J$21,DATE(YEAR(C100),MONTH(C100)+1,DAY(C100)),""),"") -> 47335 | D101: =IF(B101="","",L100) -> 1006361.9 | E101: =IFERROR(D101*TAXA,"") -> 12982.069 | F101: =IFERROR(D101+E101,"") -> 1019344 | G101: =IF($D$9>=B101,0,IFERROR(IF(C101="","",IF(SISTEMA_AMORTIZAÇÃO=PRICE_PRE,H101-E101, IF(SISTEMA_AMORTIZAÇÃO=SAC_PRE,D101/A101, IF(SISTEMA_AMORTIZAÇÃO=SAC_POS,D101/A101,)))),"")) -> 1098.6989 | H101: =IF($D$9>=B101,0,IF(D101="","", IF(SISTEMA_AMORTIZAÇÃO=PRICE_PRE,(PMT(TAXA,A101,$D101,)*-1), IF(SISTEMA_AMORTIZAÇÃO=SAC_POS,(D101/A101)+(D101*TAXA))))) -> 14080.768 | I101: =IFERROR(D101*$K$32,"") -> 172.08789 | J101: =IF(B101="","",IF(L100="","",IF(L100=0,"",$K$33*$J$17))) -> 111 | K101: =IFERROR(SUM(J101+I101+H101),"") -> 14363.856 | L101: =IFERROR(D101-G101,"") -> 1005263.2 | Q101: =IFERROR(G101*$Q$44,0) -> 32.960967 | R101: =IF($B101<=$J$21,C101-C100,) -> 31 | S101: 365 | AC101: 1260 | AD101: =IF(H101="",0,H101) -> 14080.768 | AE101: =IF(C101="",0,C101) -> 47335 | AF101: =IF(AD101="",0,AD101) -> 14080.768 | AG101: =IF(K101="",0,K101) -> 14363.856
A102: =IFERROR(IF(A101-1<1,"",A101-1),"") -> 198 | B102: =IF(IF(AND(B101>0,B101<$J$21),B101+1,0)=0,"",IF(AND(B101>0,B101<$J$21),B101+1,0)) -> 43 | C102: =IFERROR(IF(B102<=$J$21,DATE(YEAR(C101),MONTH(C101)+1,DAY(C101)),""),"") -> 47366 | D102: =IF(B102="","",L101) -> 1005263.2 | E102: =IFERROR(D102*TAXA,"") -> 12967.896 | F102: =IFERROR(D102+E102,"") -> 1018231.1 | G102: =IF($D$9>=B102,0,IFERROR(IF(C102="","",IF(SISTEMA_AMORTIZAÇÃO=PRICE_PRE,H102-E102, IF(SISTEMA_AMORTIZAÇÃO=SAC_PRE,D102/A102, IF(SISTEMA_AMORTIZAÇÃO=SAC_POS,D102/A102,)))),"")) -> 1112.8721 | H102: =IF($D$9>=B102,0,IF(D102="","", IF(SISTEMA_AMORTIZAÇÃO=PRICE_PRE,(PMT(TAXA,A102,$D102,)*-1), IF(SISTEMA_AMORTIZAÇÃO=SAC_POS,(D102/A102)+(D102*TAXA))))) -> 14080.768 | I102: =IFERROR(D102*$K$32,"") -> 171.90002 | J102: =IF(B102="","",IF(L101="","",IF(L101=0,"",$K$33*$J$17))) -> 111 | K102: =IFERROR(SUM(J102+I102+H102),"") -> 14363.668 | L102: =IFERROR(D102-G102,"") -> 1004150.4 | Q102: =IFERROR(G102*$Q$44,0) -> 33.386163 | R102: =IF($B102<=$J$21,C102-C101,) -> 31 | S102: 365 | AC102: 1290 | AD102: =IF(H102="",0,H102) -> 14080.768 | AE102: =IF(C102="",0,C102) -> 47366 | AF102: =IF(AD102="",0,AD102) -> 14080.768 | AG102: =IF(K102="",0,K102) -> 14363.668
A103: =IFERROR(IF(A102-1<1,"",A102-1),"") -> 197 | B103: =IF(IF(AND(B102>0,B102<$J$21),B102+1,0)=0,"",IF(AND(B102>0,B102<$J$21),B102+1,0)) -> 44 | C103: =IFERROR(IF(B103<=$J$21,DATE(YEAR(C102),MONTH(C102)+1,DAY(C102)),""),"") -> 47396 | D103: =IF(B103="","",L102) -> 1004150.4 | E103: =IFERROR(D103*TAXA,"") -> 12953.54 | F103: =IFERROR(D103+E103,"") -> 1017103.9 | G103: =IF($D$9>=B103,0,IFERROR(IF(C103="","",IF(SISTEMA_AMORTIZAÇÃO=PRICE_PRE,H103-E103, IF(SISTEMA_AMORTIZAÇÃO=SAC_PRE,D103/A103, IF(SISTEMA_AMORTIZAÇÃO=SAC_POS,D103/A103,)))),"")) -> 1127.2282 | H103: =IF($D$9>=B103,0,IF(D103="","", IF(SISTEMA_AMORTIZAÇÃO=PRICE_PRE,(PMT(TAXA,A103,$D103,)*-1), IF(SISTEMA_AMORTIZAÇÃO=SAC_POS,(D103/A103)+(D103*TAXA))))) -> 14080.768 | I103: =IFERROR(D103*$K$32,"") -> 171.70971 | J103: =IF(B103="","",IF(L102="","",IF(L102=0,"",$K$33*$J$17))) -> 111 | K103: =IFERROR(SUM(J103+I103+H103),"") -> 14363.478 | L103: =IFERROR(D103-G103,"") -> 1003023.1 | Q103: =IFERROR(G103*$Q$44,0) -> 33.816845 | R103: =IF($B103<=$J$21,C103-C102,) -> 30 | S103: 365 | AC103: 1320 | AD103: =IF(H103="",0,H103) -> 14080.768 | AE103: =IF(C103="",0,C103) -> 47396 | AF103: =IF(AD103="",0,AD103) -> 14080.768 | AG103: =IF(K103="",0,K103) -> 14363.478
A104: =IFERROR(IF(A103-1<1,"",A103-1),"") -> 196 | B104: =IF(IF(AND(B103>0,B103<$J$21),B103+1,0)=0,"",IF(AND(B103>0,B103<$J$21),B103+1,0)) -> 45 | C104: =IFERROR(IF(B104<=$J$21,DATE(YEAR(C103),MONTH(C103)+1,DAY(C103)),""),"") -> 47427 | D104: =IF(B104="","",L103) -> 1003023.1 | E104: =IFERROR(D104*TAXA,"") -> 12938.999 | F104: =IFERROR(D104+E104,"") -> 1015962.1 | G104: =IF($D$9>=B104,0,IFERROR(IF(C104="","",IF(SISTEMA_AMORTIZAÇÃO=PRICE_PRE,H104-E104, IF(SISTEMA_AMORTIZAÇÃO=SAC_PRE,D104/A104, IF(SISTEMA_AMORTIZAÇÃO=SAC_POS,D104/A104,)))),"")) -> 1141.7694 | H104: =IF($D$9>=B104,0,IF(D104="","", IF(SISTEMA_AMORTIZAÇÃO=PRICE_PRE,(PMT(TAXA,A104,$D104,)*-1), IF(SISTEMA_AMORTIZAÇÃO=SAC_POS,(D104/A104)+(D104*TAXA))))) -> 14080.768 | I104: =IFERROR(D104*$K$32,"") -> 171.51696 | J104: =IF(B104="","",IF(L103="","",IF(L103=0,"",$K$33*$J$17))) -> 111 | K104: =IFERROR(SUM(J104+I104+H104),"") -> 14363.285 | L104: =IFERROR(D104-G104,"") -> 1001881.4 | Q104: =IFERROR(G104*$Q$44,0) -> 34.253082 | R104: =IF($B104<=$J$21,C104-C103,) -> 31 | S104: 365 | U104: Faixa Idade | V104: Alicota | W104: MIP | AC104: 1350 | AD104: =IF(H104="",0,H104) -> 14080.768 | AE104: =IF(C104="",0,C104) -> 47427 | AF104: =IF(AD104="",0,AD104) -> 14080.768 | AG104: =IF(K104="",0,K104) -> 14363.285
A105: =IFERROR(IF(A104-1<1,"",A104-1),"") -> 195 | B105: =IF(IF(AND(B104>0,B104<$J$21),B104+1,0)=0,"",IF(AND(B104>0,B104<$J$21),B104+1,0)) -> 46 | C105: =IFERROR(IF(B105<=$J$21,DATE(YEAR(C104),MONTH(C104)+1,DAY(C104)),""),"") -> 47457 | D105: =IF(B105="","",L104) -> 1001881.4 | E105: =IFERROR(D105*TAXA,"") -> 12924.27 | F105: =IFERROR(D105+E105,"") -> 1014805.6 | G105: =IF($D$9>=B105,0,IFERROR(IF(C105="","",IF(SISTEMA_AMORTIZAÇÃO=PRICE_PRE,H105-E105, IF(SISTEMA_AMORTIZAÇÃO=SAC_PRE,D105/A105, IF(SISTEMA_AMORTIZAÇÃO=SAC_POS,D105/A105,)))),"")) -> 1156.4982 | H105: =IF($D$9>=B105,0,IF(D105="","", IF(SISTEMA_AMORTIZAÇÃO=PRICE_PRE,(PMT(TAXA,A105,$D105,)*-1), IF(SISTEMA_AMORTIZAÇÃO=SAC_POS,(D105/A105)+(D105*TAXA))))) -> 14080.768 | I105: =IFERROR(D105*$K$32,"") -> 171.32172 | J105: =IF(B105="","",IF(L104="","",IF(L104=0,"",$K$33*$J$17))) -> 111 | K105: =IFERROR(SUM(J105+I105+H105),"") -> 14363.09 | L105: =IFERROR(D105-G105,"") -> 1000724.9 | Q105: =IFERROR(G105*$Q$44,0) -> 34.694947 | R105: =IF($B105<=$J$21,C105-C104,) -> 30 | S105: 365 | U105: 18 | V105: 0.0001284 | W105: Alicota_1 | AC105: 1380 | AD105: =IF(H105="",0,H105) -> 14080.768 | AE105: =IF(C105="",0,C105) -> 47457 | AF105: =IF(AD105="",0,AD105) -> 14080.768 | AG105: =IF(K105="",0,K105) -> 14363.09
A106: =IFERROR(IF(A105-1<1,"",A105-1),"") -> 194 | B106: =IF(IF(AND(B105>0,B105<$J$21),B105+1,0)=0,"",IF(AND(B105>0,B105<$J$21),B105+1,0)) -> 47 | C106: =IFERROR(IF(B106<=$J$21,DATE(YEAR(C105),MONTH(C105)+1,DAY(C105)),""),"") -> 47488 | D106: =IF(B106="","",L105) -> 1000724.9 | E106: =IFERROR(D106*TAXA,"") -> 12909.351 | F106: =IFERROR(D106+E106,"") -> 1013634.2 | G106: =IF($D$9>=B106,0,IFERROR(IF(C106="","",IF(SISTEMA_AMORTIZAÇÃO=PRICE_PRE,H106-E106, IF(SISTEMA_AMORTIZAÇÃO=SAC_PRE,D106/A106, IF(SISTEMA_AMORTIZAÇÃO=SAC_POS,D106/A106,)))),"")) -> 1171.4171 | H106: =IF($D$9>=B106,0,IF(D106="","", IF(SISTEMA_AMORTIZAÇÃO=PRICE_PRE,(PMT(TAXA,A106,$D106,)*-1), IF(SISTEMA_AMORTIZAÇÃO=SAC_POS,(D106/A106)+(D106*TAXA))))) -> 14080.768 | I106: =IFERROR(D106*$K$32,"") -> 171.12395 | J106: =IF(B106="","",IF(L105="","",IF(L105=0,"",$K$33*$J$17))) -> 111 | K106: =IFERROR(SUM(J106+I106+H106),"") -> 14362.892 | L106: =IFERROR(D106-G106,"") -> 999553.46 | Q106: =IFERROR(G106*$Q$44,0) -> 35.142512 | R106: =IF($B106<=$J$21,C106-C105,) -> 31 | S106: 365 | U106: 19 | V106: 0.0001284 | W106: Alicota_1 | AC106: 1410 | AD106: =IF(H106="",0,H106) -> 14080.768 | AE106: =IF(C106="",0,C106) -> 47488 | AF106: =IF(AD106="",0,AD106) -> 14080.768 | AG106: =IF(K106="",0,K106) -> 14362.892
A107: =IFERROR(IF(A106-1<1,"",A106-1),"") -> 193 | B107: =IF(IF(AND(B106>0,B106<$J$21),B106+1,0)=0,"",IF(AND(B106>0,B106<$J$21),B106+1,0)) -> 48 | C107: =IFERROR(IF(B107<=$J$21,DATE(YEAR(C106),MONTH(C106)+1,DAY(C106)),""),"") -> 47519 | D107: =IF(B107="","",L106) -> 999553.46 | E107: =IFERROR(D107*TAXA,"") -> 12894.24 | F107: =IFERROR(D107+E107,"") -> 1012447.7 | G107: =IF($D$9>=B107,0,IFERROR(IF(C107="","",IF(SISTEMA_AMORTIZAÇÃO=PRICE_PRE,H107-E107, IF(SISTEMA_AMORTIZAÇÃO=SAC_PRE,D107/A107, IF(SISTEMA_AMORTIZAÇÃO=SAC_POS,D107/A107,)))),"")) -> 1186.5283 | H107: =IF($D$9>=B107,0,IF(D107="","", IF(SISTEMA_AMORTIZAÇÃO=PRICE_PRE,(PMT(TAXA,A107,$D107,)*-1), IF(SISTEMA_AMORTIZAÇÃO=SAC_POS,(D107/A107)+(D107*TAXA))))) -> 14080.768 | I107: =IFERROR(D107*$K$32,"") -> 170.92364 | J107: =IF(B107="","",IF(L106="","",IF(L106=0,"",$K$33*$J$17))) -> 111 | K107: =IFERROR(SUM(J107+I107+H107),"") -> 14362.692 | L107: =IFERROR(D107-G107,"") -> 998366.94 | Q107: =IFERROR(G107*$Q$44,0) -> 35.59585 | R107: =IF($B107<=$J$21,C107-C106,) -> 31 | S107: 365 | U107: 20 | V107: 0.0001284 | W107: Alicota_1 | AC107: 1440 | AD107: =IF(H107="",0,H107) -> 14080.768 | AE107: =IF(C107="",0,C107) -> 47519 | AF107: =IF(AD107="",0,AD107) -> 14080.768 | AG107: =IF(K107="",0,K107) -> 14362.692
A108: =IFERROR(IF(A107-1<1,"",A107-1),"") -> 192 | B108: =IF(IF(AND(B107>0,B107<$J$21),B107+1,0)=0,"",IF(AND(B107>0,B107<$J$21),B107+1,0)) -> 49 | C108: =IFERROR(IF(B108<=$J$21,DATE(YEAR(C107),MONTH(C107)+1,DAY(C107)),""),"") -> 47547 | D108: =IF(B108="","",L107) -> 998366.94 | E108: =IFERROR(D108*TAXA,"") -> 12878.933 | F108: =IFERROR(D108+E108,"") -> 1011245.9 | G108: =IF($D$9>=B108,0,IFERROR(IF(C108="","",IF(SISTEMA_AMORTIZAÇÃO=PRICE_PRE,H108-E108, IF(SISTEMA_AMORTIZAÇÃO=SAC_PRE,D108/A108, IF(SISTEMA_AMORTIZAÇÃO=SAC_POS,D108/A108,)))),"")) -> 1201.8346 | H108: =IF($D$9>=B108,0,IF(D108="","", IF(SISTEMA_AMORTIZAÇÃO=PRICE_PRE,(PMT(TAXA,A108,$D108,)*-1), IF(SISTEMA_AMORTIZAÇÃO=SAC_POS,(D108/A108)+(D108*TAXA))))) -> 14080.768 | I108: =IFERROR(D108*$K$32,"") -> 170.72075 | J108: =IF(B108="","",IF(L107="","",IF(L107=0,"",$K$33*$J$17))) -> 111 | K108: =IFERROR(SUM(J108+I108+H108),"") -> 14362.489 | L108: =IFERROR(D108-G108,"") -> 997165.1 | Q108: =IFERROR(G108*$Q$44,0) -> 36.055037 | R108: =IF($B108<=$J$21,C108-C107,) -> 28 | S108: 365 | U108: 21 | V108: 0.0001284 | W108: Alicota_1 | AC108: 1470 | AD108: =IF(H108="",0,H108) -> 14080.768 | AE108: =IF(C108="",0,C108) -> 47547 | AF108: =IF(AD108="",0,AD108) -> 14080.768 | AG108: =IF(K108="",0,K108) -> 14362.489
A109: =IFERROR(IF(A108-1<1,"",A108-1),"") -> 191 | B109: =IF(IF(AND(B108>0,B108<$J$21),B108+1,0)=0,"",IF(AND(B108>0,B108<$J$21),B108+1,0)) -> 50 | C109: =IFERROR(IF(B109<=$J$21,DATE(YEAR(C108),MONTH(C108)+1,DAY(C108)),""),"") -> 47578 | D109: =IF(B109="","",L108) -> 997165.1 | E109: =IFERROR(D109*TAXA,"") -> 12863.43 | F109: =IFERROR(D109+E109,"") -> 1010028.5 | G109: =IF($D$9>=B109,0,IFERROR(IF(C109="","",IF(SISTEMA_AMORTIZAÇÃO=PRICE_PRE,H109-E109, IF(SISTEMA_AMORTIZAÇÃO=SAC_PRE,D109/A109, IF(SISTEMA_AMORTIZAÇÃO=SAC_POS,D109/A109,)))),"")) -> 1217.3382 | H109: =IF($D$9>=B109,0,IF(D109="","", IF(SISTEMA_AMORTIZAÇÃO=PRICE_PRE,(PMT(TAXA,A109,$D109,)*-1), IF(SISTEMA_AMORTIZAÇÃO=SAC_POS,(D109/A109)+(D109*TAXA))))) -> 14080.768 | I109: =IFERROR(D109*$K$32,"") -> 170.51523 | J109: =IF(B109="","",IF(L108="","",IF(L108=0,"",$K$33*$J$17))) -> 111 | K109: =IFERROR(SUM(J109+I109+H109),"") -> 14362.283 | L109: =IFERROR(D109-G109,"") -> 995947.76 | Q109: =IFERROR(G109*$Q$44,0) -> 36.520147 | R109: =IF($B109<=$J$21,C109-C108,) -> 31 | S109: 365 | U109: 22 | V109: 0.0001284 | W109: Alicota_1 | AC109: 1500 | AD109: =IF(H109="",0,H109) -> 14080.768 | AE109: =IF(C109="",0,C109) -> 47578 | AF109: =IF(AD109="",0,AD109) -> 14080.768 | AG109: =IF(K109="",0,K109) -> 14362.283
A110: =IFERROR(IF(A109-1<1,"",A109-1),"") -> 190 | B110: =IF(IF(AND(B109>0,B109<$J$21),B109+1,0)=0,"",IF(AND(B109>0,B109<$J$21),B109+1,0)) -> 51 | C110: =IFERROR(IF(B110<=$J$21,DATE(YEAR(C109),MONTH(C109)+1,DAY(C109)),""),"") -> 47608 | D110: =IF(B110="","",L109) -> 995947.76 | E110: =IFERROR(D110*TAXA,"") -> 12847.726 | F110: =IFERROR(D110+E110,"") -> 1008795.5 | G110: =IF($D$9>=B110,0,IFERROR(IF(C110="","",IF(SISTEMA_AMORTIZAÇÃO=PRICE_PRE,H110-E110, IF(SISTEMA_AMORTIZAÇÃO=SAC_PRE,D110/A110, IF(SISTEMA_AMORTIZAÇÃO=SAC_POS,D110/A110,)))),"")) -> 1233.0419 | H110: =IF($D$9>=B110,0,IF(D110="","", IF(SISTEMA_AMORTIZAÇÃO=PRICE_PRE,(PMT(TAXA,A110,$D110,)*-1), IF(SISTEMA_AMORTIZAÇÃO=SAC_POS,(D110/A110)+(D110*TAXA))))) -> 14080.768 | I110: =IFERROR(D110*$K$32,"") -> 170.30707 | J110: =IF(B110="","",IF(L109="","",IF(L109=0,"",$K$33*$J$17))) -> 111 | K110: =IFERROR(SUM(J110+I110+H110),"") -> 14362.075 | L110: =IFERROR(D110-G110,"") -> 994714.72 | Q110: =IFERROR(G110*$Q$44,0) -> 36.991256 | R110: =IF($B110<=$J$21,C110-C109,) -> 30 | S110: 365 | U110: 23 | V110: 0.0001284 | W110: Alicota_1 | AC110: 1530 | AD110: =IF(H110="",0,H110) -> 14080.768 | AE110: =IF(C110="",0,C110) -> 47608 | AF110: =IF(AD110="",0,AD110) -> 14080.768 | AG110: =IF(K110="",0,K110) -> 14362.075
A111: =IFERROR(IF(A110-1<1,"",A110-1),"") -> 189 | B111: =IF(IF(AND(B110>0,B110<$J$21),B110+1,0)=0,"",IF(AND(B110>0,B110<$J$21),B110+1,0)) -> 52 | C111: =IFERROR(IF(B111<=$J$21,DATE(YEAR(C110),MONTH(C110)+1,DAY(C110)),""),"") -> 47639 | D111: =IF(B111="","",L110) -> 994714.72 | E111: =IFERROR(D111*TAXA,"") -> 12831.82 | F111: =IFERROR(D111+E111,"") -> 1007546.5 | G111: =IF($D$9>=B111,0,IFERROR(IF(C111="","",IF(SISTEMA_AMORTIZAÇÃO=PRICE_PRE,H111-E111, IF(SISTEMA_AMORTIZAÇÃO=SAC_PRE,D111/A111, IF(SISTEMA_AMORTIZAÇÃO=SAC_POS,D111/A111,)))),"")) -> 1248.9481 | H111: =IF($D$9>=B111,0,IF(D111="","", IF(SISTEMA_AMORTIZAÇÃO=PRICE_PRE,(PMT(TAXA,A111,$D111,)*-1), IF(SISTEMA_AMORTIZAÇÃO=SAC_POS,(D111/A111)+(D111*TAXA))))) -> 14080.768 | I111: =IFERROR(D111*$K$32,"") -> 170.09622 | J111: =IF(B111="","",IF(L110="","",IF(L110=0,"",$K$33*$J$17))) -> 111 | K111: =IFERROR(SUM(J111+I111+H111),"") -> 14361.864 | L111: =IFERROR(D111-G111,"") -> 993465.77 | Q111: =IFERROR(G111*$Q$44,0) -> 37.468444 | R111: =IF($B111<=$J$21,C111-C110,) -> 31 | S111: 365 | U111: 24 | V111: 0.0001284 | W111: Alicota_1 | AC111: 1560 | AD111: =IF(H111="",0,H111) -> 14080.768 | AE111: =IF(C111="",0,C111) -> 47639 | AF111: =IF(AD111="",0,AD111) -> 14080.768 | AG111: =IF(K111="",0,K111) -> 14361.864
A112: =IFERROR(IF(A111-1<1,"",A111-1),"") -> 188 | B112: =IF(IF(AND(B111>0,B111<$J$21),B111+1,0)=0,"",IF(AND(B111>0,B111<$J$21),B111+1,0)) -> 53 | C112: =IFERROR(IF(B112<=$J$21,DATE(YEAR(C111),MONTH(C111)+1,DAY(C111)),""),"") -> 47669 | D112: =IF(B112="","",L111) -> 993465.77 | E112: =IFERROR(D112*TAXA,"") -> 12815.708 | F112: =IFERROR(D112+E112,"") -> 1006281.5 | G112: =IF($D$9>=B112,0,IFERROR(IF(C112="","",IF(SISTEMA_AMORTIZAÇÃO=PRICE_PRE,H112-E112, IF(SISTEMA_AMORTIZAÇÃO=SAC_PRE,D112/A112, IF(SISTEMA_AMORTIZAÇÃO=SAC_POS,D112/A112,)))),"")) -> 1265.0596 | H112: =IF($D$9>=B112,0,IF(D112="","", IF(SISTEMA_AMORTIZAÇÃO=PRICE_PRE,(PMT(TAXA,A112,$D112,)*-1), IF(SISTEMA_AMORTIZAÇÃO=SAC_POS,(D112/A112)+(D112*TAXA))))) -> 14080.768 | I112: =IFERROR(D112*$K$32,"") -> 169.88265 | J112: =IF(B112="","",IF(L111="","",IF(L111=0,"",$K$33*$J$17))) -> 111 | K112: =IFERROR(SUM(J112+I112+H112),"") -> 14361.651 | L112: =IFERROR(D112-G112,"") -> 992200.71 | Q112: =IFERROR(G112*$Q$44,0) -> 37.951787 | R112: =IF($B112<=$J$21,C112-C111,) -> 30 | S112: 365 | U112: 25 | V112: 0.0001284 | W112: Alicota_1 | AC112: 1590 | AD112: =IF(H112="",0,H112) -> 14080.768 | AE112: =IF(C112="",0,C112) -> 47669 | AF112: =IF(AD112="",0,AD112) -> 14080.768 | AG112: =IF(K112="",0,K112) -> 14361.651
A113: =IFERROR(IF(A112-1<1,"",A112-1),"") -> 187 | B113: =IF(IF(AND(B112>0,B112<$J$21),B112+1,0)=0,"",IF(AND(B112>0,B112<$J$21),B112+1,0)) -> 54 | C113: =IFERROR(IF(B113<=$J$21,DATE(YEAR(C112),MONTH(C112)+1,DAY(C112)),""),"") -> 47700 | D113: =IF(B113="","",L112) -> 992200.71 | E113: =IFERROR(D113*TAXA,"") -> 12799.389 | F113: =IFERROR(D113+E113,"") -> 1005000.1 | G113: =IF($D$9>=B113,0,IFERROR(IF(C113="","",IF(SISTEMA_AMORTIZAÇÃO=PRICE_PRE,H113-E113, IF(SISTEMA_AMORTIZAÇÃO=SAC_PRE,D113/A113, IF(SISTEMA_AMORTIZAÇÃO=SAC_POS,D113/A113,)))),"")) -> 1281.3788 | H113: =IF($D$9>=B113,0,IF(D113="","", IF(SISTEMA_AMORTIZAÇÃO=PRICE_PRE,(PMT(TAXA,A113,$D113,)*-1), IF(SISTEMA_AMORTIZAÇÃO=SAC_POS,(D113/A113)+(D113*TAXA))))) -> 14080.768 | I113: =IFERROR(D113*$K$32,"") -> 169.66632 | J113: =IF(B113="","",IF(L112="","",IF(L112=0,"",$K$33*$J$17))) -> 111 | K113: =IFERROR(SUM(J113+I113+H113),"") -> 14361.434 | L113: =IFERROR(D113-G113,"") -> 990919.34 | Q113: =IFERROR(G113*$Q$44,0) -> 38.441365 | R113: =IF($B113<=$J$21,C113-C112,) -> 31 | S113: 365 | U113: 26 | V113: 0.0001284 | W113: Alicota_2 | AC113: 1620 | AD113: =IF(H113="",0,H113) -> 14080.768 | AE113: =IF(C113="",0,C113) -> 47700 | AF113: =IF(AD113="",0,AD113) -> 14080.768 | AG113: =IF(K113="",0,K113) -> 14361.434
A114: =IFERROR(IF(A113-1<1,"",A113-1),"") -> 186 | B114: =IF(IF(AND(B113>0,B113<$J$21),B113+1,0)=0,"",IF(AND(B113>0,B113<$J$21),B113+1,0)) -> 55 | C114: =IFERROR(IF(B114<=$J$21,DATE(YEAR(C113),MONTH(C113)+1,DAY(C113)),""),"") -> 47731 | D114: =IF(B114="","",L113) -> 990919.34 | E114: =IFERROR(D114*TAXA,"") -> 12782.859 | F114: =IFERROR(D114+E114,"") -> 1003702.2 | G114: =IF($D$9>=B114,0,IFERROR(IF(C114="","",IF(SISTEMA_AMORTIZAÇÃO=PRICE_PRE,H114-E114, IF(SISTEMA_AMORTIZAÇÃO=SAC_PRE,D114/A114, IF(SISTEMA_AMORTIZAÇÃO=SAC_POS,D114/A114,)))),"")) -> 1297.9086 | H114: =IF($D$9>=B114,0,IF(D114="","", IF(SISTEMA_AMORTIZAÇÃO=PRICE_PRE,(PMT(TAXA,A114,$D114,)*-1), IF(SISTEMA_AMORTIZAÇÃO=SAC_POS,(D114/A114)+(D114*TAXA))))) -> 14080.768 | I114: =IFERROR(D114*$K$32,"") -> 169.44721 | J114: =IF(B114="","",IF(L113="","",IF(L113=0,"",$K$33*$J$17))) -> 111 | K114: =IFERROR(SUM(J114+I114+H114),"") -> 14361.215 | L114: =IFERROR(D114-G114,"") -> 989621.43 | Q114: =IFERROR(G114*$Q$44,0) -> 38.937258 | R114: =IF($B114<=$J$21,C114-C113,) -> 31 | S114: 365 | U114: 27 | V114: 0.0001284 | W114: Alicota_2 | AC114: 1650 | AD114: =IF(H114="",0,H114) -> 14080.768 | AE114: =IF(C114="",0,C114) -> 47731 | AF114: =IF(AD114="",0,AD114) -> 14080.768 | AG114: =IF(K114="",0,K114) -> 14361.215
A115: =IFERROR(IF(A114-1<1,"",A114-1),"") -> 185 | B115: =IF(IF(AND(B114>0,B114<$J$21),B114+1,0)=0,"",IF(AND(B114>0,B114<$J$21),B114+1,0)) -> 56 | C115: =IFERROR(IF(B115<=$J$21,DATE(YEAR(C114),MONTH(C114)+1,DAY(C114)),""),"") -> 47761 | D115: =IF(B115="","",L114) -> 989621.43 | E115: =IFERROR(D115*TAXA,"") -> 12766.116 | F115: =IFERROR(D115+E115,"") -> 1002387.5 | G115: =IF($D$9>=B115,0,IFERROR(IF(C115="","",IF(SISTEMA_AMORTIZAÇÃO=PRICE_PRE,H115-E115, IF(SISTEMA_AMORTIZAÇÃO=SAC_PRE,D115/A115, IF(SISTEMA_AMORTIZAÇÃO=SAC_POS,D115/A115,)))),"")) -> 1314.6516 | H115: =IF($D$9>=B115,0,IF(D115="","", IF(SISTEMA_AMORTIZAÇÃO=PRICE_PRE,(PMT(TAXA,A115,$D115,)*-1), IF(SISTEMA_AMORTIZAÇÃO=SAC_POS,(D115/A115)+(D115*TAXA))))) -> 14080.768 | I115: =IFERROR(D115*$K$32,"") -> 169.22526 | J115: =IF(B115="","",IF(L114="","",IF(L114=0,"",$K$33*$J$17))) -> 111 | K115: =IFERROR(SUM(J115+I115+H115),"") -> 14360.993 | L115: =IFERROR(D115-G115,"") -> 988306.78 | Q115: =IFERROR(G115*$Q$44,0) -> 39.439549 | R115: =IF($B115<=$J$21,C115-C114,) -> 30 | S115: 365 | U115: 28 | V115: 0.0001284 | W115: Alicota_2 | AC115: 1680 | AD115: =IF(H115="",0,H115) -> 14080.768 | AE115: =IF(C115="",0,C115) -> 47761 | AF115: =IF(AD115="",0,AD115) -> 14080.768 | AG115: =IF(K115="",0,K115) -> 14360.993
A116: =IFERROR(IF(A115-1<1,"",A115-1),"") -> 184 | B116: =IF(IF(AND(B115>0,B115<$J$21),B115+1,0)=0,"",IF(AND(B115>0,B115<$J$21),B115+1,0)) -> 57 | C116: =IFERROR(IF(B116<=$J$21,DATE(YEAR(C115),MONTH(C115)+1,DAY(C115)),""),"") -> 47792 | D116: =IF(B116="","",L115) -> 988306.78 | E116: =IFERROR(D116*TAXA,"") -> 12749.157 | F116: =IFERROR(D116+E116,"") -> 1001055.9 | G116: =IF($D$9>=B116,0,IFERROR(IF(C116="","",IF(SISTEMA_AMORTIZAÇÃO=PRICE_PRE,H116-E116, IF(SISTEMA_AMORTIZAÇÃO=SAC_PRE,D116/A116, IF(SISTEMA_AMORTIZAÇÃO=SAC_POS,D116/A116,)))),"")) -> 1331.6106 | H116: =IF($D$9>=B116,0,IF(D116="","", IF(SISTEMA_AMORTIZAÇÃO=PRICE_PRE,(PMT(TAXA,A116,$D116,)*-1), IF(SISTEMA_AMORTIZAÇÃO=SAC_POS,(D116/A116)+(D116*TAXA))))) -> 14080.768 | I116: =IFERROR(D116*$K$32,"") -> 169.00046 | J116: =IF(B116="","",IF(L115="","",IF(L115=0,"",$K$33*$J$17))) -> 111 | K116: =IFERROR(SUM(J116+I116+H116),"") -> 14360.768 | L116: =IFERROR(D116-G116,"") -> 986975.16 | Q116: =IFERROR(G116*$Q$44,0) -> 39.948319 | R116: =IF($B116<=$J$21,C116-C115,) -> 31 | S116: 365 | U116: 29 | V116: 0.0001284 | W116: Alicota_2 | AC116: 1710 | AD116: =IF(H116="",0,H116) -> 14080.768 | AE116: =IF(C116="",0,C116) -> 47792 | AF116: =IF(AD116="",0,AD116) -> 14080.768 | AG116: =IF(K116="",0,K116) -> 14360.768
... A167: =IFERROR(IF(A166-1<1,"",A166-1),"") -> 133 | B167: =IF(IF(AND(B166>0,B166<$J$21),B166+1,0)=0,"",IF(AND(B166>0,B166<$J$21),B166+1,0)) -> 108 | C167: =IFERROR(IF(B167<=$J$21,DATE(YEAR(C166),MONTH(C166)+1,DAY(C166)),""),"") -> 49345 | D167: =IF(B167="","",L166) -> 893067.98 | E167: =IFERROR(D167*TAXA,"") -> 11520.577 | F167: =IFERROR(D167+E167,"") -> 904588.56 | G167: =IF($D$9>=B167,0,IFERROR(IF(C167="","",IF(SISTEMA_AMORTIZAÇÃO=PRICE_PRE,H167-E167, IF(SISTEMA_AMORTIZAÇÃO=SAC_PRE,D167/A167, IF(SISTEMA_AMORTIZAÇÃO=SAC_POS,D167/A167,)))),"")) -> 2560.1911 | H167: =IF($D$9>=B167,0,IF(D167="","", IF(SISTEMA_AMORTIZAÇÃO=PRICE_PRE,(PMT(TAXA,A167,$D167,)*-1), IF(SISTEMA_AMORTIZAÇÃO=SAC_POS,(D167/A167)+(D167*TAXA))))) -> 14080.768 | I167: =IFERROR(D167*$K$32,"") -> 152.71462 | J167: =IF(B167="","",IF(L166="","",IF(L166=0,"",$K$33*$J$17))) -> 111 | K167: =IFERROR(SUM(J167+I167+H167),"") -> 14344.483 | L167: =IFERROR(D167-G167,"") -> 890507.79 | Q167: =IFERROR(G167*$Q$44,0) -> 76.805733 | R167: =IF($B167<=$J$21,C167-C166,) -> 31 | S167: 365 | U167: 80 | V167: 0.011433 | W167: Alicota_9 | AC167: 3240 | AD167: =IF(H167="",0,H167) -> 14080.768 | AE167: =IF(C167="",0,C167) -> 49345 | AF167: =IF(AD167="",0,AD167) -> 14080.768 | AG167: =IF(K167="",0,K167) -> 14344.483
A168: =IFERROR(IF(A167-1<1,"",A167-1),"") -> 132 | B168: =IF(IF(AND(B167>0,B167<$J$21),B167+1,0)=0,"",IF(AND(B167>0,B167<$J$21),B167+1,0)) -> 109 | C168: =IFERROR(IF(B168<=$J$21,DATE(YEAR(C167),MONTH(C167)+1,DAY(C167)),""),"") -> 49373 | D168: =IF(B168="","",L167) -> 890507.79 | E168: =IFERROR(D168*TAXA,"") -> 11487.55 | F168: =IFERROR(D168+E168,"") -> 901995.34 | G168: =IF($D$9>=B168,0,IFERROR(IF(C168="","",IF(SISTEMA_AMORTIZAÇÃO=PRICE_PRE,H168-E168, IF(SISTEMA_AMORTIZAÇÃO=SAC_PRE,D168/A168, IF(SISTEMA_AMORTIZAÇÃO=SAC_POS,D168/A168,)))),"")) -> 2593.2176 | H168: =IF($D$9>=B168,0,IF(D168="","", IF(SISTEMA_AMORTIZAÇÃO=PRICE_PRE,(PMT(TAXA,A168,$D168,)*-1), IF(SISTEMA_AMORTIZAÇÃO=SAC_POS,(D168/A168)+(D168*TAXA))))) -> 14080.768 | I168: =IFERROR(D168*$K$32,"") -> 152.27683 | J168: =IF(B168="","",IF(L167="","",IF(L167=0,"",$K$33*$J$17))) -> 111 | K168: =IFERROR(SUM(J168+I168+H168),"") -> 14344.045 | L168: =IFERROR(D168-G168,"") -> 887914.57 | Q168: =IFERROR(G168*$Q$44,0) -> 77.796527 | R168: =IF($B168<=$J$21,C168-C167,) -> 28 | S168: 365 | AC168: 3270 | AD168: =IF(H168="",0,H168) -> 14080.768 | AE168: =IF(C168="",0,C168) -> 49373 | AF168: =IF(AD168="",0,AD168) -> 14080.768 | AG168: =IF(K168="",0,K168) -> 14344.045
A169: =IFERROR(IF(A168-1<1,"",A168-1),"") -> 131 | B169: =IF(IF(AND(B168>0,B168<$J$21),B168+1,0)=0,"",IF(AND(B168>0,B168<$J$21),B168+1,0)) -> 110 | C169: =IFERROR(IF(B169<=$J$21,DATE(YEAR(C168),MONTH(C168)+1,DAY(C168)),""),"") -> 49404 | D169: =IF(B169="","",L168) -> 887914.57 | E169: =IFERROR(D169*TAXA,"") -> 11454.098 | F169: =IFERROR(D169+E169,"") -> 899368.67 | G169: =IF($D$9>=B169,0,IFERROR(IF(C169="","",IF(SISTEMA_AMORTIZAÇÃO=PRICE_PRE,H169-E169, IF(SISTEMA_AMORTIZAÇÃO=SAC_PRE,D169/A169, IF(SISTEMA_AMORTIZAÇÃO=SAC_POS,D169/A169,)))),"")) -> 2626.6701 | H169: =IF($D$9>=B169,0,IF(D169="","", IF(SISTEMA_AMORTIZAÇÃO=PRICE_PRE,(PMT(TAXA,A169,$D169,)*-1), IF(SISTEMA_AMORTIZAÇÃO=SAC_POS,(D169/A169)+(D169*TAXA))))) -> 14080.768 | I169: =IFERROR(D169*$K$32,"") -> 151.83339 | J169: =IF(B169="","",IF(L168="","",IF(L168=0,"",$K$33*$J$17))) -> 111 | K169: =IFERROR(SUM(J169+I169+H169),"") -> 14343.601 | L169: =IFERROR(D169-G169,"") -> 885287.9 | Q169: =IFERROR(G169*$Q$44,0) -> 78.800102 | R169: =IF($B169<=$J$21,C169-C168,) -> 31 | S169: 365 | AC169: 3300 | AD169: =IF(H169="",0,H169) -> 14080.768 | AE169: =IF(C169="",0,C169) -> 49404 | AF169: =IF(AD169="",0,AD169) -> 14080.768 | AG169: =IF(K169="",0,K169) -> 14343.601
